Workbook

Sheet MACRO+watchlist+notes
A4: WATCHLIST | B4: top | C4: Debt | D4: 10yM | E4: d% change | G4: Region | H4: 10yM | I4: Indices | J4: 10yM | L4: Commodities | M4: 10yM | P4: Industries | Q4: 10yM | T4: Style | U4: 10yM | X4: Risk
B5: RK LOGO | C5: chart10y | D5: price | G5: chart10y | J5: price | K5: ch | L5: chart10y | P5: chart10y | T5: chart10y | X5: chart10y,M | Z5: port% | AA5: ticker | AB5: name | AC5: sector | AD5: industry | AE5: mkt cap | AF5: price | AG5: daily % change | AH5: 1m insider buying | AI5: 6m insider buying | AJ5: # of insiders | AK5: 6m val | AL5: % to val blend | AM5: % to 52w hi | AN5: % from 52w Lo | AO5: revs | AP5: s/p | AQ5: ebitda/ev | AR5: tb/p | AS5: b/p | AT5: e/p | AU5: cfo/p | AV5: sfcf/p | AW5: ncf/p | AX5: div/p | AY5: cash/p | AZ5: ncash/p | BA5: nn/p | BB5: asset/p | BC5: retear/mc | BD5: revs/debt | BE5: mc/ev
B6: DASH | C6: US Nom 5y/10y | G6: Vang US Stock Market | I6: S&P 500 | L6: Oil WTI | P6: Retail | T6: Russell1000 | X6: VIX
B7: Debt | C7: US Real 5y/10y | G7: S&P | I7: Dow | L7: Oil Brent | P7: Homebuilders | T7: Russell 2000 | X7: NYSE New Highs/Low
B8: Regin | C8: US 1-30y Treasuries | G8: All-World ex-US | I8: NASDAQ | L8: Natural Gas | P8: Homeconstruction | T8: Russell 3000 | X8: NYSE AD Line
B9: Indices | C9: US <1y Treasuries | G9: EAFE | I9: NASDAQ 100 QQQ | L9: Gold | P9: Consumer Goods | T9: S&P 500 | X9: NASDAQ AD Line
B10: Commodities | C10: US 1-3y Treasuries | G10: International | I10: Wilshire 5000 | L10: Silver | P10: Gaming | T10: S&P 500 =wght | X10: NYSE MCClellan Oscilator
B11: Industry | C11: US 7-10y Treasuries | G11: International SmallCap | I11: NYSE Composite | L11: Copper | P11: Aero & Defense | T11: S&P 400 | X11: NASDAQ McClellan
B12: Style | C12: US 20+y Treasuries | G12: Developed Markets | I12: Euronext 100 | L12: Palladium | P12: DJ Transports | T12: S&P 600 | X12: Put-Call
B13: risk | C13: US TIPS | G13: Emerging Mkts 1 | I13: Germany DAX | L13: Platinum | P13: Shipping | T13: Cambria Tall | X13: US 1-3y Treasuries
B14: RK Portfolio | C14: US Bond Market | G14: Emerging Mkts 2 | I14: London FTSE 100 | L14: Zinc | P14: Environmental Services | T14: S&P Dividend | X14: US 20+y Treasuries
B15: RK Buy | C15: Corp ST Bond | G15: Emerging SmallCap 1 | I15: France CAC 40 | L15: Aluminum | P15: US Technology | T15: MSCI US Momentum | X15: US Corp Bonds Junk
B16: RK Sell | C16: Corp MT Bond | G16: Emerging SmallCap 2 | I16: Japan Nikkei 225 | L16: Wheat US | P16: computer Software | T16: Cambria Momentum | X16: Japan
B17: Pulse | C17: Corp LT Bond | G17: Europe | I17: Hong King Hang Seng | L17: Corn US | P17: Internet | T17: S&P 500 Value | X17: *Naturl Resources No
... B19: Ind Filter | C19: US Corp | G19: Pacific ex-Japan | I19: Australia ASX 200 | L19: Sugar US | P19: Innovation | T19: S&P 600 Value | X19: Gold Miners
C20: US Corp | G20: BRIC | I20: Canada TSX | L20: Coffee US | P20: China Internet | T20: Russell 1000 Value | X20: Oil WTI
C21: EM Loc | G21: Latin 40 | I21: Energy | L21: Cotton US | P21: Semis | T21: Russell Midcp Value | X21: O&G E&S
G22: Japan | I22: Materials | L22: Cocoa US | P22: Robotics | T22: Russell 2000 Value | X22: Transocean
G23: China | I23: Industrials | L23: Live Cattle | P23: Cyber Security | T23: Towle | X23: Baytex
G24: Brazil | I24: Consumer Discretionary | L24: Lumber | P24: Biotech Nasdaq | T24: O'sh Small | X24: Rare Earths
G25: South Korea | I25: Information Technology | L25: Natural Resources | P25: Biotech General | T25: O'sh Mkt Lds Value | X25: Teck
G26: Taiwan | I26: Health Care | L26: O&G E&P | T26: Hussman Str Growth | X26: Alcoa
X27: Freeport-McMoRan
X28: Sibanye Stillwater
X29: Gooduear
X30: Ryder
X31: Robert Half
X32: Blockchain
X33: Bitcoin
X34: Momentum
X35: Collectors Universe
X36: QQQ
X37: Tesla
X38: Netflix
... X51: Hussman

Sheet Sheet39
A1: Financial Ratio | B1: FY2023 | C1: FY2022 | D1: Formula | E1: Purpose
A2: Liquidity Ratios
A3: Current Ratio | B3: 2.1x | C3: 1.8x | D3: Current Assets / Current Liabilities | E3: Measures the ability to pay short-term obligations with short-term assets
A4: Quick Ratio(Acid-Test Ratio) | B4: 1.5x | C4: 1.3x | D4: (Current Assets - Inventory) / Current Liabilities | E4: Similar to the current ratio but excludes inventory, providing a stricter assessment of liquidity.
A5: Cash Ratio | D5: Formula: Cash + Cash Equivalents/Current Liabilities | E5: Measures the company's ability to cover short-term liabilities with cash and cash equivalents.
A6: Leverage/Solvency Ratios
A7: Interest Coverage Ratio: | D7: Formula: Operating Income/Interest Expense | E7: Purpose: Assesses how easily a company can pay interest on its outstanding debt.
A8: Debt Ratio: | D8: Formula: Total Debt/Total Assets | E8: Purpose: Measures the percentage of assets financed by debt.
A9: Debt to Equity Ratio | B9: 0.6x | C9: 0.7x | D9: Total Debt / Total Equity
A10: Debt Service Coverage Ratio | B10: 1.8x | C10: 1.6x | D10: Net Operating Income / Total Debt Service
A11: Profitability Ratios
A12: Gross Margin | B12: 0.45 | C12: 0.43 | D12: Gross Profit / Revenue
A13: Net Profit Margin | B13: 0.1 | C13: 0.09 | D13: Net Income / Revenue
A14: Efficiency Ratios
A15: Gross Profit Margin: | D15: (Gross Profit/Revenue)×100
A16: Operating Profit Margin: | D16: (Operating Income/Revenue)×100
A17: Net Profit Margin: | D17: (Net Income/Revenue)×100 | E17: Indicates the percentage of revenue that remains as profit after all expenses.
A18: Return on Assets (ROA): | D18: (Net Income/Total Assets)×100 | E18: Measures how effectively a company uses its assets to generate profit.
A19: Return on Equity (ROE): | D19: (Net Income/Shareholder’s Equity)×100 | E19: Indicates the return generated on shareholders' equity.
A20: Efficiency Ratios
A21: Asset Turnover Ratio: | D21: Revenue/Total Assets | E21: Purpose: Shows how efficiently a company uses its assets to generate revenue.
A22: Inventory Turnover Ratio: | D22: Cost of Goods Sold/Average Inventory | E22: Purpose: Indicates how often inventory is sold and replaced over a period.
A23: Receivables Turnover Ratio: | D23: Net Credit Sales/Average Accounts Receivable | E23: Purpose: Measures how efficiently a company collects receivables.
A24: Payables Turnover Ratio: | D24: Cost of Goods Sold/Average Accounts Payable | E24: Formula: Cost of Goods Sold/Average Accounts Payable
A25: CASH FLOWS
A26: Operating Cash Flow (OCF) | D26: Net Income+Non-Cash Expenses+Changes in Working Capital | E26: Purpose: OCF indicates the cash generated by the company’s core business operations. It’s crucial to determine whether a company can generate sufficient cash from its regular operations to sustain its business. | F26: Key Metric: Compare OCF to net income. Ideally, OCF should consistently exceed net income, indicating that earnings are backed by real cash, not just accounting profits. | G26: Consistency: Look for companies with a stable or growing OCF over multiple periods. This suggests strong, recurring cash generation from business operations.
A27: Free Cash Flow (FCF) | D27: Operating Cash Flow−Capital Expenditures | E27: Purpose: FCF is the cash available after capital expenditures (CapEx) and is essential for understanding how much cash the company has to return to shareholders (through dividends or buybacks), reduce debt, or reinvest in the business.
A28: Cash Flow from Investing Activities | D28: Proceeds from Sale of PPE−Purchase of PPE+Proceeds from Sale of Investments−Purchase of Investments±Other Investing Activities | F28: CapEx: High and consistent CapEx may indicate ongoing investments in growth, but it can also consume significant cash. It’s important to assess whether these investments are translating into future revenue and profit growth.Asset Sales: Frequent or significant asset sales could be a red flag, suggesting the company is selling off parts of its business to generate cash.
A29: Cash Flow from Financing Activities | D29: Proceeds from Borrowing−Repayment of Debt+Proceeds from Issuing Stock−Repurchase of Stock−Dividends Paid | E29: Purpose: This section shows cash used in or generated by the company’s investment activities, such as purchasing assets, selling assets, or acquiring other businesses.
A30: Cash Conversion Cycle (CCC) | D30: Days Inventory Outstanding (DIO)+Days Sales Outstanding (DSO)−Days Payable Outstanding (DPO) | E30: Purpose: CCC measures the time it takes for a company to convert its investments in inventory and other resources into cash flows from sales. A shorter CCC indicates efficient management of working capital.
A31: Comparative Analysis | E31: Compare the cash flow metrics of the company with its industry peers. This provides context on whether the company is performing better or worse than its competitors. | F31: Key Insights: Look at industry norms for OCF, FCF, and CapEx intensity. Companies outperforming their peers in these areas may represent solid investment opportunities.
A32: Trend Analysis | E32: Key Metric: A decreasing CCC over time suggests improving efficiency in managing inventory, receivables, and payables. | F32: Key Insights: A company with consistently improving cash flows is generally a better investment candidate than one with erratic or declining cash flows.
A33: Scenario and Sensitivity Analysis | E33: Purpose: Conduct scenario analysis to assess how changes in key assumptions (like revenue growth, margins, or CapEx) impact cash flows. | F33: Key Insights: Sensitivity analysis helps in understanding the robustness of the company’s cash flows under various economic or business conditions.
A34: Stock Market Ratios
A38: Earnings Per Share (EPS):
A40: Formula: Net Income/Number of Outstanding Shares
A41: Purpose: Indicates the portion of a company's profit allocated to each outstanding share of common stock.
A43: Price to Earnings Ratio (P/E Ratio):
A45: Formula: Market Price per Share/Earnings per Share (EPS)
A46: Purpose: Measures the market value per share relative to the earnings per share.
A48: Dividend Yield:
A50: Formula: Annual Dividends per Share/Price per Share
A51: Purpose: Shows how much a company pays out in dividends each year relative to its stock price.
A53: Price to Book Ratio (P/B Ratio):
A55: Formula: Market Price per Share/Book Value per Share
... A78: Summary Indicators: Include key metrics at the top of the dashboard, such as overall profitability or liquidity status, to provide an at-a-glance overview of the company's financial health.

Sheet Finding Value
A1: How to approach finding value
A2: Screener
A3: Scour the holdings from the best growth ETFs.
A4: You'll want to narrow the field using financial metrics such as return on assets, earnings per share growth, higher price-to-sales and price-to-cash-flow ratios.
A5: The fund's fact sheet is an excellent place to find basic information such as its top 10 holdings, top sector weightings, and fund characteristics.
A6: learning about the business model, its financial situation and anything else that might influence its share price in the future.
A7: Think like a partner

Sheet Screener
A1: FALSE | B1: ticker | C1: IFTRUE(B1,) | D1: google finance | M1: Technical Analysis | O1: Fundamental | Q1: Basic Info | S1: ?, check RK
A2: INPUT: | B2: GE | D2: change % | E2: =IFERROR(__xludf.DUMMYFUNCTION("GOOGLEFINANCE(B2,""changepct"")"),-1.09) -> -1.09 | M2: Price | O2: revs | Q2: CIK | S2: <1 week
A3: CIK | D3: mkt cap | E3: =IFERROR(__xludf.DUMMYFUNCTION("GOOGLEFINANCE(B2,""marketcap"")"),3.03195451295E11) -> 303195451295 | M3: mkt cap | O3: s/p | Q3: Sector | S3: 1-2w
A4: Sector | D4: %to52w hi | M4: price | O4: ebitda/ev | Q4: company | S4: 2-4w
A5: company | D5: %from52low | M5: daily % change | O5: tb/p | Q5: sector | S5: val
A6: sector | D6: p/e | E6: =IFERROR(__xludf.DUMMYFUNCTION("GOOGLEFINANCE(B2,""pe"")"),38.28) -> 38.28 | M6: % to 52w hi | O6: b/p | Q6: industry | S6: 6m val
A7: industry | D7: e/p | E7: =(1/E6) -> 0.026123302 | M7: % from 52w Lo | O7: e/p | S7: % to val blend
A8: P/e No Growth(0%) | B8: 11 | D8: EPS | E8: =IFERROR(__xludf.DUMMYFUNCTION("GOOGLEFINANCE(B2, ""eps"")"),7.51) -> 7.51 | M8: 52range | O8: cfo/p
A9: Growth Rate???? | B9: 8.5 | D9: data delay | E9: =IFERROR(__xludf.DUMMYFUNCTION("GOOGLEFINANCE(B2,""datadelay"")"),0.0) -> 0 | M9: return1w | O9: sfcf/p
A10: 2 g: | B10: =2*(B9) -> 17 | D10: 52hi | E10: =IFERROR(__xludf.DUMMYFUNCTION("GOOGLEFINANCE(B2,""high52"")"),316.67) -> 316.67 | M10: return4w | O10: ncf/p
A11: Avg Yield AAA bond: | B11: 4.64 | D11: 52lo | E11: =IFERROR(__xludf.DUMMYFUNCTION("GOOGLEFINANCE(B2,""low52"")"),159.36) -> 159.36 | M11: return13w | O11: div/p
A12: Y=Moodys Seasoned AAA | B12: 4.77 | D12: 52range | E12: googlefinance(B2, | M12: return52w | O12: cash/p
B13: =11+17 -> 28 | D13: beta | E13: =IFERROR(__xludf.DUMMYFUNCTION("GOOGLEFINANCE(B2,""beta"")"),1.56) -> 1.56 | M13: return156w | O13: ncash/p
B14: =(B7)*(B8+(2*(B9)))*(B11) -> 0 | D14: shares | E14: =IFERROR(__xludf.DUMMYFUNCTION("GOOGLEFINANCE(B2,""shares"")"),1.054814E9) -> 1054814000 | M14: return260w | O14: nn/p
D15: data delay | E15: =IFERROR(__xludf.DUMMYFUNCTION("GOOGLEFINANCE(B2,""datadelay"")"),0.0) -> 0 | M15: distrib yield | O15: asset/p
D16: close yesterday | E16: =IFERROR(__xludf.DUMMYFUNCTION("GOOGLEFINANCE(B2,""closeyest"")"),290.62) -> 290.62 | M16: ytdreturn | O16: retear/mc
D17: price | E17: =IFERROR(__xludf.DUMMYFUNCTION("GOOGLEFINANCE(B2,""price"")"),287.44) -> 287.44 | O17: revs/debt
O18: mc/ev
O19: Insider Buying
O20: 1m insider buying
O21: 6m insider buying
O22: # of insiders
O23: 65%mos

Sheet Screener beta
B1: scrape on cgi script | C1: data.sec.gov | D1: https://www.sec.gov/cgi-bin/browse-edgar?action=getcurrent | E1: SEC Meetings
B2: Build a Screener Resources | C2: Dividendology Stock Watch search
A5: var index = 1; [].forEach.call(document.getElementsByTagName("table"), function(elements) { console.log("Index: " + index++, elements); }); | B5: Copy and paste the following code into the console to get indexes of all tables:
A6: var index = 1; [].forEach.call(document.querySelectorAll("ul,ol"), function(elements) { console.log("Index: " + index++, elements); }); | B6: If you are looking for all lists’ indexes instead, you need to get all elements with tag <ul> or <ol>. The following code may help you:
A10: =IFERROR(__xludf.DUMMYFUNCTION("IMPORTHTML(""https://finviz.com/quote.ashx?t=EXPR&ty=c&ta=1&p=d"",""table"",""10"")"),"Loading...") -> Loading...
A24: Currency
A25: =IFERROR(__xludf.DUMMYFUNCTION("IMPORTHTML(""https://finance.yahoo.com/currencies"",""table"",1)"),"Loading...") -> Loading...
B54: Stock Ticker | E54: Current Price | G54: =IFERROR(__xludf.DUMMYFUNCTION("SPARKLINE(GOOGLEFINANCE(B56,""price"",today()-700,today()))"),"") | M54: #ERROR!
E55: Volume | M55: =IFERROR(__xludf.DUMMYFUNCTION("IMPORTHTML(""https://www.sec.gov/cgi-bin/browse-edgar?action=getcurrent"",""table"",""7"")"),"Loading...") -> Loading...
B56: AAPL | E56: Day's $ change
E57: Day's % change
E58: 52hi
E59: 52lo
E60: yesterday close
A62: =IFERROR(__xludf.DUMMYFUNCTION("IMPORTHTML(""https://finviz.com/quote.ashx?t=""&B56,""table"",""10"")"),"Loading...") -> Loading...
A75: You can remove the asterisk by using the substitute formula. I use this formula in many of my portfolio trackers. Go back and view some of my portfolio tracker videos to see how I use this.
A79: Ticker | B79: Name | C79: Price | D79: 555 | E79: Day's change | F79: Day's change % | G79: Dividend | H79: 12 month return | I79: Industry
A80: EXPR | B80: =IFERROR(__xludf.DUMMYFUNCTION("GOOGLEFINANCE(A80,""name"")"),"#N/A") -> #N/A | C80: =IFERROR(__xludf.DUMMYFUNCTION("GOOGLEFINANCE(A80,""price"")"),"#N/A") -> #N/A | D80: =IFERROR(__xludf.DUMMYFUNCTION("(SPARKLINE(index(GOOGLEFINANCE(A80,""Price"",today()-$D$79,today()),,2),{""charttype"",""line"";""color"",""purple""}))"),"#N/A") -> #N/A | E80: =IFERROR(__xludf.DUMMYFUNCTION("Googlefinance(A80,""change"")"),"#N/A") -> #N/A | F80: =IFERROR(__xludf.DUMMYFUNCTION("Googlefinance(A80,""changepct"")/100"),"#N/A") -> #N/A | G80: =IFERROR(__xludf.DUMMYFUNCTION("if($A$80="""","""",substitute(SUBSTITUTE(index(importhtml(""http://finviz.com/quote.ashx?t=""&$A$80,""table"",10),7,2),""*"",""""),""-"",""0.00""))"),"Loading...") -> Loading... | H80: =IFERROR(__xludf.DUMMYFUNCTION("(GOOGLEFINANCE(A80,""price"")/index(GOOGLEFINANCE(A2,""price"", datevalue(today()-365)),2,2)-1)"),"#N/A") -> #N/A | I80: =if(O2="","",Left(O2, Search(" |",O2))) | K80: =IFERROR(__xludf.DUMMYFUNCTION("if(A2="""","""",IFERROR(substitute(Index(IMPORTHTML(""https://finviz.com/quote.ashx?t=""&A2,""Table"",8),2,1),""*"",""""),""-""))"),"")
H81: outerHTML | I81: <span class="Fw(600)">Technology</span>
H82: selector | I82: #Col1-0-Profile-Proxy > section > div.asset-profile-container > div > div > p.D\(ib\).Va\(t\) > span:nth-child(2)
H83: xpath | I83: //*[@id="Col1-0-Profile-Proxy"]/section/div[1]/div/div/p[2]/span[2]
A84: What it do? | H84: full. xpath | I84: /html/body/div[1]/div/div/div[1]/div/div[3]/div[1]/div/div[1]/section/div[1]/div/div/p[2]/span[2]
A85: =IFERROR(__xludf.DUMMYFUNCTION("IMPORTHTML(""https://finviz.com/quote.ashx?t=""&A80,""table"",""11"")"),"Loading...") -> Loading... | I85: =IFERROR(__xludf.DUMMYFUNCTION("IMPORTXML(""http://finance.yahoo.com/quote/AAPL/profile?p=AAPL"",""//section/div[1]/div/div/p[2]/span[2]"")"),"#N/A") -> #N/A
E86: =if(O2="","",Left(O2, Search(" |",O2))) | I86: ("//a/@href")
I87: "https://finviz.com/quote.ashx?t="&B56,"table","10")
I88: <div class="quote-links">
I89: <div>
I90: <a href="screener.ashx?v=111&amp;f=sec_consumercyclical" class="tab-link">Consumer Cyclical</a>
I91: <span class="text-muted-3">•</span>
I92: <a href="screener.ashx?v=111&amp;f=ind_apparelretail" class="tab-link">Apparel Retail</a>
I93: <span class="text-muted-3">•</span>
I94: <a href="screener.ashx?v=111&amp;f=geo_usa" class="tab-link">USA</a>
I95: <span class="text-muted-3">•</span>
I96: <a href="screener.ashx?v=111&amp;f=exch_nyse" class="tab-link">NYSE</a>
I97: </div>
I98: <div>
... I110: </div>

Sheet AAA
A1: TICKER | B1: CIK | C1: Company | D1: Index | E1: price | H1: Sector | I1: Industry | J1: 1 | K1: DIVIDEND | L1: mkt cap | M1: Beta | N1: INDEX&MATCH
A2: seci | B2: 925661 | C2: SECTOR 10 Inc | E2: 0.01 | K2: =IFERROR(__xludf.DUMMYFUNCTION("if(A2="""","""",substitute(SUBSTITUTE(index(importhtml(""http://finviz.com/quote.ashx?t=""&A2,""table"",10),7,2),""*"",""""),""-"",""0.00""))"),"Loading...") -> Loading... | L2: 1530 | M2: #N/A
A3: bant | B3: 1704795 | C3: Bantec Inc | E3: 0.01 | K3: =IFERROR(__xludf.DUMMYFUNCTION("if(A3="""","""",substitute(SUBSTITUTE(index(importhtml(""http://finviz.com/quote.ashx?t=""&A3,""table"",10),7,2),""*"",""""),""-"",""0.00""))"),"Loading...") -> Loading... | L3: 48960 | M3: 5.31
A4: unam | B4: 100716 | C4: Unico American Corp | E4: 0.01 | K4: =IFERROR(__xludf.DUMMYFUNCTION("if(A4="""","""",substitute(SUBSTITUTE(index(importhtml(""http://finviz.com/quote.ashx?t=""&A4,""table"",10),7,2),""*"",""""),""-"",""0.00""))"),"Loading...") -> Loading... | L4: 53050 | M4: 0.07
A5: kspn | B5: 795212 | C5: Kaspien Holdings Inc | E5: 0.01 | K5: =IFERROR(__xludf.DUMMYFUNCTION("if(A5="""","""",substitute(SUBSTITUTE(index(importhtml(""http://finviz.com/quote.ashx?t=""&A5,""table"",10),7,2),""*"",""""),""-"",""0.00""))"),"Loading...") -> Loading... | L5: 59640 | M5: 0.51
A6: pssr | B6: 225628 | C6: Passur Aerospace Inc | E6: 0.01 | K6: =IFERROR(__xludf.DUMMYFUNCTION("if(A6="""","""",substitute(SUBSTITUTE(index(importhtml(""http://finviz.com/quote.ashx?t=""&A6,""table"",10),7,2),""*"",""""),""-"",""0.00""))"),"Loading...") -> Loading... | L6: 77120 | M6: #N/A
A7: slch | B7: 1077319 | C7: spotlight Capital Holdings | E7: 0.01 | K7: =IFERROR(__xludf.DUMMYFUNCTION("if(A7="""","""",substitute(SUBSTITUTE(index(importhtml(""http://finviz.com/quote.ashx?t=""&A7,""table"",10),7,2),""*"",""""),""-"",""0.00""))"),"Loading...") -> Loading... | L7: 86810 | M7: 0.59
A8: spowf | B8: 1227282 | C8: Strata Power Corp | E8: 0.01 | K8: =IFERROR(__xludf.DUMMYFUNCTION("if(A8="""","""",substitute(SUBSTITUTE(index(importhtml(""http://finviz.com/quote.ashx?t=""&A8,""table"",10),7,2),""*"",""""),""-"",""0.00""))"),"Loading...") -> Loading... | L8: 120510 | M8: #N/A
A9: bbig | B9: 1717556 | C9: Vinco Ventures Inc | E9: 0.01 | K9: =IFERROR(__xludf.DUMMYFUNCTION("if(A9="""","""",substitute(SUBSTITUTE(index(importhtml(""http://finviz.com/quote.ashx?t=""&A9,""table"",10),7,2),""*"",""""),""-"",""0.00""))"),"Loading...") -> Loading... | L9: 124489 | M9: 0.18
A10: cwnof | B10: 1145898 | C10: Chineseworldnet.Com Inc | E10: 0.01 | K10: =IFERROR(__xludf.DUMMYFUNCTION("if(A10="""","""",substitute(SUBSTITUTE(index(importhtml(""http://finviz.com/quote.ashx?t=""&A10,""table"",10),7,2),""*"",""""),""-"",""0.00""))"),"Loading...") -> Loading... | L10: 124830 | M10: 6.55
A11: rgmp | B11: 1716324 | C11: Regnum Corp | E11: 0.01 | K11: =IFERROR(__xludf.DUMMYFUNCTION("if(A11="""","""",substitute(SUBSTITUTE(index(importhtml(""http://finviz.com/quote.ashx?t=""&A11,""table"",10),7,2),""*"",""""),""-"",""0.00""))"),"Loading...") -> Loading... | L11: 135410 | M11: 6.36
A12: ltryw | B12: 1673481 | C12: Lottery.com | E12: 0.01 | K12: =IFERROR(__xludf.DUMMYFUNCTION("if(A12="""","""",substitute(SUBSTITUTE(index(importhtml(""http://finviz.com/quote.ashx?t=""&A12,""table"",10),7,2),""*"",""""),""-"",""0.00""))"),"#N/A") -> #N/A | L12: 154382 | M12: 4.5
A13: mmnt | B13: 1653876 | C13: Momentous Holdings Corp | E13: 0.01 | K13: =IFERROR(__xludf.DUMMYFUNCTION("if(A13="""","""",substitute(SUBSTITUTE(index(importhtml(""http://finviz.com/quote.ashx?t=""&A13,""table"",10),7,2),""*"",""""),""-"",""0.00""))"),"Loading...") -> Loading... | L13: 168890 | M13: #N/A
A14: fdmsf | B14: 1668987 | C14: Fandifi Technology Corp | E14: 0.01 | K14: =IFERROR(__xludf.DUMMYFUNCTION("if(A14="""","""",substitute(SUBSTITUTE(index(importhtml(""http://finviz.com/quote.ashx?t=""&A14,""table"",10),7,2),""*"",""""),""-"",""0.00""))"),"#N/A") -> #N/A | L14: 205264 | M14: 2.06
A15: gthr | B15: 1017110 | C15: GeneThera Inc | E15: 0.01 | K15: =IFERROR(__xludf.DUMMYFUNCTION("if(A15="""","""",substitute(SUBSTITUTE(index(importhtml(""http://finviz.com/quote.ashx?t=""&A15,""table"",10),7,2),""*"",""""),""-"",""0.00""))"),"Loading...") -> Loading... | L15: 212040 | M15: -0.26
A16: sgmd | B16: 919175 | C16: Sugarmade Inc | E16: 0.01 | K16: =IFERROR(__xludf.DUMMYFUNCTION("if(A16="""","""",substitute(SUBSTITUTE(index(importhtml(""http://finviz.com/quote.ashx?t=""&A16,""table"",10),7,2),""*"",""""),""-"",""0.00""))"),"Loading...") -> Loading... | L16: 230735 | M16: 0.21
A17: wmc | B17: 1465885 | C17: Westmount Minerals Corp | E17: 0.01 | K17: =IFERROR(__xludf.DUMMYFUNCTION("if(A17="""","""",substitute(SUBSTITUTE(index(importhtml(""http://finviz.com/quote.ashx?t=""&A17,""table"",10),7,2),""*"",""""),""-"",""0.00""))"),"Loading...") -> Loading... | L17: 250340 | M17: #N/A
A18: tdrk | B18: 1282496 | C18: Tiderock Companies Inc | E18: 0.01 | K18: =IFERROR(__xludf.DUMMYFUNCTION("if(A18="""","""",substitute(SUBSTITUTE(index(importhtml(""http://finviz.com/quote.ashx?t=""&A18,""table"",10),7,2),""*"",""""),""-"",""0.00""))"),"Loading...") -> Loading... | L18: 263896 | M18: -4.25
A19: blis | B19: 1703625 | C19: Treasure & Shipwreck Recovery Inc | E19: 0.01 | K19: =IFERROR(__xludf.DUMMYFUNCTION("if(A19="""","""",substitute(SUBSTITUTE(index(importhtml(""http://finviz.com/quote.ashx?t=""&A19,""table"",10),7,2),""*"",""""),""-"",""0.00""))"),"Loading...") -> Loading... | L19: 276760 | M19: 49.62
A20: rad | B20: 84129 | C20: Radial Research Corp | E20: 0.01 | K20: =IFERROR(__xludf.DUMMYFUNCTION("if(A20="""","""",substitute(SUBSTITUTE(index(importhtml(""http://finviz.com/quote.ashx?t=""&A20,""table"",10),7,2),""*"",""""),""-"",""0.00""))"),"Loading...") -> Loading... | L20: 278380 | M20: #N/A
A21: apsi | B21: 1553264 | C21: Aqua Power Systems Inc | E21: 0.01 | K21: =IFERROR(__xludf.DUMMYFUNCTION("if(A21="""","""",substitute(SUBSTITUTE(index(importhtml(""http://finviz.com/quote.ashx?t=""&A21,""table"",10),7,2),""*"",""""),""-"",""0.00""))"),"Loading...") -> Loading... | L21: 281868 | M21: 0.7
A22: rahgf | B22: 1611852 | C22: Roan Holdings Group Co Ltd | E22: 0.01 | K22: =IFERROR(__xludf.DUMMYFUNCTION("if(A22="""","""",substitute(SUBSTITUTE(index(importhtml(""http://finviz.com/quote.ashx?t=""&A22,""table"",10),7,2),""*"",""""),""-"",""0.00""))"),"Loading...") -> Loading... | L22: 296370 | M22: -1.71
A23: scps | B23: 1772028 | C23: Scopus Biopharma Inc | E23: 0.01 | K23: =IFERROR(__xludf.DUMMYFUNCTION("if(A23="""","""",substitute(SUBSTITUTE(index(importhtml(""http://finviz.com/quote.ashx?t=""&A23,""table"",10),7,2),""*"",""""),""-"",""0.00""))"),"Loading...") -> Loading... | L23: 315630 | M23: 1.46
A24: sset | B24: 1561686 | C24: Starstream Entertainment Inc | E24: 0.01 | K24: =IFERROR(__xludf.DUMMYFUNCTION("if(A24="""","""",substitute(SUBSTITUTE(index(importhtml(""http://finviz.com/quote.ashx?t=""&A24,""table"",10),7,2),""*"",""""),""-"",""0.00""))"),"Loading...") -> Loading... | L24: 364026 | M24: -0.4
A25: cnbx | B25: 1343009 | C25: CNBX Pharmaceuticals Inc | E25: 0.01 | K25: =IFERROR(__xludf.DUMMYFUNCTION("if(A25="""","""",substitute(SUBSTITUTE(index(importhtml(""http://finviz.com/quote.ashx?t=""&A25,""table"",10),7,2),""*"",""""),""-"",""0.00""))"),"Loading...") -> Loading... | L25: 378107 | M25: 0.68
A26: mgi | B26: 1273931 | C26: Magnum Goldcorp Inc | E26: 0.01 | K26: =IFERROR(__xludf.DUMMYFUNCTION("if(A26="""","""",substitute(SUBSTITUTE(index(importhtml(""http://finviz.com/quote.ashx?t=""&A26,""table"",10),7,2),""*"",""""),""-"",""0.00""))"),"Loading...") -> Loading... | L26: 386200 | M26: -5.5
A27: hgyn | B27: 1324759 | C27: Hong Yuan Holding Group | E27: 0.01 | K27: =IFERROR(__xludf.DUMMYFUNCTION("if(A27="""","""",substitute(SUBSTITUTE(index(importhtml(""http://finviz.com/quote.ashx?t=""&A27,""table"",10),7,2),""*"",""""),""-"",""0.00""))"),"Loading...") -> Loading... | L27: 388128 | M27: 2.58
A28: kmgh | B28: 1471302 | C28: Kemiao Garment Holding Group | E28: 0.01 | K28: =IFERROR(__xludf.DUMMYFUNCTION("if(A28="""","""",substitute(SUBSTITUTE(index(importhtml(""http://finviz.com/quote.ashx?t=""&A28,""table"",10),7,2),""*"",""""),""-"",""0.00""))"),"Loading...") -> Loading... | L28: 404640 | M28: 66.48
A29: ptoi | B29: 1381105 | C29: Plastic2Oil Inc | E29: 0.01 | K29: =IFERROR(__xludf.DUMMYFUNCTION("if(A29="""","""",substitute(SUBSTITUTE(index(importhtml(""http://finviz.com/quote.ashx?t=""&A29,""table"",10),7,2),""*"",""""),""-"",""0.00""))"),"Loading...") -> Loading... | L29: 426914 | M29: -0.06
A30: trirf | B30: 1819876 | C30: Triterras Inc | E30: 0.01 | K30: =IFERROR(__xludf.DUMMYFUNCTION("if(A30="""","""",substitute(SUBSTITUTE(index(importhtml(""http://finviz.com/quote.ashx?t=""&A30,""table"",10),7,2),""*"",""""),""-"",""0.00""))"),"Loading...") -> Loading... | L30: 459144 | M30: 0.86
A31: mccx | B31: 1535079 | C31: MCX Technologies Corp | E31: 0.01 | K31: =IFERROR(__xludf.DUMMYFUNCTION("if(A31="""","""",substitute(SUBSTITUTE(index(importhtml(""http://finviz.com/quote.ashx?t=""&A31,""table"",10),7,2),""*"",""""),""-"",""0.00""))"),"Loading...") -> Loading... | L31: 510650 | M31: #N/A
A32: duuo | B32: 1635136 | C32: Duo World Inc | E32: 0.01 | K32: =IFERROR(__xludf.DUMMYFUNCTION("if(A32="""","""",substitute(SUBSTITUTE(index(importhtml(""http://finviz.com/quote.ashx?t=""&A32,""table"",10),7,2),""*"",""""),""-"",""0.00""))"),"Loading...") -> Loading... | L32: 530260 | M32: 1.05
A33: wddd | B33: 1961 | C33: Worlds Inc | E33: 0.01 | K33: =IFERROR(__xludf.DUMMYFUNCTION("if(A33="""","""",substitute(SUBSTITUTE(index(importhtml(""http://finviz.com/quote.ashx?t=""&A33,""table"",10),7,2),""*"",""""),""-"",""0.00""))"),"Loading...") -> Loading... | L33: 537144 | M33: 0.8
A34: gspt | B34: 1076262 | C34: Super Fresh Foods Inc | E34: 0.01 | K34: =IFERROR(__xludf.DUMMYFUNCTION("if(A34="""","""",substitute(SUBSTITUTE(index(importhtml(""http://finviz.com/quote.ashx?t=""&A34,""table"",10),7,2),""*"",""""),""-"",""0.00""))"),"Loading...") -> Loading... | L34: 573581 | M34: 2.42
A35: crtdw | B35: 1357671 | C35: CREATD | E35: 0.01 | K35: =IFERROR(__xludf.DUMMYFUNCTION("if(A35="""","""",substitute(SUBSTITUTE(index(importhtml(""http://finviz.com/quote.ashx?t=""&A35,""table"",10),7,2),""*"",""""),""-"",""0.00""))"),"Loading...") -> Loading... | L35: 587766 | M35: 4.22
A36: mmmw | B36: 1117228 | C36: Mass Megawatts Inc | E36: 0.01 | K36: =IFERROR(__xludf.DUMMYFUNCTION("if(A36="""","""",substitute(SUBSTITUTE(index(importhtml(""http://finviz.com/quote.ashx?t=""&A36,""table"",10),7,2),""*"",""""),""-"",""0.00""))"),"Loading...") -> Loading... | L36: 629781 | M36: 0.22
A37: revbw | B37: 1810560 | C37: Revelation Biosciences Inc | E37: 0.01 | K37: =IFERROR(__xludf.DUMMYFUNCTION("if(A37="""","""",substitute(SUBSTITUTE(index(importhtml(""http://finviz.com/quote.ashx?t=""&A37,""table"",10),7,2),""*"",""""),""-"",""0.00""))"),"Loading...") -> Loading... | L37: 639181 | M37: 1.88
A38: acmb | B38: 1598323 | C38: Agro Capital Management Corp | E38: 0.01 | K38: =IFERROR(__xludf.DUMMYFUNCTION("if(A38="""","""",substitute(SUBSTITUTE(index(importhtml(""http://finviz.com/quote.ashx?t=""&A38,""table"",10),7,2),""*"",""""),""-"",""0.00""))"),"Loading...") -> Loading... | L38: 658030 | M38: 2.89
A39: nuvi | B39: 1410708 | C39: Emo Capital Corp | E39: 0.01 | K39: =IFERROR(__xludf.DUMMYFUNCTION("if(A39="""","""",substitute(SUBSTITUTE(index(importhtml(""http://finviz.com/quote.ashx?t=""&A39,""table"",10),7,2),""*"",""""),""-"",""0.00""))"),"Loading...") -> Loading... | L39: 672320 | M39: -1.47
A40: mdl | B40: 1370496 | C40: Medallion Resources Ltd | E40: 0.01 | K40: =IFERROR(__xludf.DUMMYFUNCTION("if(A40="""","""",substitute(SUBSTITUTE(index(importhtml(""http://finviz.com/quote.ashx?t=""&A40,""table"",10),7,2),""*"",""""),""-"",""0.00""))"),"Loading...") -> Loading... | L40: 701939 | M40: 1.52
A41: mllof | B41: 1370496 | C41: Medallion Resources Ltd | E41: 0.01 | K41: =IFERROR(__xludf.DUMMYFUNCTION("if(A41="""","""",substitute(SUBSTITUTE(index(importhtml(""http://finviz.com/quote.ashx?t=""&A41,""table"",10),7,2),""*"",""""),""-"",""0.00""))"),"Loading...") -> Loading... | L41: 701939 | M41: 2.2
A42: tcbpw | B42: 1872812 | C42: TC BioPharm Ltd | E42: 0.01 | K42: =IFERROR(__xludf.DUMMYFUNCTION("if(A42="""","""",substitute(SUBSTITUTE(index(importhtml(""http://finviz.com/quote.ashx?t=""&A42,""table"",10),7,2),""*"",""""),""-"",""0.00""))"),"Loading...") -> Loading... | L42: 715432 | M42: #N/A
A43: laab | B43: 1584480 | C43: Startech Labs Inc | E43: 0.01 | K43: =IFERROR(__xludf.DUMMYFUNCTION("if(A43="""","""",substitute(SUBSTITUTE(index(importhtml(""http://finviz.com/quote.ashx?t=""&A43,""table"",10),7,2),""*"",""""),""-"",""0.00""))"),"Loading...") -> Loading... | L43: 758090 | M43: -0.28
A44: rgus | B44: 922330 | C44: REGI U S Inc | E44: 0.01 | K44: =IFERROR(__xludf.DUMMYFUNCTION("if(A44="""","""",substitute(SUBSTITUTE(index(importhtml(""http://finviz.com/quote.ashx?t=""&A44,""table"",10),7,2),""*"",""""),""-"",""0.00""))"),"Loading...") -> Loading... | L44: 761570 | M44: 0.5
A45: frzt | B45: 1485074 | C45: Freeze Tag Inc | E45: 0.01 | K45: =IFERROR(__xludf.DUMMYFUNCTION("if(A45="""","""",substitute(SUBSTITUTE(index(importhtml(""http://finviz.com/quote.ashx?t=""&A45,""table"",10),7,2),""*"",""""),""-"",""0.00""))"),"Loading...") -> Loading... | L45: 835375 | M45: 0.26
A46: psybf | B46: 1833371 | C46: Psybio Therapeutics Corp | E46: 0.01 | K46: =IFERROR(__xludf.DUMMYFUNCTION("if(A46="""","""",substitute(SUBSTITUTE(index(importhtml(""http://finviz.com/quote.ashx?t=""&A46,""table"",10),7,2),""*"",""""),""-"",""0.00""))"),"Loading...") -> Loading... | L46: 839270 | M46: #N/A
A47: nbco | B47: 1383637 | C47: Neon Bloom Inc | E47: 0.01 | K47: =IFERROR(__xludf.DUMMYFUNCTION("if(A47="""","""",substitute(SUBSTITUTE(index(importhtml(""http://finviz.com/quote.ashx?t=""&A47,""table"",10),7,2),""*"",""""),""-"",""0.00""))"),"Loading...") -> Loading... | L47: 899240 | M47: 2.91
A48: gkin | B48: 1509786 | C48: Guskin Gold Corp | E48: 0.01 | K48: =IFERROR(__xludf.DUMMYFUNCTION("if(A48="""","""",substitute(SUBSTITUTE(index(importhtml(""http://finviz.com/quote.ashx?t=""&A48,""table"",10),7,2),""*"",""""),""-"",""0.00""))"),"Loading...") -> Loading... | L48: 907105 | M48: 0.04
A49: luxff | B49: 1871928 | C49: Luxxfolio Holdings Inc | E49: 0.01 | K49: =IFERROR(__xludf.DUMMYFUNCTION("if(A49="""","""",substitute(SUBSTITUTE(index(importhtml(""http://finviz.com/quote.ashx?t=""&A49,""table"",10),7,2),""*"",""""),""-"",""0.00""))"),"Loading...") -> Loading... | L49: 975577 | M49: #N/A
A50: koan | B50: 897078 | C50: Resonate Blends Inc | E50: 0.01 | K50: =IFERROR(__xludf.DUMMYFUNCTION("if(A50="""","""",substitute(SUBSTITUTE(index(importhtml(""http://finviz.com/quote.ashx?t=""&A50,""table"",10),7,2),""*"",""""),""-"",""0.00""))"),"Loading...") -> Loading... | L50: 996170 | M50: 1.03
A51: trtk | B51: 1560905 | C51: TORtec Group Corp | E51: 0.01 | K51: =IFERROR(__xludf.DUMMYFUNCTION("if(A51="""","""",substitute(SUBSTITUTE(index(importhtml(""http://finviz.com/quote.ashx?t=""&A51,""table"",10),7,2),""*"",""""),""-"",""0.00""))"),"Loading...") -> Loading... | L51: 1010750 | M51: #N/A
A52: avpmf | B52: 1445467 | C52: Avrupa Minerals Ltd | E52: 0.01 | K52: =IFERROR(__xludf.DUMMYFUNCTION("if(A52="""","""",substitute(SUBSTITUTE(index(importhtml(""http://finviz.com/quote.ashx?t=""&A52,""table"",10),7,2),""*"",""""),""-"",""0.00""))"),"Loading...") -> Loading... | L52: 1064100 | M52: 3.64
A53: jksm | B53: 860543 | C53: Jacksam Corp | E53: 0.01 | K53: =IFERROR(__xludf.DUMMYFUNCTION("if(A53="""","""",substitute(SUBSTITUTE(index(importhtml(""http://finviz.com/quote.ashx?t=""&A53,""table"",10),7,2),""*"",""""),""-"",""0.00""))"),"Loading...") -> Loading... | L53: 1077260 | M53: -1.55
A54: hadv | B54: 1531477 | C54: Health Advance Inc | E54: 0.01 | K54: =IFERROR(__xludf.DUMMYFUNCTION("if(A54="""","""",substitute(SUBSTITUTE(index(importhtml(""http://finviz.com/quote.ashx?t=""&A54,""table"",10),7,2),""*"",""""),""-"",""0.00""))"),"Loading...") -> Loading... | L54: 1097090 | M54: 2.01
A55: gblx | B55: 1165320 | C55: GB Sciences Inc | E55: 0.01 | K55: =IFERROR(__xludf.DUMMYFUNCTION("if(A55="""","""",substitute(SUBSTITUTE(index(importhtml(""http://finviz.com/quote.ashx?t=""&A55,""table"",10),7,2),""*"",""""),""-"",""0.00""))"),"Loading...") -> Loading... | L55: 1120617 | M55: 0.3
A56: endv | B56: 1528172 | C56: Endonovo Therapeutics Inc | E56: 0.01 | K56: =IFERROR(__xludf.DUMMYFUNCTION("if(A56="""","""",substitute(SUBSTITUTE(index(importhtml(""http://finviz.com/quote.ashx?t=""&A56,""table"",10),7,2),""*"",""""),""-"",""0.00""))"),"Loading...") -> Loading... | L56: 1147506 | M56: -0.79
A57: nihk | B57: 1084475 | C57: Video River Networks, Inc. Common Stock | E57: 0.01 | K57: =IFERROR(__xludf.DUMMYFUNCTION("if(A57="""","""",substitute(SUBSTITUTE(index(importhtml(""http://finviz.com/quote.ashx?t=""&A57,""table"",10),7,2),""*"",""""),""-"",""0.00""))"),"Loading...") -> Loading... | L57: 1197513 | M57: 1.73
A58: chs | B58: 897429 | C58: Comprehensive Healthcare Systems Inc | E58: 0.01 | K58: =IFERROR(__xludf.DUMMYFUNCTION("if(A58="""","""",substitute(SUBSTITUTE(index(importhtml(""http://finviz.com/quote.ashx?t=""&A58,""table"",10),7,2),""*"",""""),""-"",""0.00""))"),"Loading...") -> Loading... | L58: 1240239 | M58: 8.67
A59: arebw | B59: 1648087 | C59: American Rebel Holdings Inc | E59: 0.01 | K59: =IFERROR(__xludf.DUMMYFUNCTION("if(A59="""","""",substitute(SUBSTITUTE(index(importhtml(""http://finviz.com/quote.ashx?t=""&A59,""table"",10),7,2),""*"",""""),""-"",""0.00""))"),"Loading...") -> Loading... | L59: 1247314 | M59: #N/A
A60: ukomw | B60: 1821424 | C60: Ucommune International Ltd | E60: 0.01 | K60: =IFERROR(__xludf.DUMMYFUNCTION("if(A60="""","""",substitute(SUBSTITUTE(index(importhtml(""http://finviz.com/quote.ashx?t=""&A60,""table"",10),7,2),""*"",""""),""-"",""0.00""))"),"Loading...") -> Loading... | L60: 1269717 | M60: 0.08
A61: brg | B61: 1442626 | C61: Brigadier Gold Ltd | E61: 0.01 | K61: =IFERROR(__xludf.DUMMYFUNCTION("if(A61="""","""",substitute(SUBSTITUTE(index(importhtml(""http://finviz.com/quote.ashx?t=""&A61,""table"",10),7,2),""*"",""""),""-"",""0.00""))"),"Loading...") -> Loading... | L61: 1277640 | M61: 4.81
A62: andr | B62: 6494 | C62: Andrea Electronics Corporation | E62: 0.01 | K62: =IFERROR(__xludf.DUMMYFUNCTION("if(A62="""","""",substitute(SUBSTITUTE(index(importhtml(""http://finviz.com/quote.ashx?t=""&A62,""table"",10),7,2),""*"",""""),""-"",""0.00""))"),"Loading...") -> Loading... | L62: 1417099 | M62: 0.28
A63: ger | B63: 1612875 | C63: Glen Eagle Resources Inc | E63: 0.01 | K63: =IFERROR(__xludf.DUMMYFUNCTION("if(A63="""","""",substitute(SUBSTITUTE(index(importhtml(""http://finviz.com/quote.ashx?t=""&A63,""table"",10),7,2),""*"",""""),""-"",""0.00""))"),"Loading...") -> Loading... | L63: 1458019 | M63: 0.97
A64: id | B64: 1698113 | C64: Identillect Technologies Corp | E64: 0.01 | K64: =IFERROR(__xludf.DUMMYFUNCTION("if(A64="""","""",substitute(SUBSTITUTE(index(importhtml(""http://finviz.com/quote.ashx?t=""&A64,""table"",10),7,2),""*"",""""),""-"",""0.00""))"),"Loading...") -> Loading... | L64: 1471910 | M64: 0.67
A65: sqllw | B65: 1605888 | C65: SEQLL | E65: 0.01 | K65: =IFERROR(__xludf.DUMMYFUNCTION("if(A65="""","""",substitute(SUBSTITUTE(index(importhtml(""http://finviz.com/quote.ashx?t=""&A65,""table"",10),7,2),""*"",""""),""-"",""0.00""))"),"Loading...") -> Loading... | L65: 1522588 | M65: #N/A
A66: vism | B66: 1082733 | C66: Visium Technologies Inc | E66: 0.01 | K66: =IFERROR(__xludf.DUMMYFUNCTION("if(A66="""","""",substitute(SUBSTITUTE(index(importhtml(""http://finviz.com/quote.ashx?t=""&A66,""table"",10),7,2),""*"",""""),""-"",""0.00""))"),"Loading...") -> Loading... | L66: 1527358 | M66: 2.27
A67: agriw | B67: 1826397 | C67: AgriFORCE Growing Systems | E67: 0.01 | K67: =IFERROR(__xludf.DUMMYFUNCTION("if(A67="""","""",substitute(SUBSTITUTE(index(importhtml(""http://finviz.com/quote.ashx?t=""&A67,""table"",10),7,2),""*"",""""),""-"",""0.00""))"),"Loading...") -> Loading... | L67: 1534441 | M67: #N/A
A68: svsn | B68: 1099814 | C68: Stereo Vision Entertainment Inc | E68: 0.01 | K68: =IFERROR(__xludf.DUMMYFUNCTION("if(A68="""","""",substitute(SUBSTITUTE(index(importhtml(""http://finviz.com/quote.ashx?t=""&A68,""table"",10),7,2),""*"",""""),""-"",""0.00""))"),"Loading...") -> Loading... | L68: 1637880 | M68: -0.23
A69: cbnt | B69: 1421636 | C69: C-Bond Systems Inc | E69: 0.01 | K69: =IFERROR(__xludf.DUMMYFUNCTION("if(A69="""","""",substitute(SUBSTITUTE(index(importhtml(""http://finviz.com/quote.ashx?t=""&A69,""table"",10),7,2),""*"",""""),""-"",""0.00""))"),"Loading...") -> Loading... | L69: 1699689 | M69: 0.64
A70: purt | B70: 1126162 | C70: Purthanol Resources Ltd | E70: 0.01 | K70: =IFERROR(__xludf.DUMMYFUNCTION("if(A70="""","""",substitute(SUBSTITUTE(index(importhtml(""http://finviz.com/quote.ashx?t=""&A70,""table"",10),7,2),""*"",""""),""-"",""0.00""))"),"Loading...") -> Loading... | L70: 1708270 | M70: #N/A
A71: gmer | B71: 1454742 | C71: Good Gaming Inc | E71: 0.01 | K71: =IFERROR(__xludf.DUMMYFUNCTION("if(A71="""","""",substitute(SUBSTITUTE(index(importhtml(""http://finviz.com/quote.ashx?t=""&A71,""table"",10),7,2),""*"",""""),""-"",""0.00""))"),"Loading...") -> Loading... | L71: 1743075 | M71: 0.33
A72: brshw | B72: 1913210 | C72: Bruush Oral Care | E72: 0.01 | K72: =IFERROR(__xludf.DUMMYFUNCTION("if(A72="""","""",substitute(SUBSTITUTE(index(importhtml(""http://finviz.com/quote.ashx?t=""&A72,""table"",10),7,2),""*"",""""),""-"",""0.00""))"),"Loading...") -> Loading... | L72: 1753937 | M72: #N/A
A73: tamg | B73: 1158702 | C73: Transnational Automotive Group Inc Common Stock | E73: 0.01 | K73: =IFERROR(__xludf.DUMMYFUNCTION("if(A73="""","""",substitute(SUBSTITUTE(index(importhtml(""http://finviz.com/quote.ashx?t=""&A73,""table"",10),7,2),""*"",""""),""-"",""0.00""))"),"Loading...") -> Loading... | L73: 1837280 | M73: 2.85
A74: cpwr | B74: 827099 | C74: Ocean Thermal Energy Corp | E74: 0.01 | K74: =IFERROR(__xludf.DUMMYFUNCTION("if(A74="""","""",substitute(SUBSTITUTE(index(importhtml(""http://finviz.com/quote.ashx?t=""&A74,""table"",10),7,2),""*"",""""),""-"",""0.00""))"),"Loading...") -> Loading... | L74: 1843700 | M74: #N/A
A75: kitl | B75: 1608092 | C75: Kisses From Italy Inc | E75: 0.01 | K75: =IFERROR(__xludf.DUMMYFUNCTION("if(A75="""","""",substitute(SUBSTITUTE(index(importhtml(""http://finviz.com/quote.ashx?t=""&A75,""table"",10),7,2),""*"",""""),""-"",""0.00""))"),"Loading...") -> Loading... | L75: 1894289 | M75: 2.79
A76: ycrm | B76: 1624517 | C76: Yuenglings Ice Cream Corp | E76: 0.01 | K76: =IFERROR(__xludf.DUMMYFUNCTION("if(A76="""","""",substitute(SUBSTITUTE(index(importhtml(""http://finviz.com/quote.ashx?t=""&A76,""table"",10),7,2),""*"",""""),""-"",""0.00""))"),"Loading...") -> Loading... | L76: 1929296 | M76: 2.44
A77: gcfff | B77: 863678 | C77: Goldcliff Resource Corporation | E77: 0.01 | K77: =IFERROR(__xludf.DUMMYFUNCTION("if(A77="""","""",substitute(SUBSTITUTE(index(importhtml(""http://finviz.com/quote.ashx?t=""&A77,""table"",10),7,2),""*"",""""),""-"",""0.00""))"),"Loading...") -> Loading... | L77: 2017740 | M77: 0.19
A78: jshg | B78: 1475430 | C78: Joshua Gold Resources Inc | E78: 0.01 | K78: =IFERROR(__xludf.DUMMYFUNCTION("if(A78="""","""",substitute(SUBSTITUTE(index(importhtml(""http://finviz.com/quote.ashx?t=""&A78,""table"",10),7,2),""*"",""""),""-"",""0.00""))"),"Loading...") -> Loading... | L78: 2051664 | M78: 0.2
A79: btzi | B79: 1525852 | C79: Bots Inc | E79: 0.01 | K79: =IFERROR(__xludf.DUMMYFUNCTION("if(A79="""","""",substitute(SUBSTITUTE(index(importhtml(""http://finviz.com/quote.ashx?t=""&A79,""table"",10),7,2),""*"",""""),""-"",""0.00""))"),"Loading...") -> Loading... | L79: 2149150 | M79: 0.37
A80: drop | B80: 842722 | C80: Fuse Science Inc | E80: 0.01 | K80: =IFERROR(__xludf.DUMMYFUNCTION("if(A80="""","""",substitute(SUBSTITUTE(index(importhtml(""http://finviz.com/quote.ashx?t=""&A80,""table"",10),7,2),""*"",""""),""-"",""0.00""))"),"Loading...") -> Loading... | L80: 2307700 | M80: 1.35
A81: ptnyf | B81: 1819074 | C81: ParcelPal Logistics Inc | E81: 0.01 | K81: =IFERROR(__xludf.DUMMYFUNCTION("if(A81="""","""",substitute(SUBSTITUTE(index(importhtml(""http://finviz.com/quote.ashx?t=""&A81,""table"",10),7,2),""*"",""""),""-"",""0.00""))"),"Loading...") -> Loading... | L81: 2331529 | M81: 0.72
A82: tlcc | B82: 1590695 | C82: Twinlab Consolidated Holdings Inc | E82: 0.01 | K82: =IFERROR(__xludf.DUMMYFUNCTION("if(A82="""","""",substitute(SUBSTITUTE(index(importhtml(""http://finviz.com/quote.ashx?t=""&A82,""table"",10),7,2),""*"",""""),""-"",""0.00""))"),"Loading...") -> Loading... | L82: 2590930 | M82: 0.18
A83: ipix | B83: 1355250 | C83: Innovation Pharmaceuticals Inc | E83: 0.01 | K83: =IFERROR(__xludf.DUMMYFUNCTION("if(A83="""","""",substitute(SUBSTITUTE(index(importhtml(""http://finviz.com/quote.ashx?t=""&A83,""table"",10),7,2),""*"",""""),""-"",""0.00""))"),"Loading...") -> Loading... | L83: 2648758 | M83: -0.29
A84: edblw | B84: 1809750 | C84: Edible Garden AG | E84: 0.01 | K84: =IFERROR(__xludf.DUMMYFUNCTION("if(A84="""","""",substitute(SUBSTITUTE(index(importhtml(""http://finviz.com/quote.ashx?t=""&A84,""table"",10),7,2),""*"",""""),""-"",""0.00""))"),"Loading...") -> Loading... | L84: 2656875 | M84: #N/A
A85: alds | B85: 1755101 | C85: APPlife Digital Solutions Inc | E85: 0.01 | K85: =IFERROR(__xludf.DUMMYFUNCTION("if(A85="""","""",substitute(SUBSTITUTE(index(importhtml(""http://finviz.com/quote.ashx?t=""&A85,""table"",10),7,2),""*"",""""),""-"",""0.00""))"),"Loading...") -> Loading... | L85: 2739893 | M85: -6.02
A86: kor | B86: 1507964 | C86: Korab Resources Limited | E86: 0.01 | K86: =IFERROR(__xludf.DUMMYFUNCTION("if(A86="""","""",substitute(SUBSTITUTE(index(importhtml(""http://finviz.com/quote.ashx?t=""&A86,""table"",10),7,2),""*"",""""),""-"",""0.00""))"),"Loading...") -> Loading... | L86: 2936400 | M86: #N/A
A87: nugl | B87: 1096768 | C87: NUGL Inc | E87: 0.01 | K87: =IFERROR(__xludf.DUMMYFUNCTION("if(A87="""","""",substitute(SUBSTITUTE(index(importhtml(""http://finviz.com/quote.ashx?t=""&A87,""table"",10),7,2),""*"",""""),""-"",""0.00""))"),"Loading...") -> Loading... | L87: 3095463 | M87: -0.06
A88: cnnc | B88: 1410187 | C88: Cannonau Corp | E88: 0.01 | K88: =IFERROR(__xludf.DUMMYFUNCTION("if(A88="""","""",substitute(SUBSTITUTE(index(importhtml(""http://finviz.com/quote.ashx?t=""&A88,""table"",10),7,2),""*"",""""),""-"",""0.00""))"),"Loading...") -> Loading... | L88: 3144854 | M88: 4.82
A89: gultu | B89: 1565146 | C89: Gulf Coast Ultra Deep Royalty Trust | E89: 0.01 | K89: =IFERROR(__xludf.DUMMYFUNCTION("if(A89="""","""",substitute(SUBSTITUTE(index(importhtml(""http://finviz.com/quote.ashx?t=""&A89,""table"",10),7,2),""*"",""""),""-"",""0.00""))"),"#N/A") -> #N/A | L89: 3314484 | M89: 0.59
A90: gmblz | B90: 1451448 | C90: Esports Entertainment Group Inc | E90: 0.01 | K90: =IFERROR(__xludf.DUMMYFUNCTION("if(A90="""","""",substitute(SUBSTITUTE(index(importhtml(""http://finviz.com/quote.ashx?t=""&A90,""table"",10),7,2),""*"",""""),""-"",""0.00""))"),"Loading...") -> Loading... | L90: 3439950 | M90: #N/A
A91: ammj | B91: 945617 | C91: American Cannabis Company Inc | E91: 0.01 | K91: =IFERROR(__xludf.DUMMYFUNCTION("if(A91="""","""",substitute(SUBSTITUTE(index(importhtml(""http://finviz.com/quote.ashx?t=""&A91,""table"",10),7,2),""*"",""""),""-"",""0.00""))"),"Loading...") -> Loading... | L91: 3490246 | M91: 0.95
A92: tgiff | B92: 1706145 | C92: 1933 Industries Inc | E92: 0.01 | K92: =IFERROR(__xludf.DUMMYFUNCTION("if(A92="""","""",substitute(SUBSTITUTE(index(importhtml(""http://finviz.com/quote.ashx?t=""&A92,""table"",10),7,2),""*"",""""),""-"",""0.00""))"),"Loading...") -> Loading... | L92: 3548759 | M92: -0.05
A93: snaxw | B93: 1691936 | C93: Stryve Foods | E93: 0.01 | K93: =IFERROR(__xludf.DUMMYFUNCTION("if(A93="""","""",substitute(SUBSTITUTE(index(importhtml(""http://finviz.com/quote.ashx?t=""&A93,""table"",10),7,2),""*"",""""),""-"",""0.00""))"),"Loading...") -> Loading... | L93: 3599637 | M93: 1.88
A94: gads | B94: 711665 | C94: Gadsden Properties Inc | E94: 0.01 | K94: =IFERROR(__xludf.DUMMYFUNCTION("if(A94="""","""",substitute(SUBSTITUTE(index(importhtml(""http://finviz.com/quote.ashx?t=""&A94,""table"",10),7,2),""*"",""""),""-"",""0.00""))"),"Loading...") -> Loading... | L94: 3653550 | M94: #N/A
A95: ncr | B95: 70866 | C95: Nucoal Resources Ltd | E95: 0.01 | K95: =IFERROR(__xludf.DUMMYFUNCTION("if(A95="""","""",substitute(SUBSTITUTE(index(importhtml(""http://finviz.com/quote.ashx?t=""&A95,""table"",10),7,2),""*"",""""),""-"",""0.00""))"),"Loading...") -> Loading... | L95: 3843060 | M95: #N/A
A96: mrge | B96: 1623360 | C96: Mirage Energy Corp | E96: 0.01 | K96: =IFERROR(__xludf.DUMMYFUNCTION("if(A96="""","""",substitute(SUBSTITUTE(index(importhtml(""http://finviz.com/quote.ashx?t=""&A96,""table"",10),7,2),""*"",""""),""-"",""0.00""))"),"Loading...") -> Loading... | L96: 3886799 | M96: #N/A
A97: cgolf | B97: 1759352 | C97: Contact Gold Corp | E97: 0.01 | K97: =IFERROR(__xludf.DUMMYFUNCTION("if(A97="""","""",substitute(SUBSTITUTE(index(importhtml(""http://finviz.com/quote.ashx?t=""&A97,""table"",10),7,2),""*"",""""),""-"",""0.00""))"),"Loading...") -> Loading... | L97: 3963449 | M97: -0.01
A98: nugn | B98: 1593549 | C98: Livento Group Inc | E98: 0.01 | K98: =IFERROR(__xludf.DUMMYFUNCTION("if(A98="""","""",substitute(SUBSTITUTE(index(importhtml(""http://finviz.com/quote.ashx?t=""&A98,""table"",10),7,2),""*"",""""),""-"",""0.00""))"),"Loading...") -> Loading... | L98: 4040695 | M98: 4.59
A99: ceadw | B99: 1482541 | C99: CEA Industries | E99: 0.01 | K99: =IFERROR(__xludf.DUMMYFUNCTION("if(A99="""","""",substitute(SUBSTITUTE(index(importhtml(""http://finviz.com/quote.ashx?t=""&A99,""table"",10),7,2),""*"",""""),""-"",""0.00""))"),"Loading...") -> Loading... | L99: 4244206 | M99: #N/A
A100: newh | B100: 1371128 | C100: Newhydrogen Inc | E100: 0.01 | K100: =IFERROR(__xludf.DUMMYFUNCTION("if(A100="""","""",substitute(SUBSTITUTE(index(importhtml(""http://finviz.com/quote.ashx?t=""&A100,""table"",10),7,2),""*"",""""),""-"",""0.00""))"),"Loading...") -> Loading... | L100: 4261432 | M100: 1.78
...

Sheet BBB
A1: TICKER | B1: Industry | C1: Sector | D1: IPO | F1: Company Name | G1: MKT CAP | H1: price | I1: Country | J1: Industry | K1: Sector | L1: INDEX | O1: GOAL TO SLIM DOWN LISTINGS
A2: AAPL | B2: Technology | C2: Computer Manufacturing | D2: 1980 | F2: Apple Inc. Common Stock | G2: 2899032972800 | H2: 186.4 | I2: United States | J2: Technology | K2: Computer Manufacturing | L2: NASDAQ
A3: MSFT | B3: Technology | C3: Computer Software: Prepackaged Software | D3: 1986 | F3: Microsoft Corporation Common Stock | G3: 2747484415161 | H3: 369.67 | I3: United States | J3: Technology | K3: Computer Software: Prepackaged Software | L3: NASDAQ
A4: GOOG | B4: Technology | C4: Computer Software: Programming Data Processing | D4: 2004 | F4: Alphabet Inc. Class C Capital Stock | G4: 1677894960000 | H4: 134.06 | I4: United States | J4: Technology | K4: Computer Software: Programming Data Processing | L4: NASDAQ
A5: GOOGL | B5: Technology | C5: Computer Software: Programming Data Processing | D5: 2004 | F5: Alphabet Inc. Class A Common Stock | G5: 1659496440000 | H5: 132.59 | I5: United States | J5: Technology | K5: Computer Software: Programming Data Processing | L5: NASDAQ
A6: AMZN | B6: Consumer Discretionary | C6: Catalog/Specialty Distribution | D6: 1997 | F6: Amazon.com Inc. Common Stock | G6: 1483553430926 | H6: 143.56 | I6: Bermuda | J6: Consumer Discretionary | K6: Catalog/Specialty Distribution | L6: NASDAQ
A7: NVDA | B7: Technology | C7: Semiconductors | D7: 1999 | F7: NVIDIA Corporation Common Stock | G7: 1193874500000 | H7: 483.35 | I7: United States | J7: Technology | K7: Semiconductors | L7: NASDAQ
A8: META | B8: Technology | C8: Computer Software: Programming Data Processing | D8: 2012 | F8: Meta Platforms Inc. Class A Common Stock | G8: 844893770400 | H8: 328.77 | I8: United States | J8: Technology | K8: Computer Software: Programming Data Processing | L8: NASDAQ
A9: BRK/A | F9: Berkshire Hathaway Inc. | G9: 782337288364 | H9: 531886 | I9: United States | L9: NASDAQ
A12: BRK/B | F12: Berkshire Hathaway Inc. | G12: 773444514218 | H12: 350.56 | I12: United States | L12: NYSE
A13: HSBC | B13: Savings Institutions | C13: Finance | F13: HSBC Holdings plc. Common Stock | G13: 729231790000 | H13: 37.03 | I13: United States | J13: Savings Institutions | K13: Finance | L13: NYSE,NASDAQ
A14: HSBC | B14: Finance | C14: Savings Institutions | F14: HSBC Holdings plc. Common Stock | G14: 729231790000 | H14: 37.03 | I14: United States | J14: Finance | K14: Savings Institutions | L14: NASDAQ
A15: TSLA | B15: Consumer Discretionary | C15: Auto Manufacturing | D15: 2010 | F15: Tesla Inc. Common Stock | G15: 682355476578 | H15: 214.65 | I15: Ireland | J15: Consumer Discretionary | K15: Auto Manufacturing | L15: NASDAQ
A16: LLY | B16: Health Care | C16: Biotechnology: Pharmaceutical Preparations | F16: Eli Lilly and Company Common Stock | G16: 567410428627 | H16: 597.71 | I16: United States | J16: Health Care | K16: Biotechnology: Pharmaceutical Preparations | L16: NASDAQ
A17: LLY | B17: Biotechnology: Pharmaceutical Preparations | C17: Health Care | F17: Eli Lilly and Company Common Stock | G17: 567410428627 | H17: 597.71 | I17: United States | J17: Biotechnology: Pharmaceutical Preparations | K17: Health Care | L17: NYSE
A18: TSM | B18: Technology | C18: Semiconductors | D18: 1997 | F18: Taiwan Semiconductor Manufacturing Company Ltd. | G18: 505331254404 | H18: 97.44 | I18: United States | J18: Technology | K18: Semiconductors | L18: NASDAQ
A19: TSM | B19: Semiconductors | C19: Technology | D19: 1997 | F19: Taiwan Semiconductor Manufacturing Company Ltd. | G19: 505331254404 | H19: 97.44 | I19: United States | J19: Semiconductors | K19: Technology | L19: NYSE
A20: UNH | B20: Medical Specialities | C20: Health Care | F20: UnitedHealth Group Incorporated Common Stock (DE) | G20: 500578817825 | H20: 541.21 | I20: United States | J20: Medical Specialities | K20: Health Care | L20: NYSE
A21: UNH | B21: Health Care | C21: Medical Specialities | F21: UnitedHealth Group Incorporated Common Stock (DE) | G21: 500578817825 | H21: 541.21 | I21: United States | J21: Health Care | K21: Medical Specialities | L21: NASDAQ
A22: V | B22: Consumer Discretionary | C22: Business Services | F22: Visa Inc. | G22: 456616403717 | H22: 245.25 | I22: Israel | J22: Consumer Discretionary | K22: Business Services | L22: NASDAQ
A23: V | B23: Business Services | C23: Consumer Discretionary | F23: Visa Inc. | G23: 456616403717 | H23: 245.25 | I23: United States | J23: Business Services | K23: Consumer Discretionary | L23: NYSE
A24: NVO | B24: Health Care | C24: Biotechnology: Biological Products (No Diagnostic Substances) | F24: Novo Nordisk A/S Common Stock | G24: 453124941994 | H24: 101.19 | I24: United States | J24: Health Care | K24: Biotechnology: Biological Products (No Diagnostic Substances) | L24: NASDAQ
A25: NVO | B25: Biotechnology: Biological Products (No Diagnostic Substances) | C25: Health Care | F25: Novo Nordisk A/S Common Stock | G25: 453124941994 | H25: 101.19 | I25: United States | J25: Biotechnology: Biological Products (No Diagnostic Substances) | K25: Health Care | L25: NYSE
A26: WMT | B26: Consumer Discretionary | C26: Department/Specialty Retail Stores | F26: Walmart Inc. Common Stock | G26: 447310996232 | H26: 166.19 | I26: Israel | J26: Consumer Discretionary | K26: Department/Specialty Retail Stores | L26: NASDAQ
A27: WMT | B27: Department/Specialty Retail Stores | C27: Consumer Discretionary | F27: Walmart Inc. Common Stock | G27: 447310996232 | H27: 166.19 | I27: United States | J27: Department/Specialty Retail Stores | K27: Consumer Discretionary | L27: NYSE
A28: SHEL | B28: Energy | C28: Oil & Gas Production | D28: 2022 | F28: Shell PLC American Depositary Shares (each representing two (2) Ordinary Shares) | G28: 438904081600 | H28: 65.6 | I28: South Korea | J28: Energy | K28: Oil & Gas Production | L28: NASDAQ
A29: SHEL | B29: Oil & Gas Production | C29: Energy | D29: 2022 | F29: Shell PLC American Depositary Shares (each representing two (2) Ordinary Shares) | G29: 438904081600 | H29: 65.6 | I29: United States | J29: Oil & Gas Production | K29: Energy | L29: NYSE
A30: JPM | B30: Major Banks | C30: Finance | F30: JP Morgan Chase & Co. Common Stock | G30: 423330351373 | H30: 146.43 | I30: United States | J30: Major Banks | K30: Finance | L30: NYSE
A31: JPM | B31: Finance | C31: Major Banks | F31: JP Morgan Chase & Co. Common Stock | G31: 423330351373 | H31: 146.43 | I31: United States | J31: Finance | K31: Major Banks | L31: NASDAQ
A32: XOM | B32: Energy | C32: Integrated oil Companies | F32: Exxon Mobil Corporation Common Stock | G32: 411152730673 | H32: 103.75 | I32: Switzerland | J32: Energy | K32: Integrated oil Companies | L32: NASDAQ
A33: XOM | B33: Integrated oil Companies | C33: Energy | F33: Exxon Mobil Corporation Common Stock | G33: 411152730673 | H33: 103.75 | I33: United States | J33: Integrated oil Companies | K33: Energy | L33: NYSE
A34: AVGO | B34: Technology | C34: Semiconductors | D34: 2009 | F34: Broadcom Inc. Common Stock | G34: 395202499790 | H34: 957.52 | I34: United States | J34: Technology | K34: Semiconductors | L34: NASDAQ
A35: MA | B35: Consumer Discretionary | C35: Business Services | D35: 2006 | F35: Mastercard Incorporated Common Stock | G35: 369840122937 | H35: 394.38 | I35: China | J35: Consumer Discretionary | K35: Business Services | L35: NASDAQ
A36: MA | B36: Business Services | C36: Consumer Discretionary | D36: 2006 | F36: Mastercard Incorporated Common Stock | G36: 369840122937 | H36: 394.38 | I36: United States | J36: Business Services | K36: Consumer Discretionary | L36: NYSE
A37: PG | B37: Consumer Discretionary | C37: Package Goods/Cosmetics | F37: Procter & Gamble Company (The) Common Stock | G37: 356856141208 | H37: 151.41 | I37: China | J37: Consumer Discretionary | K37: Package Goods/Cosmetics | L37: NASDAQ
A38: PG | B38: Package Goods/Cosmetics | C38: Consumer Discretionary | F38: Procter & Gamble Company (The) Common Stock | G38: 356856141208 | H38: 151.41 | I38: United States | J38: Package Goods/Cosmetics | K38: Consumer Discretionary | L38: NYSE
A39: JNJ | B39: Health Care | C39: Biotechnology: Pharmaceutical Preparations | F39: Johnson & Johnson Common Stock | G39: 354471776795 | H39: 147.25 | I39: United States | J39: Health Care | K39: Biotechnology: Pharmaceutical Preparations | L39: NASDAQ
A40: JNJ | B40: Biotechnology: Pharmaceutical Preparations | C40: Health Care | F40: Johnson & Johnson Common Stock | G40: 354471776795 | H40: 147.25 | I40: United States | J40: Biotechnology: Pharmaceutical Preparations | K40: Health Care | L40: NYSE
A41: ORCL | B41: Technology | C41: Computer Software: Prepackaged Software | D41: 1986 | F41: Oracle Corporation Common Stock | G41: 309791560470 | H41: 113.07 | I41: United States | J41: Technology | K41: Computer Software: Prepackaged Software | L41: NASDAQ
A42: ORCL | B42: Computer Software: Prepackaged Software | C42: Technology | D42: 1986 | F42: Oracle Corporation Common Stock | G42: 309791560470 | H42: 113.07 | I42: United States | J42: Computer Software: Prepackaged Software | K42: Technology | L42: NYSE
A43: BHP | B43: Basic Materials | C43: Metal Mining | F43: BHP Group Limited American Depositary Shares (Each representing two Ordinary Shares) | G43: 294090217971 | H43: 58.07 | I43: Argentina | J43: Basic Materials | K43: Metal Mining | L43: NASDAQ
A44: BHP | B44: Metal Mining | C44: Basic Materials | F44: BHP Group Limited American Depositary Shares (Each representing two Ordinary Shares) | G44: 294090217971 | H44: 58.07 | I44: United States | J44: Metal Mining | K44: Basic Materials | L44: NYSE
A45: HD | B45: Consumer Discretionary | C45: RETAIL: Building Materials | F45: Home Depot Inc. (The) Common Stock | G45: 291609239691 | H45: 291.59 | I45: Cayman Islands | J45: Consumer Discretionary | K45: RETAIL: Building Materials | L45: NASDAQ
A46: HD | B46: RETAIL: Building Materials | C46: Consumer Discretionary | F46: Home Depot Inc. (The) Common Stock | G46: 291609239691 | H46: 291.59 | I46: United States | J46: RETAIL: Building Materials | K46: Consumer Discretionary | L46: NYSE
A47: ADBE | B47: Technology | C47: Computer Software: Prepackaged Software | D47: 1986 | F47: Adobe Inc. Common Stock | G47: 271914266000 | H47: 597.22 | I47: United States | J47: Technology | K47: Computer Software: Prepackaged Software | L47: NASDAQ
A48: CVX | B48: Energy | C48: Integrated oil Companies | F48: Chevron Corporation Common Stock | G48: 269853671662 | H48: 142.95 | I48: Netherlands | J48: Energy | K48: Integrated oil Companies | L48: NASDAQ
A49: CVX | B49: Integrated oil Companies | C49: Energy | F49: Chevron Corporation Common Stock | G49: 269853671662 | H49: 142.95 | I49: United States | J49: Integrated oil Companies | K49: Energy | L49: NYSE
A50: ASML | B50: Technology | C50: Industrial Machinery/Components | D50: 1995 | F50: ASML Holding N.V. New York Registry Shares | G50: 260934085706 | H50: 661.28 | I50: United States | J50: Technology | K50: Industrial Machinery/Components | L50: NASDAQ
A51: TM | B51: Consumer Discretionary | C51: Auto Manufacturing | F51: Toyota Motor Corporation Common Stock | G51: 257654238798 | H51: 187 | I51: India | J51: Consumer Discretionary | K51: Auto Manufacturing | L51: NASDAQ
A52: TM | B52: Auto Manufacturing | C52: Consumer Discretionary | F52: Toyota Motor Corporation Common Stock | G52: 257654238798 | H52: 187 | I52: United States | J52: Auto Manufacturing | K52: Consumer Discretionary | L52: NYSE
A53: MRK | B53: Health Care | C53: Biotechnology: Pharmaceutical Preparations | F53: Merck & Company Inc. Common Stock (new) | G53: 256924600487 | H53: 101.39 | I53: United States | J53: Health Care | K53: Biotechnology: Pharmaceutical Preparations | L53: NASDAQ
A54: MRK | B54: Biotechnology: Pharmaceutical Preparations | C54: Health Care | F54: Merck & Company Inc. Common Stock (new) | G54: 256924600487 | H54: 101.39 | I54: United States | J54: Biotechnology: Pharmaceutical Preparations | K54: Health Care | L54: NYSE
A55: COST | B55: Consumer Discretionary | C55: Department/Specialty Retail Stores | F55: Costco Wholesale Corporation Common Stock | G55: 255514438913 | H55: 577.12 | I55: Canada | J55: Consumer Discretionary | K55: Department/Specialty Retail Stores | L55: NASDAQ
A56: KO | B56: Consumer Staples | C56: Beverages (Production/Distribution) | F56: Coca-Cola Company (The) Common Stock | G56: 245224031303 | H56: 56.72 | I56: Japan | J56: Consumer Staples | K56: Beverages (Production/Distribution) | L56: NASDAQ
A57: KO | B57: Beverages (Production/Distribution) | C57: Consumer Staples | F57: Coca-Cola Company (The) Common Stock | G57: 245224031303 | H57: 56.72 | I57: United States | J57: Beverages (Production/Distribution) | K57: Consumer Staples | L57: NYSE
A58: ABBV | B58: Health Care | C58: Biotechnology: Pharmaceutical Preparations | D58: 2012 | F58: AbbVie Inc. Common Stock | G58: 244685831176 | H58: 138.59 | I58: United States | J58: Health Care | K58: Biotechnology: Pharmaceutical Preparations | L58: NASDAQ
A59: ABBV | B59: Biotechnology: Pharmaceutical Preparations | C59: Health Care | D59: 2012 | F59: AbbVie Inc. Common Stock | G59: 244685831176 | H59: 138.59 | I59: United States | J59: Biotechnology: Pharmaceutical Preparations | K59: Health Care | L59: NYSE
A60: PEP | B60: Consumer Staples | C60: Beverages (Production/Distribution) | F60: PepsiCo Inc. Common Stock | G60: 229492292370 | H60: 166.92 | I60: Luxembourg | J60: Consumer Staples | K60: Beverages (Production/Distribution) | L60: NASDAQ
A61: NGG | B61: Utilities | C61: Natural Gas Distribution | F61: National Grid Transco PLC National Grid PLC (NEW) American Depositary Shares | G61: 224895933598 | H61: 60.98 | I61: United States | J61: Utilities | K61: Natural Gas Distribution | L61: NASDAQ
A62: NGG | B62: Natural Gas Distribution | C62: Utilities | F62: National Grid Transco PLC National Grid PLC (NEW) American Depositary Shares | G62: 224895933598 | H62: 60.98 | I62: United States | J62: Natural Gas Distribution | K62: Utilities | L62: NYSE
A63: BAC | B63: Finance | C63: Major Banks | F63: Bank of America Corporation Common Stock | G63: 219052102148 | H63: 27.68 | I63: United Kingdom | J63: Finance | K63: Major Banks | L63: NASDAQ
A64: BAC | B64: Major Banks | C64: Finance | F64: Bank of America Corporation Common Stock | G64: 219052102148 | H64: 27.68 | I64: United States | J64: Major Banks | K64: Finance | L64: NYSE
A65: CSCO | B65: Telecommunications | C65: Computer Communications Equipment | D65: 1990 | F65: Cisco Systems Inc. Common Stock (DE) | G65: 213244970808 | H65: 52.59 | I65: United States | J65: Telecommunications | K65: Computer Communications Equipment | L65: NASDAQ
A66: ACN | B66: Technology | C66: EDP Services | D66: 2001 | F66: Accenture plc Class A Ordinary Shares (Ireland) | G66: 212629676060 | H66: 319.69 | I66: United States | J66: Technology | K66: EDP Services | L66: NASDAQ
A67: ACN | B67: EDP Services | C67: Technology | D67: 2001 | F67: Accenture plc Class A Ordinary Shares (Ireland) | G67: 212629676060 | H67: 319.69 | I67: United States | J67: EDP Services | K67: Technology | L67: NYSE
A68: BABA | B68: Consumer Discretionary | C68: Catalog/Specialty Distribution | D68: 2014 | F68: Alibaba Group Holding Limited American Depositary Shares each representing eight Ordinary share | G68: 212315995709 | H68: 82.75 | I68: Brazil | J68: Consumer Discretionary | K68: Catalog/Specialty Distribution | L68: NASDAQ
A69: BABA | B69: Catalog/Specialty Distribution | C69: Consumer Discretionary | D69: 2014 | F69: Alibaba Group Holding Limited American Depositary Shares each representing eight Ordinary share | G69: 212315995709 | H69: 82.75 | I69: United States | J69: Catalog/Specialty Distribution | K69: Consumer Discretionary | L69: NYSE
A70: CRM | B70: Technology | C70: Computer Software: Prepackaged Software | D70: 2004 | F70: Salesforce Inc. Common Stock | G70: 207861990000 | H70: 213.63 | I70: United States | J70: Technology | K70: Computer Software: Prepackaged Software | L70: NASDAQ
A71: CRM | B71: Computer Software: Prepackaged Software | C71: Technology | D71: 2004 | F71: Salesforce Inc. Common Stock | G71: 207861990000 | H71: 213.63 | I71: United States | J71: Computer Software: Prepackaged Software | K71: Technology | L71: NYSE
A72: NVS | B72: Health Care | C72: Biotechnology: Pharmaceutical Preparations | F72: Novartis AG Common Stock | G72: 198268231192 | H72: 93.54 | I72: United States | J72: Health Care | K72: Biotechnology: Pharmaceutical Preparations | L72: NASDAQ
A73: NVS | B73: Biotechnology: Pharmaceutical Preparations | C73: Health Care | F73: Novartis AG Common Stock | G73: 198268231192 | H73: 93.54 | I73: United States | J73: Biotechnology: Pharmaceutical Preparations | K73: Health Care | L73: NYSE
A74: NFLX | B74: Consumer Discretionary | C74: Consumer Electronics/Video Chains | D74: 2002 | F74: Netflix Inc. Common Stock | G74: 195747855164 | H74: 447.24 | I74: China | J74: Consumer Discretionary | K74: Consumer Electronics/Video Chains | L74: NASDAQ
A75: MCD | B75: Consumer Discretionary | C75: Restaurants | F75: McDonald's Corporation Common Stock | G75: 194239342214 | H75: 267.79 | I75: China | J75: Consumer Discretionary | K75: Restaurants | L75: NASDAQ
A76: MCD | B76: Restaurants | C76: Consumer Discretionary | F76: McDonald's Corporation Common Stock | G76: 194239342214 | H76: 267.79 | I76: United States | J76: Restaurants | K76: Consumer Discretionary | L76: NYSE
A77: LIN | B77: Industrials | C77: Major Chemicals | F77: Linde plc Ordinary Shares | G77: 193878611922 | H77: 399.84 | I77: United States | J77: Industrials | K77: Major Chemicals | L77: NASDAQ
A78: AMD | B78: Technology | C78: Semiconductors | F78: Advanced Micro Devices Inc. Common Stock | G78: 191582013484 | H78: 118.59 | I78: United States | J78: Technology | K78: Semiconductors | L78: NASDAQ
A79: SAP | B79: Technology | C79: EDP Services | F79: SAP SE ADS | G79: 178255964063 | H79: 145.1 | I79: United States | J79: Technology | K79: EDP Services | L79: NASDAQ
A80: SAP | B80: EDP Services | C80: Technology | F80: SAP SE ADS | G80: 178255964063 | H80: 145.1 | I80: United States | J80: EDP Services | K80: Technology | L80: NYSE
A81: TTE | B81: Energy | C81: Oil & Gas Production | F81: TotalEnergies SE | G81: 174381760955 | H81: 66.58 | I81: Spain | J81: Energy | K81: Oil & Gas Production | L81: NASDAQ
A82: TTE | B82: Oil & Gas Production | C82: Energy | F82: TotalEnergies SE | G82: 174381760955 | H82: 66.58 | I82: United States | J82: Oil & Gas Production | K82: Energy | L82: NYSE
A83: TMO | B83: Industrials | C83: Industrial Machinery/Components | F83: Thermo Fisher Scientific Inc Common Stock | G83: 173260939906 | H83: 448.43 | I83: United States | J83: Industrials | K83: Industrial Machinery/Components | L83: NASDAQ
A84: TMO | B84: Industrial Machinery/Components | C84: Industrials | F84: Thermo Fisher Scientific Inc Common Stock | G84: 173260939906 | H84: 448.43 | I84: United States | J84: Industrial Machinery/Components | K84: Industrials | L84: NYSE
A85: TMUS | B85: Telecommunications | C85: Telecommunications Equipment | F85: T-Mobile US Inc. Common Stock | G85: 170707283607 | H85: 147.61 | I85: United States | J85: Telecommunications | K85: Telecommunications Equipment | L85: NASDAQ
A86: CMCSA | B86: Telecommunications | C86: Cable & Other Pay Television Services | F86: Comcast Corporation Class A Common Stock | G86: 168691092281 | H86: 41.91 | I86: United States | J86: Telecommunications | K86: Cable & Other Pay Television Services | L86: NASDAQ
... A88: PFE | B88: Biotechnology: Pharmaceutical Preparations | C88: Health Care | F88: Pfizer Inc. Common Stock | G88: 166456263848 | H88: 29.48 | I88: United States | J88: Biotechnology: Pharmaceutical Preparations | K88: Health Care | L88: NYSE
A89: TBC | B89: Telecommunications Equipment | C89: Telecommunications | D89: 2018 | F89: AT&T Inc. 5.625% Global Notes due 2067 | G89: 164950964122 | H89: 23.07 | I89: United States | J89: Telecommunications Equipment | K89: Telecommunications | L89: NYSE
A90: TBC | B90: Telecommunications | C90: Telecommunications Equipment | D90: 2018 | F90: AT&T Inc. 5.625% Global Notes due 2067 | G90: 164950964122 | H90: 23.07 | I90: United States | J90: Telecommunications | K90: Telecommunications Equipment | L90: NASDAQ
A91: INTC | B91: Technology | C91: Semiconductors | F91: Intel Corporation Common Stock | G91: 163833760000 | H91: 38.86 | I91: United States | J91: Technology | K91: Semiconductors | L91: NASDAQ
A92: ABT | B92: Medical/Dental Instruments | C92: Health Care | F92: Abbott Laboratories Common Stock | G92: 163137420628 | H92: 93.97 | I92: United States | J92: Medical/Dental Instruments | K92: Health Care | L92: NYSE
A93: ABT | B93: Health Care | C93: Medical/Dental Instruments | F93: Abbott Laboratories Common Stock | G93: 163137420628 | H93: 93.97 | I93: United States | J93: Health Care | K93: Medical/Dental Instruments | L93: NASDAQ
A94: DIS | B94: Consumer Discretionary | C94: Services-Misc. Amusement & Recreation | F94: Walt Disney Company (The) Common Stock | G94: 161514573705 | H94: 88.27 | I94: Canada | J94: Consumer Discretionary | K94: Services-Misc. Amusement & Recreation | L94: NASDAQ
A95: DIS | B95: Services-Misc. Amusement & Recreation | C95: Consumer Discretionary | F95: Walt Disney Company (The) Common Stock | G95: 161514573705 | H95: 88.27 | I95: United States | J95: Services-Misc. Amusement & Recreation | K95: Consumer Discretionary | L95: NYSE
A96: NKE | B96: Consumer Discretionary | C96: Shoe Manufacturing | F96: Nike Inc. Common Stock | G96: 161489883364 | H96: 106.11 | I96: China | J96: Consumer Discretionary | K96: Shoe Manufacturing | L96: NASDAQ
A97: NKE | B97: Shoe Manufacturing | C97: Consumer Discretionary | F97: Nike Inc. Common Stock | G97: 161489883364 | H97: 106.11 | I97: United States | J97: Shoe Manufacturing | K97: Consumer Discretionary | L97: NYSE
A98: TBB | B98: Telecommunications Equipment | C98: Telecommunications | D98: 2017 | F98: AT&T Inc. 5.350% Global Notes due 2066 | G98: 156942941590 | H98: 21.95 | I98: United States | J98: Telecommunications Equipment | K98: Telecommunications | L98: NYSE
A99: TBB | B99: Telecommunications | C99: Telecommunications Equipment | D99: 2017 | F99: AT&T Inc. 5.350% Global Notes due 2066 | G99: 156942941590 | H99: 21.95 | I99: United States | J99: Telecommunications | K99: Telecommunications Equipment | L99: NASDAQ
A100: VZ | B100: Telecommunications | C100: Telecommunications Equipment | F100: Verizon Communications Inc. Common Stock | G100: 150128470243 | H100: 35.71 | I100: United States | J100: Telecommunications | K100: Telecommunications Equipment | L100: NASDAQ
A101: WFC | B101: Major Banks | C101: Finance | F101: Wells Fargo & Company Common Stock | G101: 148497747905 | H101: 40.89 | I101: United States | J101: Major Banks | K101: Finance | L101: NYSE
A102: WFC | B102: Finance | C102: Major Banks | F102: Wells Fargo & Company Common Stock | G102: 148497747905 | H102: 40.89 | I102: United States | J102: Finance | K102: Major Banks | L102: NASDAQ
A103: INTU | B103: Technology | C103: Computer Software: Prepackaged Software | D103: 1993 | F103: Intuit Inc. Common Stock | G103: 148226443253 | H103: 528.89 | I103: United States | J103: Technology | K103: Computer Software: Prepackaged Software | L103: NASDAQ
...

Sheet CCC
A1: TICKER | B1: Industry | C1: Sector
G2: Computer Manufacturing
G3: Computer Software: Prepackaged Software
A4: BRK/A | G4: Computer Software: Programming Data Processing
A5: AAPL | B5: Computer Manufacturing | C5: Technology | G5: Computer Software: Programming Data Processing
A6: MSFT | B6: Computer Software: Prepackaged Software | C6: Technology | G6: Catalog/Specialty Distribution
A7: GOOG | B7: Computer Software: Programming Data Processing | C7: Technology | G7: Semiconductors
A8: GOOGL | B8: Computer Software: Programming Data Processing | C8: Technology | G8: Computer Software: Programming Data Processing
A9: AMZN | B9: Catalog/Specialty Distribution | C9: Consumer Discretionary
A10: NVDA | B10: Semiconductors | C10: Technology
A11: META | B11: Computer Software: Programming Data Processing | C11: Technology
A12: BRK/B
A13: HSBC | B13: Savings Institutions | C13: Finance
A14: HSBC | B14: Finance | C14: Savings Institutions
A15: TSLA | B15: Consumer Discretionary | C15: Auto Manufacturing
A16: LLY | B16: Health Care | C16: Biotechnology: Pharmaceutical Preparations
A17: LLY | B17: Biotechnology: Pharmaceutical Preparations | C17: Health Care
A18: TSM | B18: Technology | C18: Semiconductors
A19: TSM | B19: Semiconductors | C19: Technology
A20: UNH | B20: Medical Specialities | C20: Health Care
A21: UNH | B21: Health Care | C21: Medical Specialities
A22: V | B22: Consumer Discretionary | C22: Business Services
A23: V | B23: Business Services | C23: Consumer Discretionary
A24: NVO | B24: Health Care | C24: Biotechnology: Biological Products (No Diagnostic Substances)
... A139: RTX | B139: Aerospace | C139: Industrials
A140: RY
A141: RY
A142: UPS | B142: Trucking Freight/Courier Services | C142: Industrials
A143: UPS | B143: Industrials | C143: Trucking Freight/Courier Services
A144: SNY | B144: Health Care | C144: Biotechnology: Pharmaceutical Preparations
A145: NEE | B145: Utilities | C145: Electric Utilities: Central
A146: NEE | B146: Electric Utilities: Central | C146: Utilities
A147: AXP | B147: Finance | C147: Finance: Consumer Services
A148: AXP | B148: Finance: Consumer Services | C148: Finance
A149: LOW | B149: Consumer Discretionary | C149: RETAIL: Building Materials
A150: LOW | B150: RETAIL: Building Materials | C150: Consumer Discretionary
A151: T | B151: Telecommunications Equipment | C151: Telecommunications
A152: T | B152: Telecommunications | C152: Telecommunications Equipment
A153: LMT | B153: Military/Government/Technical | C153: Industrials
A154: LMT | B154: Industrials | C154: Military/Government/Technical
A155: TD
A156: TD
A157: SONY | B157: Consumer Staples | C157: Consumer Electronics/Appliances
A158: SONY | B158: Consumer Electronics/Appliances | C158: Consumer Staples
A159: DE | B159: Industrials | C159: Industrial Machinery/Components
A160: DE | B160: Industrial Machinery/Components | C160: Industrials
A161: ELV | B161: Medical Specialities | C161: Health Care
A162: ELV | B162: Health Care | C162: Medical Specialities
A163: BKNG | B163: Consumer Discretionary | C163: Transportation Services
A164: RIO | B164: Basic Materials | C164: Metal Mining
A165: RIO | B165: Metal Mining | C165: Basic Materials
A166: GS | B166: Investment Bankers/Brokers/Service | C166: Finance
A167: GS | B167: Finance | C167: Investment Bankers/Brokers/Service
A168: UBER | B168: Technology | C168: EDP Services
... A230: SNPS | B230: Technology | C230: Computer Software: Prepackaged Software
A231: SHOP
A232: SHOP
A233: PANW | B233: Technology | C233: Computer peripheral equipment
A234: CME | B234: Finance | C234: Investment Bankers/Brokers/Service
A235: ZTS | B235: Health Care | C235: Biotechnology: Pharmaceutical Preparations
A236: ZTS | B236: Biotechnology: Pharmaceutical Preparations | C236: Health Care
A237: ABNB | B237: Consumer Discretionary | C237: Hotels/Resorts
A238: SLB | B238: Energy | C238: Oilfield Services/Equipment
A239: SLB | B239: Oilfield Services/Equipment | C239: Energy
A240: BSX | B240: Medical/Dental Instruments | C240: Health Care
A241: BSX | B241: Health Care | C241: Medical/Dental Instruments
A242: SO | B242: Utilities | C242: Power Generation
A243: SO | B243: Power Generation | C243: Utilities
A244: NTES | B244: Technology | C244: Computer Software: Prepackaged Software
... A247: KLAC | B247: Technology | C247: Electronic Components
A248: CNI
A249: CNI
A250: EQIX | B250: Real Estate | C250: Real Estate Investment Trusts
A251: EOG | B251: Energy | C251: Oil & Gas Production
A252: EOG | B252: Oil & Gas Production | C252: Energy
A253: CDNS | B253: Technology | C253: Computer Software: Prepackaged Software
A254: ENB | B254: Energy | C254: Natural Gas Distribution
A255: ENB | B255: Natural Gas Distribution | C255: Energy
A256: MO | B256: Medicinal Chemicals and Botanical Products | C256: Health Care
A257: MO | B257: Health Care | C257: Medicinal Chemicals and Botanical Products
A258: GSK | B258: Health Care | C258: Biotechnology: Pharmaceutical Preparations
A259: GSK | B259: Biotechnology: Pharmaceutical Preparations | C259: Health Care
A260: CNQ | B260: Energy | C260: Oil & Gas Production
A261: CNQ | B261: Oil & Gas Production | C261: Energy
... A339: EPD | B339: Natural Gas Distribution | C339: Utilities
A340: BMO
A341: BMO
A342: ROP | B342: Industrials | C342: Industrial Machinery/Components
A343: MPC | B343: Energy | C343: Integrated oil Companies
A344: MPC | B344: Integrated oil Companies | C344: Energy
A345: TDG | B345: Military/Government/Technical | C345: Industrials
A346: TDG | B346: Industrials | C346: Military/Government/Technical
A347: AMX | B347: Telecommunications Equipment | C347: Telecommunications
A348: AMX | B348: Telecommunications | C348: Telecommunications Equipment
A349: SCCO | B349: Basic Materials | C349: Metal Mining
A350: SCCO | B350: Metal Mining | C350: Basic Materials
A351: KKR | B351: Investment Managers | C351: Finance
A352: KKR | B352: Finance | C352: Investment Managers
A353: PXD | B353: Energy | C353: Oil & Gas Production
... A361: AJG | B361: Specialty Insurers | C361: Finance
...

Sheet Watchlist
A1: dm | B1: 3d
A2: ssys | B2: 3d
A3: ddd
A4: frd
A5: vir
A6: pbf
D101: \

Sheet Altman Z
A1: Brand Equity | B1: 12 Months Ended | M1: EXPRESS | N1: Altman Z-score | O1: "Z-Score" model is a numerical measurement that is used to predict the chances of a business becoming bankrupt in the next two years.
B2: 44954 | C2: 44982 | D2: 44772 | M2: 10-k, 1/28/23 | O2: The formula takes into account profitability, leverage, liquidity, solvency, and activity ratios.
A3: Cover [Abstract] | M3: Steps: 1 | N3: working capital= | O3: Current Assets − Current Liabilities | Q3: 534404000 | R3: 1090756000 | S3: =Q3-R3 -> -556352000 | T3: Working capital is a measure of a company's operational liquidity and short-term financial health.
A4: Document Type | B4: 10-K | M4: 2 | N4: Retained Earnings= | O4: Begin Retained Earnings+NI−Dividends | S4: 355736000 | T4: Retained earnings=leftover profit after paying all its direct/indirect costs, taxes & dividends
A5: Document Annual Report | B5: TRUE | G5: working cap | H5: working cap | M5: 3 | N5: EBIT= Operating income = | O5: gross profit - OpEx | Q5: 528594000 | R5: 596081000 | S5: =Q5-R5 -> -67487000 | T5: represents the point on the income statement where all operating costs have been deducted.
A6: Document Period End Date | B6: 44954 | F6: Question | G6: 10-k january | H6: 10q october | M6: 4 | N6: Market Value of Equity(mktcap)= | O6: share price * # Outstanding Shares | Q6: 7.45 | R6: 73761930 | S6: =Q6*R6 -> 5.4952638e+08 | T6: Shows the degree to which a company’s market value would decline when it declares bankruptcy before the value of liabilities exceeds the value of assets on the balance sheet.
A7: Current Fiscal Year End Date | B7: --01-28 | M7: 5 | N7: Current Assets/Liab(-)= | O7: found on balance sheet = | Q7: 598879000 | S7: 613068000 | T7: A high market value of equity to total liabilities ratio can be interpreted to mean high investor confidence in the company’s financial strength.
A8: Document Transition Report | B8: FALSE | N8: Total Assets/Liab(-)= | O8: found on balance sheet = | Q8: 1398325000 | S8: 1090756000 | T8: current assets (liabilities) = liquid assets that can be sold (received) within a year
A9: Entity File Number | B9: 001-34742 | N9: Sales(net sales or rev) | O9: found on balance sheet = | Q9: 1864182000 | T9: Book Value=Total Assets−Total Liabilities
A10: Entity Registrant Name | B10: EXPRESS, INC. | N10: Altman Z-Score = | O10: 1.2ₓ₁ + 1.4ₓ₂ + 3.3ₓ₃ + 0.6ₓ₄ + 1.0ₓ₅
A11: Entity Incorporation, State or Country Code | B11: DE
A12: Entity Tax Identification Number | B12: 26-2828128 | N12: x1= | O12: =S3 -> -556352000 | P12: / | Q12: =Q8 -> 1398325000 | R12: =O12/Q12 -> -0.39787031 | T12: X1 = Working Capital / Total Assets (measures liquidity)
A13: Entity Address, Address Line One | B13: 1 Express Drive | N13: x2= | O13: =S4 -> 355736000 | P13: / | Q13: =Q8 -> 1398325000 | R13: =O13/Q13 -> 0.25440152 | T13: X2 = Retained Earnings / Total Assets
A14: Entity Address, City or Town | B14: Columbus | N14: x3= | O14: =S5 -> -67487000 | P14: / | Q14: =Q8 -> 1398325000 | R14: =O14/Q14 -> -0.048262743 | T14: X3 = Earnings Before Tax and Interest (OI)/ Total Assets (measures how effectively the company uses its assets to get return)
A15: Entity Address, State or Province | B15: OH | N15: x4= | O15: =S6 -> 5.4952638e+08 | P15: / | Q15: =S8 -> 1090756000 | R15: =O15/Q15 -> 0.50380321 | T15: X4 = Market Value of Equity / Total Liabilities (measures the market’s view of the company’s health)
A16: Entity Address, Postal Zip Code | B16: 43230 | N16: x5= | O16: =Q9 -> 1864182000 | P16: / | Q16: =Q8 -> 1398325000 | R16: =O16/Q16 -> 1.3331536 | T16: X5 = Sales / Total Assets (indicated asset turnover)
A17: City Area Code | B17: 614 | G17: Z= | H17: 1.2(
A18: Local Phone Number | B18: 474-4001 | N18: ζ₁= | O18: 1.2 X1 + 1.4 X2 + 3.3 X3 + 0.6 X4 + 1.0 X5 | Q18: = | R18: =SUM(R12:R16) -> 1.6452253 | X18: NYU Stern's Altman Z-score formula in 1967, and it was published in 1968. Over the years, Altman has continued to reevaluate his Z-score. From 1969-1975, Altman looked at 86 companies in distress, then 110 from 1976 to 1995, and finally 120 from 1996 to 1999, finding that the Z-score had an accuracy of between 82% and 94%.
A19: Title of 12(b) Security | B19: Common Stock, $.01 par value
A20: Trading Symbol | B20: EXPR | T20: The formula takes into account profitability, leverage, liquidity, solvency, and activity ratios.
A21: Security Exchange Name | B21: NYSE | T21: Score below 1.8: Suggests a higher risk of financial distress and potential bankruptcy.
A22: Entity Well-known Seasoned Issuer | B22: No | T22: close to 0 suggests a company might be headed for bankruptcy.
A23: Entity Voluntary Filers | B23: No | T23: A score closer to 3 suggests a company is in solid financial positioning
A24: Entity Current Reporting Status | B24: Yes
A25: Entity Interactive Data Current | B25: Yes
A26: Entity Filer Category | B26: Accelerated Filer
A27: Entity Small Business | B27: FALSE | G27: A is the working capital / total assets ratio.
A28: Entity Emerging Growth Company | B28: FALSE | G28: B is the retained earnings / total assets ratio.
A29: ICFR Auditor Attestation Flag | B29: TRUE | G29: C is the earnings before interest and taxes (EBIT) / total assets ratio.
A30: Entity Shell Company | B30: FALSE | G30: D is the market value of equity / total liabilities ratio.
A31: Entity Public Float | D31: 111275008 | G31: E is the sales / total assets ratio.
A32: Entity Common Stock, Shares Outstanding | C32: 73761930
A33: Documents Incorporated by Reference | B33: Certain portions of the registrant's definitive Proxy Statement for its 2023 A
A34: Entity Central Index Key | B34: 1483510
A35: Document Fiscal Year Focus | B35: 2022
A36: Document Fiscal Period Focus | B36: FY
A37: Amendment Flag | B37: FALSE
A38: Audit Information | B38: 12 Months Ended
B39: 44954 | M39: 1. Working Capital/Total Assets
A40: Audit Information [Abstract] | M40: Working capital is the difference between the current assets of a company and its current liabilities. The value of a company’s working capital determines its short-term financial health. A positive working capital means that a company can meet its short-term financial obligations and still make funds available to invest and grow.
A41: Auditor Name | B41: PricewaterhouseCoopers LLP
A42: Auditor Location | B42: Columbus, Ohio | M42: In contrast, negative working capital means that a company will struggle to meet its short-term financial obligations because there are inadequate current assets.
A43: Auditor Firm ID | B43: 238
A44: Consolidated Balance Sheets - USD ($) $ in Thousands | B44: 44954 | C44: 44590 | M44: 2. Retained Earnings/Total Assets
A45: Current Assets: | M45: The retained earnings/total assets ratio shows the amount of retained earnings or losses in a company. If a company reports a low retained earnings to total assets ratio, it means that it is financing its expenditure using borrowed funds rather than funds from its retained earnings. It increases the probability of a company going bankrupt.
A46: Cash and cash equivalents | B46: 65612 | C46: 41176
A47: Receivables, net | B47: 12374 | C47: 11744 | M47: On the other hand, a high retained earnings to total assets ratio shows that a company uses its retained earnings to fund capital expenditure. It shows that the company achieved profitability over the years, and it does not need to rely on borrowings.
A48: Income tax receivable | B48: 1462 | C48: 53665
A49: Inventories | B49: 365649 | C49: 358795 | M49: 3. Earnings Before Interest and Tax/Total Assets
A50: Prepaid royalty | B50: 59565 | C50: 0 | M50: EBIT, a measure of a company’s profitability, refers to the ability of a company to generate profits solely from its operations. The EBIT/Total Assets ratio demonstrates a company’s ability to generate enough revenues to stay profitable and fund ongoing operations and make debt payments.
A51: Prepaid rent | B51: 7744 | C51: 5602
A52: Other | B52: 21998 | C52: 19755 | M52: 4. Market Value of Equity/Total Liabilities
A53: Total current assets | B53: 534404 | C53: 490737 | M53: The market value, also known as market capitalization, is the value of a company’s equity. It is obtained by multiplying the number of outstanding shares by the current price of stocks.
A54: Right of Use Asset, Net | B54: 505350 | C54: 615462
A55: Property and Equipment | B55: 1019577 | C55: 975802 | M55: The market value of the equity/total liabilities ratio shows the degree to which a company’s market value would decline when it declares bankruptcy before the value of liabilities exceeds the value of assets on the balance sheet. A high market value of equity to total liabilities ratio can be interpreted to mean high investor confidence in the company’s financial strength.
A56: Less: accumulated depreciation | B56: -886193 | C56: -827820
A57: Property and equipment, net | B57: 133384 | C57: 147982 | M57: 5. Sales/Total Assets
A58: Non-Current Income Tax Receivable | B58: 52278 | C58: 0 | M58: The sales to total assets ratio shows how efficiently the management uses assets to generate revenues vis-à-vis the competition. A high sales to total assets ratio is translated to mean that the management requires a small investment to generate sales, which increases the overall profitability of the company.
A59: Equity Method Investment | B59: 166106 | C59: 0 | M59: In contrast, a low or falling sales to total assets ratio means that the management will need to use more resources to generate enough sales, which will reduce the company’s profitability.
A60: Other Assets | B60: 6803 | C60: 5273
A61: TOTAL ASSETS | B61: 1398325 | C61: 1259454 | N61: 39weeks = 0.75
A62: Current Liabilities:
A63: Short-term lease liability | B63: 189006 | C63: 196628
A64: Accounts payable | B64: 191386 | C64: 231974 | M64: EXPRESS | N64: Altman Z-score | O64: "Z-Score" model is a numerical measurement that is used to predict the chances of a business becoming bankrupt in the next two years.
A65: Deferred royalty income | B65: 19852 | C65: 0 | M65: 10-k, 1/28/23 | O65: The formula takes into account profitability, leverage, liquidity, solvency, and activity ratios.
A66: Deferred revenue | B66: 35543 | C66: 35985 | M66: Steps: 1 | N66: working capital= | O66: Current Assets − Current Liabilities | Q66: 2323700000 | R66: 1339100000 | S66: =Q66-R66 -> 984600000 | T66: Working capital is a measure of a company's operational liquidity and short-term financial health.
A67: Short-term debt | B67: 0 | C67: 11216 | M67: 2 | N67: Retained Earnings= | O67: Begin Retained Earnings+NI−Dividends | S67: -219500000 | T67: Retained earnings=leftover profit after paying all its direct/indirect costs, taxes & dividends
A68: Accrued expenses | B68: 105803 | C68: 110850 | M68: 3 | N68: EBIT= Operating income = | O68: gross profit - OpEx | Q68: 1372000000 | R68: 55900000 | S68: =Q68-R68 -> 1316100000 | T68: represents the point on the income statement where all operating costs have been deducted.
A69: Total current liabilities | B69: 541590 | C69: 586653 | M69: 4 | N69: Market Value of Equity(mktcap)= | O69: share price * # Outstanding Shares | Q69: 14.51 | R69: 304675439 | S69: =Q69*R69 -> 4420840620 | T69: Shows the degree to which a company’s market value would decline when it declares bankruptcy before the value of liabilities exceeds the value of assets on the balance sheet.
A70: Long-Term Lease Liability | B70: 406448 | C70: 536905 | M70: 5 | N70: Current Assets/Liab(-)= | O70: found on balance sheet = | Q70: 2323700000 | S70: 1339100000 | T70: A high market value of equity to total liabilities ratio can be interpreted to mean high investor confidence in the company’s financial strength.
A71: Long-Term Debt | B71: 122000 | C71: 117581 | N71: Total Assets/Liab(-)= | O71: found on balance sheet = | Q71: 3113400000 | S71: 1791100000 | T71: current assets (liabilities) = liquid assets that can be sold (received) within a year
A72: Other Long-Term Liabilities | B72: 20718 | C72: 17007 | N72: Sales(net sales or rev) | O72: found on balance sheet = | Q72: 5927200000 | T72: Book Value=Total Assets−Total Liabilities
A73: Total Liabilities | B73: 1090756 | C73: 1258146 | N73: Altman Z-Score = | O73: 1.2ₓ₁ + 1.4ₓ₂ + 3.3ₓ₃ + 0.6ₓ₄ + 1.0ₓ₅
A74: Commitments and Contingencies (Note 12)
A75: Stockholders’ Equity: | N75: x1= | O75: =S66 -> 984600000 | P75: / | Q75: =Q71 -> 3113400000 | R75: =O75/Q75 -> 0.3162459 | T75: X1 = Working Capital / Total Assets (measures liquidity)
A76: Preferred stock – $0.01 par value; 10,000 shares authorized; no shares issued or outstanding | B76: 0 | C76: 0 | N76: x2= | O76: =S67 -> -219500000 | P76: / | Q76: =Q71 -> 3113400000 | R76: =O76/Q76 -> -0.070501702 | T76: X2 = Retained Earnings / Total Assets
A77: Common stock – $0.01 par value; 500,000 shares authorized; 99,067 shares and 93,632 shares issued at January 28, 2023 and January 29, 2022, respectively, and 73,760 shares and 67,072 shares outstanding at January 28, 2023 and January 29, 2022, respectively | B77: 990 | C77: 936 | N77: x3= | O77: =S68 -> 1316100000 | P77: / | Q77: =Q71 -> 3113400000 | R77: =O77/Q77 -> 0.42272114 | T77: X3 = Earnings Before Tax and Interest (OI)/ Total Assets (measures how effectively the company uses its assets to get return)
A78: Additional paid-in capital | B78: 228633 | C78: 220078 | N78: x4= | O78: =S69 -> 4420840620 | P78: / | Q78: =S71 -> 1791100000 | R78: =O78/Q78 -> 2.4682266 | T78: X4 = Market Value of Equity / Total Liabilities (measures the market’s view of the company’s health)
A79: Retained earnings | B79: 355736 | C79: 77093 | N79: x5= | O79: =Q72 -> 5927200000 | P79: / | Q79: =Q71 -> 3113400000 | R79: =O79/Q79 -> 1.9037708 | T79: X5 = Sales / Total Assets (indicated asset turnover)
A80: Treasury stock – at average cost; 25,307 shares and 26,560 shares at January 28, 2023 and January 29, 2022, respectively | B80: -277790 | C80: -296799
A81: Total stockholders’ equity | B81: 307569 | C81: 1308 | N81: ζ₁= | O81: 1.2 X1 + 1.4 X2 + 3.3 X3 + 0.6 X4 + 1.0 X5 | Q81: = | R81: =SUM(R75:R79) -> 5.0404627 | X81: NYU Stern's Altman Z-score formula in 1967, and it was published in 1968. Over the years, Altman has continued to reevaluate his Z-score. From 1969-1975, Altman looked at 86 companies in distress, then 110 from 1976 to 1995, and finally 120 from 1996 to 1999, finding that the Z-score had an accuracy of between 82% and 94%.
A82: TOTAL LIABILITIES AND STOCKHOLDERS' EQUITY | B82: 1398325 | C82: 1259454
A83: Consolidated Balance Sheets (Parentheticals) - $ / shares | B83: 44954 | C83: 44590 | T83: The formula takes into account profitability, leverage, liquidity, solvency, and activity ratios.
A84: Statement of Financial Position [Abstract] | T84: Score below 1.8: Suggests a higher risk of financial distress and potential bankruptcy.
A85: Preferred stock, par value (in USD per share) | B85: 0.01 | C85: 0.01 | T85: close to 0 suggests a company might be headed for bankruptcy.
A86: Preferred stock, shares authorized (in shares) | B86: 10000000 | C86: 10000000 | T86: A score closer to 3 suggests a company is in solid financial positioning
A87: Preferred stock, shares issued (in shares) | B87: 0 | C87: 0
A88: Preferred stock, shares outstanding (in shares) | B88: 0 | C88: 0
A89: Common stock, par value (in USD per share) | B89: 0.01 | C89: 0.01
A90: Common stock, shares authorized (in shares) | B90: 500000000 | C90: 500000000
A91: Common stock, shares, issued (in shares) | B91: 99067000 | C91: 93632000
A92: Common stock, shares, outstanding (in shares) | B92: 73760000 | C92: 67072000
A93: Treasury stock, shares at average cost (in shares) | B93: 25307000 | C93: 26560000
A94: Consolidated Statements of Income and Comprehensive Income - USD ($) shares in Thousands, $ in Thousands | B94: 12 Months Ended
B95: 44954 | C95: 44590 | D95: 44226
A96: Income Statement [Abstract]
A97: Net Sales | B97: 1864182 | C97: 1870296 | D97: 1208374
A98: Cost of Goods Sold, Buying and Occupancy Costs | B98: 1335588 | C98: 1311829 | D98: 1213281
A99: GROSS PROFIT/(LOSS) | B99: 528594 | C99: 558467 | D99: -4907 | E99: 528000000
A100: Operating Expenses:
...

Sheet Library
A1: Terminology | E1: random jargon | F1: BOOKS & ARTICLES | G1: coding | H1: HELP
A2: (STM) | E2: Software as a service (SaaS) | F2: Secrets of Successful Traders | G2: web server machine | H2: Simple way to select and edit range
A3: *Revenues Avg3 | E3: INTERPOL wanted list | H3: formula help
A4: 5 C's of Credit | E4: b2b marketing
A5: Absolute return | E5: p2p
A6: Accounts Receivabe >90%ile | E6: chimerical,
A7: accruals | E7: heuristics
A8: Accumulated Depreciation | E8: Complex adaptive systems
A9: Accumulated Other Comprehensive Income (AOCI) | E9: non-linearity
A10: Acid Test Ratio | E10: linear regression
A11: Actionable | E11: decile
A12: Activity-Based Costing | E12: illusory
A13: Adjusted Gross Income | E13: diversity loss
A14: Altman Z' Score | E14: apophenia
A15: Altman Z'' Score | E15: breadth
... A19: Asset Quality Index (AQI) | E19: econometrics
A20: Assets
A21: Assets Revaluation
A22: Assets/sh
A23: Assumptions/Drivers of a Financial Model
A24: Available Core Funding (ACF)
A25: Average inventory
A26: Avg Yield of AAA Corp Bonds
A27: b/p
A28: Balance Sheet LHS
A29: Barriers to entry
A30: base rates
A31: Beachhead
... A291: Net Operating Income (NOI)
A292: Net Present Value (NPV) | F292: DSCR = Net Operating Income/Total Debt Service | H292: NOI | I292: TDS (NetInt-PrincipalPayments)
A293: Net Sales | G293: Operating Revs - Operating Exp | H293: =G294-G295 -> 1268101000 | I293: -1254000000 | J293: =H293/I293 -> -1.0112448
A294: Net Sales | F294: Op Rev | G294: 1864182000
A295: Net-Net /sh | F295: Op Exp | G295: 596081000
A296: Next Twelve Months (NTM)
A297: nn/p | G297: Net Interest Expense | H297: -29103000
A298: Non-Common Equities | G298: Principle Payments | H298: -96737000
A299: Non-Current (Long-Term) Liabilities | H299: =sum(H297+H298) -> -125840000
A300: non-linear financials
A301: Non-Operating Cost
A302: Normalized EBITDA
A303: Note
A304: NTM Revenue
A305: Omega Ratio
A306: Omnichannel
A307: operating assets
A308: Operating Cash Flow (OCF), Cash Flow per share
A309: Operating Cash Flow Sales Ratio
A310: Operating Cost
A311: Operating Cycle
... A496: market tide

Sheet A-Z
A1: Questions to ask about why to buy or sell a stock
A2: Interrogative determiners: Who what where why when can will | E2: 1. Screening Requirements
A3: Bond info | E3: 2. Holding Requirements
A4: quickly see the company’s historical return on equity. | E4: 3. Selling Requirements
A5: I wanted to quickly see how these numbers compare to the other companies in the industry. | E5: -Think about adding data about insiders CEO quality etc
A6: if their profit margin was growing | E6: -Catalysts
A7: show me whether the company can make its debt payments. | E7: -Integrate API
A8: if the stock is undervalued based on a detailed discounted cash flow valuation. | E8: -Intregrate Scrapes
A9: Is the current P/E ratio of 96.82 high or low relative to other online retailers?(AMZN) | E9: -Integrate cashtag mentions from WSB, X etc.
A10: Is it high or low compared to the market average?
A11: Is it high or low compared to 2 years ago?
A12: when is a company with negative earnings a good investnment
A13: Is a stock repurchase ever a bad thing?
A14: Track record of board members, years
A15: How do I figure out the debt payment requirements for a public company
A16: What all should I screen for when choosing companies to invest in?
A17: How has Marks(Oaktree Cap) and his team have generated market-beating returns for decades, mainly by value investing in distressed debt and controlling risks.
A18: Make a tracker that analyzes and charts how a stock tends to move after a particular individual buys the stock.
A19: What does it mean to "buy low"?
A20: Firm is in stable growth; grows at constant rate forever. Domoradan?
A21: OK so lets say there are two companies that enter a strategic parthernship The first company invests 23 million dollars into the second company. The first company receives 5.4 million shares of the second company. the second company has good cash flows but has high debt levels. who got a better deal in this scenario?
... A101: What conditions would mean the federal reserve is not tight enough?

Sheet Data Engineering
A1: Extract, Transform, Load (ETL) | C1: How can you parallelize predictive modeling for big data analytics? | I1: What are irrelevant or redundant features?
A2: Lakehouses | C2: Great use of Figma/PowerPoint background template for rounded edges. | I2: Why remove irrelevant or redundant features?
A3: DataWeave (dw) Format | I3: How to identify irrelevant or redundant features?
A4: XML | I4: How to evaluate the impact of removing irrelevant or redundant features?
A5: A/B testing | I5: Here’s what else to consider
A6: Database Management Systems (DBMS)
A7: DataOps | I7: You want to be able to analyze the data with a multi-cloud data tool that is inexpensive, fast, and does not create additional overhead of decentralized data governance. By using BigQuery Omni, we reduce these frictions with a unified interface.
A8: data engineering
A9: Hard Skills vs Soft Skills
A10: Causal Inference
A11: pedagogy
A12: Third Normal Form
A13: ERP
A14: siloed
A15: SDK
A16: DML statements

Sheet Valuation
A1: Graham's Valuation | B1: A Stock-Picker’s Guide to Benjamin Graham’s Screening Rules | E1: V = EPS x (8.5 + 2g) x 4.4 / Y | I1: shares in millions instead of thousands15552752000000 | K1: =8.5+17 -> 25.5
A2: Ticker | B2: expr | G2: 1000000
A3: P/e ttm? | B3: =IFERROR(__xludf.DUMMYFUNCTION("GOOGLEFINANCE(B2,""pe"")"),"#N/A") -> #N/A | D3: current price | E3: =IFERROR(__xludf.DUMMYFUNCTION("GOOGLEFINANCE(B2,""price"")"),"#N/A") -> #N/A | F3: latest earnings(net income) | G3: 96995000000 | H3: latest OS #: | I3: 15552752000
A4: Earnings Yield (e/p) | B4: =1/B3 -> #N/A
A5: EPS google finance | B5: =IFERROR(__xludf.DUMMYFUNCTION("GOOGLEFINANCE(B2, ""eps"")"),"#N/A") -> #N/A | G5: EPS | H5: =G3/I3 -> 6.2365169 | J5: V= | K5: =K4/4.77 -> 0
A6: P/e No Growth(0%) | B6: 8.5 | G6: P/e | H6: =E3/H5 -> #N/A
A7: Growth Rate???? | B7: 8.5 | E7: 50.3*17*4.4 | F7: %🔺 Current price/intrinsic value
A8: 2 g: | B8: =2*(B7) -> 17 | G8: Buy or Sell: | H8: =If(H7>H4,"Buy","Sell") -> Sell
A9: Avg Yield AAA bond: | B9: 4.64
A10: Y=Moodys Seasoned AAA | B10: 4.77
B11: =11+17 -> 28
A12: EPS*(P/e(nogrowth=8.5)*2g)*Avg Yield AA | B12: =(B5)*(B6+B8)*(B9) -> #N/A
A13: V, Intrinsic Value= | B13: =B12/B10 -> #N/A | E13: Asmoradan Advanced Valuation Ratios
A14: Stock Price | B14: =IFERROR(__xludf.DUMMYFUNCTION("GOOGLEFINANCE(B2,""price"")"),"#N/A") -> #N/A
A15: %🔺 Current price/intrinsic value | B15: =B14/B13 -> #N/A
A16: Margin of Safety(65%)Acceptable buy price | B16: =B13*0.65 -> #N/A
A17: Buy or Sell: | B17: =If(B16>B13,"Buy","Sell") -> #N/A
A19: GRahams REvised Valuation formula
A21: 1 | B21: In finance, valuation is the process of determining the value of a (potential) investment, asset, or security. Generally, there are three approaches taken, namely discounted cashflow valuation, relative valuation, and contingent claim valuation.[1] Valuations can be done for assets (for example, investments in marketable securities such as companies' shares and related rights, business enterprises, or intangible assets such as patents, data and trademarks) or for liabilities (e.g., bonds issued by a company). Valuation is a subjective exercise, and in fact, the process of valuation itself can also affect the value of the asset in question. Valuations may be needed for various reasons such as investment analysis, capital budgeting, merger and acquisition transactions, financial reporting, taxable events to determine the proper tax liability. In a business valuation context, various techniques are used to determine the (hypothetical) price that a third party would pay for a given company; while in a portfolio management context, stock valuation is used by analysts to determine the price at which the stock is fairly valued relative to its projected and historical earnings, and to thus profit from related price movement.
A22: 2 | B22: Valuation overview Common terms for the value of an asset or liability are market value, fair value, and intrinsic value. The meanings of these terms differ. For instance, when an analyst believes a stock's intrinsic value is greater (or less) than its market price, an analyst makes a "buy" (or "sell") recommendation. Moreover, an asset's intrinsic value may be subject to personal opinion and vary among analysts. The International Valuation Standards include definitions for common bases of value and generally accepted practice procedures for valuing assets of all types. Regardless, the valuation itself is done generally using one or more of the following approaches;[2] but see also, Outline of finance § Valuation: Absolute value models ("Intrinsic valuation") that determine the present value of an asset's expected future cash flows. These models take two general forms: multi-period models such as discounted cash flow models, or single-period models such as the Gordon model (which, in fact, often "telescope" the former). These models rely on mathematics rather than price observation. See § Discounted cash flow valuation there. Relative value models determine value based on the observation of market prices of 'comparable' assets, relative to a common variable like earnings, cashflows, book value or sales. This result will often be used to complement / revisit the intrinsic valuation. See § Relative valuation there. Option pricing models, in this context, are used to value specific balance-sheet items, or the asset itself, when these have option-like characteristics. Examples of the first type are warrants, employee stock options, and investments with embedded options such as callable bonds; the second type are usually real options. The most common option pricing models employed here are the Black–Scholes-Merton models and lattice models. This approach is sometimes referred to as contingent claim valuation, in that the value will be contingent on some other asset; see § Contingent claim valuation there.
A23: 3 | B23: Usage In finance, valuation analysis is required for many reasons including tax assessment, wills and estates, divorce settlements, business analysis, and basic bookkeeping and accounting. Since the value of things fluctuates over time, valuations are as of a specific date like the end of the accounting quarter or year. They may alternatively be mark-to-market estimates of the current value of assets or liabilities as of this minute or this day for the purposes of managing portfolios and associated financial risk (for example, within large financial firms including investment banks and stockbrokers). Some balance sheet items are much easier to value than others. Publicly traded stocks and bonds have prices that are quoted frequently and readily available. Other assets are harder to value. For instance, private firms that have no frequently quoted price. Additionally, financial instruments that have prices that are partly dependent on theoretical models of one kind or another are difficult to value and this generates valuation risk. For example, options are generally valued using the Black–Scholes model while the liabilities of life assurance firms are valued using the theory of present value. Intangible business assets, like goodwill and intellectual property, are open to a wide range of value interpretations. Another intangible asset, data, is increasingly being recognized as a valuable asset in the information economy.[3] It is possible and conventional for financial professionals to make their own estimates of the valuations of assets or liabilities that they are interested in. Their calculations are of various kinds including analyses of companies that focus on price-to-book, price-to-earnings, price-to-cash-flow and present value calculations, and analyses of bonds that focus on credit ratings, assessments of default risk, risk premia, and levels of real interest rates. All of these approaches may be thought of as creating estimates of value that compete for credibility with the prevailing share or bond prices, where applicable, and may or may not result in buying or selling by market participants. Where the valuation is for the purpose of a merger or acquisition the respective businesses make available further detailed financial information, usually on the completion of a non-disclosure agreement. Valuation requires judgment and assumptions: There are different circumstances and purposes to value an asset (e.g., distressed firm, tax purposes, mergers and acquisitions, financial reporting). Such differences can lead to different valuation methods or different interpretations of the method results All valuation models and methods have limitations (e.g., degree of complexity, relevance of observations, mathematical form) Model inputs can vary significantly because of necessary judgment and differing assumptions Users of valuations benefit when key information, assumptions, and limitations are disclosed to them. Then they can weigh the degree of reliability of the result and make their decision.
A24: 4 | B24: Business valuation Main article: Business valuation Businesses or fractional interests in businesses may be valued for various purposes such as mergers and acquisitions, sale of securities, and taxable events. When correct, a valuation should reflect the capacity of the business to match a certain market demand, as it is the only true predictor of future cash flows. An accurate valuation of privately owned companies largely depends on the reliability of the firm's historic financial information. Public company financial statements are audited by Certified Public Accountants (USA), Chartered Certified Accountants (ACCA) or Chartered Accountants (UK), and Chartered Professional Accountants (Canada) and overseen by a government regulator. Alternatively, private firms do not have government oversight—unless operating in a regulated industry—and are usually not required to have their financial statements audited. Moreover, managers of private firms often prepare their financial statements to minimize profits and, therefore, taxes. Alternatively, managers of public firms tend to want higher profits to increase their stock price. Therefore, a firm's historic financial information may not be accurate and can lead to over- and undervaluation. In an acquisition, a buyer often performs due diligence to verify the seller's information. Financial statements prepared in accordance with generally accepted accounting principles (GAAP) show many assets based on their historic costs rather than at their current market values. For instance, a firm's balance sheet will usually show the value of land it owns at what the firm paid for it rather than at its current market value. But under GAAP requirements, a firm must show the fair values (which usually approximates market value) of some types of assets such as financial instruments that are held for sale rather than at their original cost. When a firm is required to show some of its assets at fair value, some call this process "mark-to-market". But reporting asset values on financial statements at fair values gives managers ample opportunity to slant asset values upward to artificially increase profits and their stock prices. Managers may be motivated to alter earnings upward so they can earn bonuses. Despite the risk of manager bias, equity investors and creditors prefer to know the market values of a firm's assets—rather than their historical costs—because current values give them better information to make decisions. There are commonly three pillars to valuing business entities: comparable company analyses, discounted cash flow analysis, and precedent transaction analysis. Business valuation credentials include the Chartered Business Valuator (CBV) offered by the CBV Institute, ASA and CEIV from the American Society of Appraisers, and the CVA by the National Association of Certified Valuators and Analysts. Discounted cash flow method Main article: Valuation using discounted cash flows This method estimates the value of an asset based on its expected future cash flows, which are discounted to the present (i.e., the present value). This concept of discounting future money is commonly known as the time value of money. For instance, an asset that matures and pays $1 in one year is worth less than $1 today. The size of the discount is based on an opportunity cost of capital and it is expressed as a percentage or discount rate. In finance theory, the amount of the opportunity cost is based on a relation between the risk and return of some sort of investment. Classic economic theory maintains that people are rational and averse to risk. They, therefore, need an incentive to accept risk. The incentive in finance comes in the form of higher expected returns after buying a risky asset. In other words, the more risky the investment, the more return investors want from that investment. Using the same example as above, assume the first investment opportunity is a government bond that will pay interest of 5% per year and the principal and interest payments are guaranteed by the government. Alternatively, the second investment opportunity is a bond issued by small company and that bond also pays annual interest of 5%. If given a choice between the two bonds, virtually all investors would buy the government bond rather than the small-firm bond because the first is less risky while paying the same interest rate as the riskier second bond. In this case, an investor has no incentive to buy the riskier second bond. Furthermore, in order to attract capital from investors, the small firm issuing the second bond must pay an interest rate higher than 5% that the government bond pays. Otherwise, no investor is likely to buy that bond and, therefore, the firm will be unable to raise capital. But by offering to pay an interest rate more than 5% the firm gives investors an incentive to buy a riskier bond. For a valuation using the discounted cash flow method, one first estimates the future cash flows from the investment and then estimates a reasonable discount rate after considering the riskiness of those cash flows and interest rates in the capital markets. Next, one makes a calculation to compute the present value of the future cash flows. Guideline companies method Main article: Comparable company analysis This method determines the value of a firm by observing the prices of similar companies (called "guideline companies") that sold in the market. Those sales could be shares of stock or sales of entire firms. The observed prices serve as valuation benchmarks. From the prices, one calculates price multiples such as the price-to-earnings or price-to-book ratios—one or more of which used to value the firm. For example, the average price-to-earnings multiple of the guideline companies is applied to the subject firm's earnings to estimate its value. Many price multiples can be calculated. Most are based on a financial statement element such as a firm's earnings (price-to-earnings) or book value (price-to-book value) but multiples can be based on other factors such as price-per-subscriber. Net asset value method The third-most common method of estimating the value of a company looks to the assets and liabilities of the business. At a minimum, a solvent company could shut down operations, sell off the assets, and pay the creditors. Any cash that would remain establishes a floor value for the company. This method is known as the net asset value or cost method. In general the discounted cash flows of a well-performing company exceed this floor value. Some companies, however, are worth more "dead than alive", like weakly performing companies that own many tangible assets. This method can also be used to value heterogeneous portfolios of investments, as well as nonprofits, for which discounted cash flow analysis is not relevant. The valuation premise normally used is that of an orderly liquidation of the assets, although some valuation scenarios (e.g., purchase price allocation) imply an "in-use" valuation such as depreciated replacement cost new. An alternative approach to the net asset value method is the excess earnings method. (This method was first described in the U.S. Internal Revenue Service's Appeals and Review Memorandum 34,[further explanation needed] and later refined by Revenue Ruling 68-609.) The excess earnings method has the appraiser identify the value of tangible assets, estimate an appropriate return on those tangible assets, and subtract that return from the total return for the business, leaving the "excess" return, which is presumed to come from the intangible assets. An appropriate capitalization rate is applied to the excess return, resulting in the value of those intangible assets. That value is added to the value of the tangible assets and any non-operating assets, and the total is the value estimate for the business as a whole. See Clean surplus accounting, Residual income valuation.
B25: Specialised cases The approaches to valuation, as outlined, are generic and will be modified for the unique positioning and characteristics [4] of the business in question. [5] In the below cases, however, more specific valuation-practices have developed [6] within the investment industry. For these, more than elsewhere, real options valuation may be applied. [7] Valuation of a suffering company Investors in a suffering company, or in other "distressed securities", may intend (i) to restructure the business, with the valuation reflecting its potential thereafter, or (ii) to purchase the company - or its debt - at a discount, as part of an Investment Strategy aimed at realizing a profit on recovery. Preliminary to the valuation, the financial statements are initially recast, to "better reflect the firm's indebtedness, financing costs and recurring earnings".[8] Here adjustments are made to working capital, deferred capital expenditures, cost of goods sold, non-recurring professional fees and costs, above- or below-market leases, excess salaries in the case of private companies, and certain non-operating income/expense items.[9] The valuation is built on this base, with any of the standard market-, income-, or asset-based approaches employed. Often these are used in combination, providing a "triangulation" or (weighted) average. Particularly in the second case above, the company may be valued using real options analysis, serving to complement (or sometimes replace) this standard value; see Business valuation § Option pricing approaches and Merton model. As required, various adjustments are then made to this result, so as to reflect characteristics of the firm external to its profitability and cash flow. These adjustments consider any lack of marketability resulting in a discount, and re the stake in question, any control premium or lack of control discount. Balance sheet items external to the valuation, but due to the new owners, are similarly recognized; these include excess (or restricted) cash, and other non-operating assets and liabilities. Valuation of a startup company Startup companies such as Uber, which was valued at $50 billion in early 2015, are assigned post-money valuations based on the price at which their most recent investor put money into the company. The price reflects what investors, for the most part venture capital firms, are willing to pay for a share of the firm. They are not listed on any stock market, nor is the valuation based on their assets or profits, but on their potential for success, growth, and eventually, possible profits.[10] Many startup companies use internal growth factors to show their potential growth which may attribute to their valuation. The professional investors who fund startups are experts, but hardly infallible, see Dot-com bubble.[11] Valuation using discounted cash flows discusses various considerations here. The valuation of early-stage startups can be more nuanced due to their lack of established track records. One common approach is using comparative valuations, although this method can be less accurate given the uniqueness of each startup.[12] Some methods adjust the average pre-money valuation of pre-revenue startups based on various attributes within the same market.[13] Average pre-money valuations in a particular region or sector, obtained from recent market deals, can also serve as reference points.[14] During Series A funding rounds, the typical valuation for startups is reported to be between $10 million to $15 million[15] Valuation of intangible assets Valuation models can be used to value intangible assets such as for patent valuation, but also in copyrights, software, trade secrets, and customer relationships.[16] As economies are becoming increasingly informational, it is recognized that there is a need for new methods to value data, another intangible asset. Valuations here are often necessary both for financial reporting and intellectual property transactions. They are also inherent in securities analysis - listed and private - in cases where analysts must estimate the incremental contribution of patents (etc) to equity value; see next paragraph. Since few sales of benchmark intangible assets can ever be observed, one often values these sorts of assets using either a present value model, or by estimating the cost of recreating the asset in question. In some cases,[17] option-based techniques or decision trees may be applied. Regardless of the method, the process is often time-consuming and costly. If required, stock markets can give an indirect estimate of a corporation's intangible asset value: this can be reckoned as the difference between its market capitalisation and its book value (including only hard assets), i.e. effectively its goodwill; see also PVGO. As regards listed equity, the above techniques are most often applied in the biotech-, life sciences- and pharmaceutical sectors [18] [19] [20] (see List of largest biotechnology and pharmaceutical companies). These businesses are involved in research and development (R&D), and testing, that typically takes years to complete, and where the new product may ultimately not be approved (see Contingent value rights). Industry specialists thus apply the above techniques - and here especially rNPV - to the pipeline of products under development, and, at the same time,[16] also estimate the impact on existing revenue streams due to expiring patents. For relative valuation,[18] a specialized ratio is R&D spend as a percentage of sales. Similar analysis may be applied to options on films re the valuation of film studios. Valuation of mining projects Further information: Mineral economics, Mineral resource estimation, and Mineral resource classification In mining, valuation is the process of determining the value or worth of a mining property - i.e. as distinct from a listed mining corporate. Mining valuations are sometimes required for IPOs, fairness opinions, litigation, mergers and acquisitions, and shareholder-related matters. In valuing a mining project or mining property, fair market value is the standard of value to be used. In general, [21] this result will be a function of the property's "reserve" - the estimated size and grade of the deposit in question - and the complexity and costs of extracting this.[22] [23] "CIMVal" generally applied by the Toronto Stock Exchange, is widely recognised as a "standard" for the valuation of mining projects. (CIMVal: Canadian Institute of Mining, Metallurgy and Petroleum on Valuation of Mineral Properties [24]) The Australasian equivalent is VALMIN; the Southern African is SAMVAL. These standards stress the use of the cost approach, market approach, and the income approach, depending on the stage of development of the mining property or project; see [25] for further discussion and context. Real Options analysis [26] [27] is sometimes [21] [25] [26] used when there is a need to evaluate the project under different scenarios from inception. Analyzing listed mining corporates (and other resource companies) is also specialized,[22] as the valuation requires a good understanding of the company's overall assets, its operational business model as well as key market drivers,[28] and an understanding of that sector of the stock market.[22] Re the latter, a distinction is usually made based on size and financial capabilities; see Mining § Corporate classifications. The price of a "Junior" mining stock, typically having one asset, will at its early stages be linked to the result of its feasibility study; later, the price will be a function of that mine's viability and value, largely applying the above techniques. A "Major", on the other hand, has numerous properties, and the contents of any single deposit will impact stock value in a limited fashion; this due to diversification, access to funding, and, also, since the share price inheres goodwill. Typically, then, the exposure is more to the market value of each mineral in the portfolio, than to the individual properties. Valuing financial services firms There are two main difficulties with valuing financial services firms. [29] [30] [31] [32] The first is that the cash flows to a financial service firm cannot be easily estimated, since capital expenditures, working capital and debt are not clearly defined: "debt for a financial service firm is more akin to raw material than to a source of capital; the notion of cost of capital and enterprise value (EV) may be meaningless as a consequence."[29] (See related discussion re. the risk management of financial- vs non-financial firms.) The second is that these firms operate under a highly regulated environment, and valuation assumptions (and model outputs) must incorporate regulatory limits, at least as "bounds".[32] The approach taken for a DCF valuation, is to then "remove" debt from the valuation, by discounting free cash flow to equity at the cost of equity (or equivalently to apply a modified dividend discount model). This is in contrast to the more typical approach of discounting free cash flow to the Firm where EBITDA less capital expenditures and working capital is discounted at the weighted average cost of capital, which incorporates the cost of debt. For a multiple based valuation, similarly, price to earnings is preferred to EV/EBITDA. Here, there are also industry-specific measures used to compare between investments and within sub-sectors; this, once normalized by market cap (or other appropriate result), and recognizing regulatory differences: Insurance companies: embedded value and actuarial reserves Banking sector: net interest margin and provision for credit losses Wealth- and investment management firms: assets under management Investment banks: price to tangible book value and return on tangible equity.
B26: Mismarking Further information: Product control and Mark-to-market accounting Mismarking in securities valuation takes place when the value that is assigned to securities does not reflect what the securities are actually worth, due to intentional fraudulent mispricing.[33][34][35] Mismarking misleads investors and fund executives about how much the securities in a securities portfolio managed by a trader are worth (the securities' net asset value, or NAV), and thus misrepresents performance.[36][37][38] When a rogue trader engages in mismarking, it allows him to obtain a higher bonus from the financial firm for which he works, where his bonus is calculated by the performance of the securities portfolio that he is managing.[36][37]

Sheet calc
A1: =IFERROR(__xludf.DUMMYFUNCTION("importxml(""https://en.wikipedia.org/wiki/Benjamin_Graham_formula"",""/html/body/div[2]/div/div[3]/main/div[3]/div[3]/div[1]/p[1]/b"")"),"#N/A") -> #N/A
A2: /html/body/div/table[2]
A3: /html/body/div/table[2]
A4: <ix:nonfraction unitref="usd" contextref="c-1" decimals="-6" name="us-gaap:CostOfGoodsAndServicesSold" format="ixt:num-dot-decimal" scale="6" id="f-78">214,137</ix:nonfraction>
A5: <table summary="">
A6: <table summary="">
A7: <tbody><tr bgcolor="#D6D6D6">
A8: <th align="left" nowrap="nowrap" width="4%">Accepted</th>
A9: <th align="left" nowrap="nowrap" width="4%">Filing Date</th>
A10: <th align="left" nowrap="nowrap" width="4%">Form</th>
A11: <th align="left" nowrap="nowrap" width="4%">Formats</th>
A12: <th align="left" width="40%">Description</th>
A13: full xpath
... A18: IMPORTXML("https://www.sec.gov/cgi-bin/browse-edgar?action=getcurrent", "xmlDoc.evaluate()")
A19: IMPORTXML(URL, XPath expression | I19: =IFERROR(__xludf.DUMMYFUNCTION("IF(NOT(ISBLANK(I13)), importhtml(secData(I13),""table"",1), """")"),"")
A20: IMPORTXML(URL, XPath expression)
A21: =IFERROR(__xludf.DUMMYFUNCTION("IMPORTXML(""https://www.browserstack.com/guide/xpath-locators-cheat-sheet"",""/html/body/div[2]/main/section/article/div[1]/div/div/div[1]/h1"")"),"#N/A") -> #N/A
A22: var i = 1; [].forEach.call(document.getElementsByTagName("table"). function(x) {console.log(i++, x); });
A23: xmlDoc.evaluate(xpath, xmlDoc, null, XPathResult.ANY_TYPE,null);
A24: =IFERROR(__xludf.DUMMYFUNCTION("IMPORTXML(""https://www.sec.gov/ix?doc=/Archives/edgar/data/320193/000032019323000106/aapl-20230930.htm#i1cb1ba018cb1455aa66bd3f9ab0c5b1a_73"",""/html/body/div[1]/div[7]/div[481]/table/tbody/tr[7]/td[2]/span/span/ix:nonfraction"")"),"#N/A") -> #N/A
A25: =IFERROR(__xludf.DUMMYFUNCTION("IMPORTXML(""https://www.sec.gov/ix?doc=/Archives/edgar/data/320193/000032019323000106/aapl-20230930.htm#i1cb1ba018cb1455aa66bd3f9ab0c5b1a_73"",""/html/body/div[1]/div[7]/div[481]/table/tbody/tr[7]/td[2]/span/span/ix:nonfraction"")"),"#N/A") -> #N/A
A26: =IMPORTHTML("https://www.sec.gov/Archives/edgar/data/320193/000032019323000106/aapl-20230930.htm","<td colspan="2" style="background-color:#ffffff;border-top:1pt solid #000000;padding:2px 0 2px 1pt;text-align:right;vertical-align:bottom"><span style="color:#000000;font-family:'Helvetica',sans-serif;font-size:9pt;font-weight:400;line-height:100%"><ix:nonfraction unitref="usd" contextref="c-1" decimals="-6" name="us-gaap:CostOfGoodsAndServicesSold" format="ixt:num-dot-decimal" scale="6" id="f-78">214,137</ix:nonfraction>&nbsp;</span></td>") -> #ERROR!
A27: =IFERROR(__xludf.DUMMYFUNCTION("IMPORTHTML(""https://www.sec.gov/Archives/edgar/data/320193/000032019323000106/aapl-20230930.htm"",""list"",""table"",2)"),"#VALUE!") -> #VALUE!
A28: =IFERROR(__xludf.DUMMYFUNCTION("IMPORTXML(""https://www.sec.gov/Archives/edgar/data/320193/000032019323000106/aapl-20230930.html"",""/html/body/div[481]/table/tbody/tr[13]/td[2]/span/ix:nonfraction"")"),"#N/A") -> #N/A
A29: =IFERROR(__xludf.DUMMYFUNCTION("IMPORTDATA()"),"#N/A") -> #N/A
A30: =IFERROR(__xludf.DUMMYFUNCTION("IMPORTXML(""https://phish.wpenginepowered.com/wp-content/uploads/2023/01/Phish-RM-SOCIALS_FINAL_JM.jpg"",""/html/body/div[1]/div"")"),"#N/A") -> #N/A
A31: =IFERROR(__xludf.DUMMYFUNCTION("IMPORTXML(""https://www.phish.com"",""/html/body/div[1]/div/img"")"),"#N/A") -> #N/A
A32: =IFERROR(__xludf.DUMMYFUNCTION("importhtml(SEC(),""table"",1)"),"#N/A") -> #N/A
A33: =IFERROR(__xludf.DUMMYFUNCTION("IMPORTXML(""https://www.phish.com"",""/html/body/div[1]/div/img"")"),"#N/A") -> #N/A
A34: =IFERROR(__xludf.DUMMYFUNCTION("GOOGLEFINANCE(""ET"",""netassets"")"),"#N/A") -> #N/A
A35: =IFERROR(__xludf.DUMMYFUNCTION("query(sort( ARRAYFORMULA(IFerror(Vlookup(Unique(sort(filter(db!A36:A1000,db!Q36:Q1000=""yes""))),Sort(db!A36:Z1000,24,0,2,0),{1,2,3,4,5,6,7,8,9,10,11,12,13,14,15,16,17,18,19,20,21,22,23,24},0),)),4,1,5,1,6,1,9,0),""select * where Col17 = 'yes'"")"),"#N/A") -> #N/A
A36: =IFERROR(__xludf.DUMMYFUNCTION("importhtml(SEC(),""table"",1)"),"#N/A") -> #N/A
A37: =IFERROR(__xludf.DUMMYFUNCTION("IF(NOT(ISBLANK(A31)), importhtml(secData(A31),""table"",1), """")"),"#ERROR!") -> #ERROR!
A38: =IFERROR(__xludf.DUMMYFUNCTION("IMPORTXML("""", ""//a/@href"")"),"#VALUE!") -> #VALUE!
A39: =IFERROR(__xludf.DUMMYFUNCTION("IMPORTXML(""https://www.sec.gov/spotlight/xbrl/filings-and-feeds.shtml"",)"),"#VALUE!") -> #VALUE!
A40: =IFERROR(__xludf.DUMMYFUNCTION("query(sort( ARRAYFORMULA(IFerror(Vlookup(Unique(sort(filter(db!A41:A1000,db!Q41:Q1000=""yes""))),Sort(db!A41:Z1000,24,0,2,0),{1,2,3,4,5,6,7,8,9,10,11,12,13,14,15,16,17,18,19,20,21,22,23,24},0),)),4,1,5,1,6,1,9,0),""select * where Col17 = 'yes'"")"),"#N/A") -> #N/A
A41: {=index(html!G200:$G1000,match(B24,html!A200:$A1000,0))} -> #REF!
A42: SPARKLINE(
A43: Query
A44: INDEX(A1:D6, MATCH(2, D1:D6, 0), MATCH("Guest Name", A1:D1, 0))
A46: INDEX and MATCH can be used together to perform more advanced and dynamic lookups.
B47: J
A48: Tip: VLOOKUP can be used when the lookup value is to the left of the desired attribute to return. INDEX and MATCH can be used regardless of where the lookup value is located in the dataset. | B48: Balance on 3/21: | C48: 2231
A49: LoopStdDev(“Sales(Ctr,Qtr)”,12,0). Yuval Taylor:Portfolio123 | C49: 7600 | D49: 4 lbs @ 1900
A50: IMPORTXML("https://finance.yahoo.com/quote/"&B2,"/html/body/div[1]/div/div/div[1]/div/div[2]/div/div/div[5]/div/div/div/div[3]/div[1]/div[1]/fin-streamer[1]") | C50: 125 | D50: 1/2 oz @ 250
A51: =REGEXEXTRACT() | C51: 245 | D51: 7 carts @ $37
A52: =IF(ISBLANK(H513), INDEX(A!$A$1:$A$10000, 2, 8), "") | C52: 60 | D52: 1 cart live reson
A53: {=IF(ISBLANK(C53), INDEX(BBB!$A$1000:$AB$10000, 2, 8), "")} | C53: 150 | D53: 5 carts @ $30
C54: 70 | D54: 1 rosin cart
A55: =IF(ISBLANK(G533), VLOOKUP(ABC!$A:$Z, $A$Z, MATCH("Sector", ABC!$1:$1, 0), FALSE), "") | B55: delivered on 3/25 | C55: 700 | D55: 70g wax (2.5 oz) | E55: 7/19 balance was $10,481 before the wax, you said the balance was 8200 but forgot to include the 70g wax in new balance
A56: =IF(ISBLANK(G533) | C56: -2281 | D56: PAYMENT (3/25ish)
A57: =IF(ISBLANK(H516), INDEX(A!$B:$Z, MATCH(INDEX(A!$A:$Z, ROW()), A!$B$1:$Z$1, 0), MATCH("Industry", A!$B$1:$Z$1, 0)), "") | B57: Balance on 3/25 | C57: =SUM(C48:C56) -> 8900
A59: =IF(ISBLANK(H517), INDEX(A!$B:$Z, MATCH(INDEX(A!$A:$Z, ROW()), A!$B$1:$Z$1, 0), MATCH("Industry", A!$B$1:$Z$1, 0)), "") | B59: Transactions | C59: =5*28*10 -> 1400 | D59: 5 oz wax | E59: july 11th asked about guy in town with wax and when i can send carts
A60: =IF(ISBLANK(H519), INDEX(A!$A$1:$Z$10, 2, 8), "") | C60: 160 | D60: 2 oz mushroom 80/oz
A61: {=IF(ISBLANK(C61), INDEX(BBB!$A$1:$AB$10000, 2, 8), "")} | C61: =15*37 -> 555 | D61: 15 carts @ $37
A62: =IF(ISBLANK(G533), VLOOKUP(ABC!$A:$Z, $A$Z, MATCH("Sector", ABC!$1:$1, 0), FALSE), "") | C62: 1900 | D62: 1 lb @ 1900
A63: =IF(ISBLANK(G533) | C63: =3*-400 -> -1200 | D63: (Flower Adjustment) 3@ -400
A64: =IF(ISBLANK(H523), INDEX(A!$B:$Z, MATCH(INDEX(A!$A:$Z, ROW()), A!$B$1:$Z$1, 0), MATCH("Industry", A!$B$1:$Z$1, 0)), "") | C64: -2000 | D64: PAYMENT 1/23
A65: =IF(ISBLANK(H523), INDEX(A!$B:$Z, MATCH(INDEX(A!$A:$Z, ROW()), A!$B$1:$Z$1, 0), MATCH("Industry", A!$B$1:$Z$1, 0)), "") | C65: 360 | D65: 3 oz from Chris
A66: =IFERROR(IF(INDEX('sheetAAA'!$A:$A, MATCH(A530, BBB!$A:$A, 0)) = #REF!, VLOOKUP(#REF!, BBB!$A:$Z, MATCH("Sector", BBB!$1:$1, 0), FALSE), ""), "") | C66: =SUM(C59:C65)+8900 -> 10075 | D66: CURRENT BALANCE
A67: =IF(ISBLANK(G543), (INDEX('CIK screener'!$A:$A, MATCH(A543, ABC!$A:$A, 0)) = A2, VLOOKUP(A2, ABC!$A:$Z, MATCH("Sector", ABC!$1:$1, 0), FALSE), ""), "")
A68: =IF(ISBLANK(G543), (INDEX('CIK screener'!$A:$A, MATCH(A543, ABC!$A:$A, 0)) = A2, VLOOKUP(A2, ABC!$A:$Z, MATCH("Sector", ABC!$1:$1, 0), FALSE), ""), "")
A69: =IF(ISBLANK(G527), (INDEX(A!$A1:$Z1, MATCH(CIK screener!$A2$A12000,$I1:$I1000, 0)) = A2, VLOOKUP(A2, ABC!$A:$Z, MATCH("Sector", ABC!$1:$1, 0), FALSE)), "") | B69: Kirby | C69: 5790
A70: =IF(ISBLANK(I520), INDEX(A!$A$1:$Z$10000, 2, 8), "") | C70: -3600 | D70: 3/24 Payment
C71: 970 | D71: 232g super soaker | G71: J | H71: 10075
C72: 865 | D72: 204g soap | G72: K | H72: 6318
C73: 2293 | D73: 540.8g gg | G73: B | H73: 14940
C74: =SUM(C69:C73) -> 6318 | D74: BALANCE | G74: B | H74: 475
G75: T | H75: 2169
G76: RL | H76: 5550
G77: MW | H77: 21030
B78: Balthrop | G78: AD | H78: 4000
C79: 13300 | D79: Balance | G79: CR | H79: 1065
C80: 1269 | D80: 11/28 carts | G80: RC | H80: 6000
C81: 731 | D81: 9 oz squat mac | H81: =SUM(H71:H80) -> 71622 | J81: 71622 | K81: owed in
C82: -360 | D82: -3ozj | J82: 34640 | K82: next run total price
C83: =SUM(C79:C82) -> 14940 | D83: BALANCE | J83: 3500
G84: =9*2000 -> 18000 | H84: 9@2000 | J84: 300
B85: Brad | C85: 475 | D85: BALANCE | G85: =5*1900 -> 9500 | H85: 5@1900 | J85: 560 | K85: remaining mushroom
G86: =5*1260 -> 6300 | H86: 5outdoor | J86: =SUM(J81:J85) -> 110622 | K86: TOTAL ASSETS?
G87: =700+70+70 -> 840 | H87: 1oz rosin+2g wax | J87: 16000 | K87: TOTAL LIAB(DEBT)
B88: Toe | C88: 111 | G88: =SUM(G84:G87) -> 34640 | J88: =J86-J87 -> 94622
C89: 456 | J89: 40000 | K89: STOCK
C90: 116 | J90: =SUM(J88:J89) -> 134622 | K90: TOTAL EQUITY
C91: 52
C92: 128
C93: 246
C94: 70
C95: 40 | D95: =SUM(C88:C95) -> 1219
C96: 950
C97: =SUM(C88:C96) -> 2169 | D97: BALANCE
B99: RoLe | C99: 3800
C100: 1750
C101: 5550 | D101: BALANCE
B106: Matt | C106: 23030
C107: -2000 | D107: transfer 1 lb gg plus 100 credit
C108: =SUM(C106:C107) -> 21030 | D108: BALANCE
B111: Chad
C112: 880 | D112: 4 oz(2@200,2@240)
C113: -615 | D113: payment in records
...

Sheet EARNINGS

Sheet OPTIONS
A1: You might consider using a long vega trade if you think vol is low and could revert higher, or a short vega trade if you think vol is high and could revert lower.

Sheet SNAPdash
A1: Company
A2: TICKER | C2: Year
A3: Company | C3: Period Ending
A4: Sector | C4: Outstanding shares
A5: Subsector? | C5: Gross Margin | D5: Revenues
C6: Shareholders' Equity
C7: Book Value
C8: Book Value per Share | F8: Zombie Meter
A9: Stock Price | C9: EBITDA Margin | D9: Revs Avg3 | F9: Z'' Score | H9: Balance Sheet LHS
A10: market cap | C10: EBIT Margin | D10: Turnover Avg3 | F10: *CFO Avg3 / Net Com Ove | H10: *Excess Cash
C11: Net Inc Margin | D11: Gross Inc / TO | F11: Net Com Ov / Assets | H11: Inventory
A12: 1m Ins | C12: CFO Margin | D12: cfEBIT adj / TQ | F12: mktCap / EV | H12: Receivables
A13: 6m Ins | C13: SFCF Margin | D13: ROIC Avg3 | F13: Int Coverage - CFO + Int | H13: Curr Other Lia
A14: <1w | C14: NCF Margin | D14: CROIC Avg3 | F14: Leverage (OA/Bk) | H14: Fixed Assets
A15: 1-2w | C15: SGA Margin | D15: CROSIC Avg3?? | F15: Revs / Net Com Over | H15: Intangibles
A16: 2-4w | C16: R&D Margin | D16: Gross Margin Avg3 | H16: LT Inv
A17: 3m | H17: Tax Assets
A18: 12m ($ | C18: EBITDA | D18: Profit Margin(Net Inc Margin) | H18: LT Other Assets
C19: EBIT | D19: CFO Margin Avg3
A20: revs | C20: BM Earnings | D20: SFCF Margin Avg3 | H20: BS RHS
A21: s/p | C21: bm EPS | D21: NCF Margin Avg3 | H21: Payables
A22: ebitda/e | C22: TBM Earnings | D22: Revs /sh | H22: ST Other Liab
A23: tb/p | C23: tbm EPS | D23: Assets /sh | H23: Def Revs
A24: b/p | C24: Dividends | D24: *Net Excess C | H24: ST Debt
A25: e/p | C25: Discont Com NetInc | D25: Net Com Over | F25: Delevered Outstanding Shares | H25: LT Debt
A26: cfo/p | C26: Common NetInc | D26: Book /sh | F26: Current Outstanding Shares | H26: Tax Liabs
A27: sfcf/p | C27: CFO | D27: Tang Book /sh | F27: CFO Avg3 / NCO | H27: LT Other Liabs
A28: ncf/p | C28: SECF | D28: bm ROE 3yr % | F28: NCO / Assets | H28: Book
A29: div/p | C29: MSFCF Acqs | D29: bm ROE 5yr %
A30: cash/p | C30: NCF | D30: tbm ROE 3yr %
A31: ncash/p | C31: Depr & Amort | D31: tbm ROE 5yr %
A32: nn/p | C32: CapEx | D32: Div /sh
C33: Net Acqs / Divests | D33: bm EPS Avg3
A34: max3 | C34: CapEx + Net Acq/D? | D34: EBITDA /sh | H34: ? possible
A35: *ev/ebitd | C35: Excess Cash | D35: EBITDA Avg3 /sh | H35: EV/FCF | I35: Book Value | K35: Equity Multiplier
A36: e/p | C36: Assets | D36: EBITDA Avg7 /sh | H36: Gross Margin | K36: Retention Rate
A37: cf/p | C37: Excess Cash & ST | D37: EPS | H37: Operating Margin | K37: Gearing Ratio
A38: sfcf/p | C38: ST Debt | D38: IC | H38: Net Debt / EBIT | K38: Return on Common Equity(ROCE)
A39: ncf/p | C39: Total Debt | H39: ROE | K39: EPS
C40: Net Common Overhang | H40: CROIC | K40: Dividend Yield
A41: chart | C41: Non-Common Equities | H41: P/FCF | K41: CET1
C42: Book | H42: Revenues | K42: Assets
C43: Tang Book | H43: Net Income | K43: Equity
C44: Net-Net /sh | H44: ROA | K44: AOCI
C45: *CapEx Avg3 /sh | H45: ROE** | K45: Perpetuity Growth Model(Gordon Growth Model)
C46: CapEx + NetAcqs | H46: FCFF | K46: Exit Multiple Method
C47: Working Capital /sh | H47: FCF | K47: Cost of Sales
C48: *** Capital /sh | H48: FCFE | K48: COGS
D49: Notes: | H49: D/E | K49: Inventory
D50: 20 years of performance plus is wanted | H50: Probability of Default | K50: Begin Inventory
D51: Present Value of Cash Flows, 20% discount rate, compounding 1 | H51: NPV | K51: Ending Inventory
D52: Invesetment Style 2of2 : Doesnt do DCF Models bc value is just one factor | H52: Overhang | K52: Comprehensive Income Statement
D53: 1. sizeable discount often in relation to crude fundamentals face value/ sometimes the chart, historical operating of 20 years balance sheet, revenues, earnings, cash flow, gross and net margin, share count. Gap is reliable enough for his approach. Technical usually compliments Fundamentals for timing/ insider buying, Keep universe broad, benefit of large universe to be worth the associated cost of stepping outside wheelhouse | H53: Average inventory | K53: Net Sales
D54: 2. Leverage/Credit Risk - dont shy away from leveraged companies. its a balancing act/ assessing credit risk metrics: the youlin of publicly traded debt, those bond folks are on the ball. esp if trading out a couple years and its priced in. Potential covenant breach, analysis of ratings agencies, who owns the debt, | K54: Net Income
D55: 3. Insider Buying- weighs heavily - buying by prom execs CFO's insiders at least half mil plus. Seeing if the insiders are buying when its cheap/inflection point
D56: 4. At least 20% insider ownership would like to see, not always a good thing when owned by a family. when respectable value shops and activists, tracking good analysis
D57: 5. Confidence level
D59: Tools Part 2 google sheets/finance functions, chrome has great features, 1. Improve bookmarks/opening in groups, manage search engines for shortcuts, extensions: context menu search, search center, chart lists(stock charts) groupings, shortcuts, openinsider, whalewisdom, integrating with spreadsheets, Funds: scion, towle, greenlight, fairfax, baupost, abrams cap, appaloosa, weber alan, carl icahn, berkshire, lapides asset mgmt, perceptive advisor, ares mgmt, oaktree cap, MHR fund mgmt, hussman strategic, third avenue, walthausen, portolan capital, knowledge leaders, mcclain value mgmt, signia cap, bernzott cap advisor, sheffield asset mgmt, hodges cap, weitz, intrepid,old west, luminus, oshaughnessy, kopernik global, barel karsan, jeremy raper, jeremy blum, stephen simpson, carlton Getz, WYCO researcher, vincent ventures,Henrik Alex, Bumbershoot holdings, David Orr, scott Perry, Dmitriy Kozin, Rida Morwa, Prati Mgmt, Adam Levine-,Kingdom Capital, Timothy Stabosz, Strategic Investor, Magic investments, Rota Fortunae FINRA Bond data yield to maturity, Moody's ratings, insidertracking.com, fidelity historical sector performance, google sheet function list, ***google sheets scripting site stack overflow, 24 minutes in video
D60: Tools Part 3 RK Tracker share radar(vince), quandle(data aggregator), flex.io, quantal?, data and flux, conditional formatting, broad financial metrics, 34minutes: sheer level of revenues, net margin, trends, net earnings ,common earnings, operating cash flow, simple free cashflow, loads of balance sheet stuff(book value,

Sheet Log
C1: b/s | D1: date | E1: entry price | F1: exit price | G1: % gain | H1: current price | I1: comments
B2: HSCS | C2: s | D2: 45258 | I2: Up 58%
B3: CREX | C3: b | D3: 45258 | I3: Digital signage installer and provider of signage software. Software biz has sticky, high-margin, and highly recurring revenues, putting CREX on the verge of an inflection as they ramp up sales of its software to other signage installers. The core digital signage business also continues to grow with three recent large customer wins. Meanwhile, CREX is trading at only 4.4x NTM EV/EBITDA with 50% expected growth over the next 12 months if they execute on their large backlog. https://www.deepsailcapital.com/_files/ugd/50dba3_a0c7512782854335bf671e5834a0f711.pdf
B4: LBTYK | C4: b | D4: 45258 | I4: Weaker USD and lower 10-year Treasury yields are bullish for $LBTYA / $LBTYK, yet shares have barely budged.
B5: LBTYA | C5: b | D5: 45258 | I5: Buffet
B6: QS | C6: b | D6: 45258 | I6: cnbc article. battery much better than teslas
B7: GoodRX | C7: s | D7: 45265 | I7: sold bc I'm up and also bc I'm trying to free capital due to a losing position
B8: BILL | C8: s | D8: 45265 | I8: sold bc I'm up and also bc I'm trying to free capital due to a losing position
B9: UHAUL | C9: s | D9: 45265 | I9: sold bc I'm up and also bc I'm trying to free capital due to a losing position
B10: ENSTAR | C10: s | D10: 45265 | I10: sold bc I'm up and also bc I'm trying to free capital due to a losing position
B11: HOOD | C11: s | D11: 45265 | I11: sold bc I'm up and also bc I'm trying to free capital due to a losing position
B12: ZG | C12: s | I12: sold bc I'm up and also bc I'm trying to free capital due to a losing position. see if this goes higher bc of lower dollar
B13: paypal | C13: s | D13: 45273 | I13: up 2.23%
B14: EXPR | C14: b | D14: 45309 | E14: 7.36 | I14: favorable p/e. negative news, store closings,chart pattern,

Sheet Portfolio
A1: symbol | B1: name | C1: sector | D1: industry | E1: mkt cap | F1: price | G1: daily % change | H1: 1m insider buying | I1: 6m insider buying | J1: # of insiders | K1: 6m val | L1: % to val blend | M1: % to 52w hi | N1: % from 52w Lo | O1: revs | P1: s/p | Q1: ebitda/ev | R1: tb/p | S1: b/p | T1: e/p | U1: cfo/p | V1: sfcf/p | W1: ncf/p | X1: div/p | Y1: cash/p | Z1: ncash/p | AA1: nn/p | AB1: asset/p | AC1: retear/mc | AD1: revs/debt | AE1: mc/ev

Sheet UNIVERSE
A1: Formula
C8: tb/p | D8: b/p | E8: e/p | F8: cfo/p | G8: sfcf/p | H8: ncf/p | I8: div/p | J8: cash/p | K8: ncash/p | L8: nn/p | M8: asset/p | N8: retear/mc | O8: revs/debt | P8: mc/ev
A17: Valuation ratios
A18: s/p
A19: PTBV
A20: ebitda/ev
A21: tb/p
A22: b/p
A23: e/p
A24: cfo/p
A25: sfcf/p
A26: ncf/p
A27: div/p
A28: Acid Test Ratio

Sheet EDGAR CIK raw
A1: TICKER | B1: CIK | C1: Company | D1: Sector
A2: svix | B2: 1793497 | C2: -1x Short VIX Futures ETF
A3: flws | B3: 1084869 | C3: 1-800-Flowers.Com Inc
A4: vcxb | B4: 1848948 | C4: 10X Capital Venture Acquisition III Corp
A5: txg | B5: 1770787 | C5: 10X Genomics Inc
A6: yi | B6: 1738906 | C6: 111 Inc - ADR
A7: retc | B7: 1627611 | C7: 12 Retech Corp
A8: yq | B8: 1821468 | C8: 17 Education & Technology Group Inc
A9: turn | B9: 893739 | C9: 180 Degree Capital Corp
A10: atnfw | B10: 1690080 | C10: 180 Life Sciences
A11: atnf | B11: 1690080 | C11: 180 Life Sciences Corp
A12: kegs | B12: 884380 | C12: 1812 Brewing Company Inc
A13: efsh | B13: 1599407 | C13: 1847 Holdings LLC
... A3518: gbs | B3518: 1725430 | C3518: Gold Bullion Securities Limited
A3519: gegp | B3519: 1081188 | C3519: #N/A
A3520: gfi | B3520: 1172724 | C3520: Gold Fields Limited
A3521: gfiof | B3521: 1172724 | C3521: Gold Fields Limited
A3522: gdrzf | B3522: 1072725 | C3522: Gold Reserve Inc.
A3523: goro | B3523: 1160791 | C3523: Gold Resource Corporation
A3524: grhi | B3524: 894501 | C3524: Gold Rock Holdings Ord Shs Class A
A3525: groy | B3525: 1834026 | C3525: Gold Royalty Corp
A3526: gcfff | B3526: 863678 | C3526: Goldcliff Resource Corporation
A3527: aqpw | B3527: 1317833 | C3527: Golden Ally Lifetech Group Inc
A3528: gamcw | B3528: 1841125 | C3528: Golden Arrow Merger
A3529: gamc | B3529: 1841125 | C3529: Golden Arrow Merger Corp
A3530: gamcu | B3530: 1841125 | C3530: Golden Arrow Merger Units
A3531: garwf | B3531: 1403870 | C3531: Golden Arrow Resources Corp
... A4872: lzgi | B4872: 1126115 | C4872: Lzg International Inc
A4873: mpti | B4873: 1902314 | C4873: #N/A
A4874: mho | B4874: 799292 | C4874: M/I Homes Inc
A4875: mfbp | B4875: 1094738 | C4875: M&F Bancorp Inc
A4876: mtb | B4876: 36270 | C4876: M&t Bank Corp
A4877: mcbc | B4877: 1053584 | C4877: Macatawa Bank Corp
A4878: mac | B4878: 912242 | C4878: Macerich Co
A4879: mtsi | B4879: 1493594 | C4879: MACOM Technology Solutions Holdings Inc
A4880: mfd | B4880: 1276469 | C4880: Macquarie/first Trust Glbl nfrstrctr/tlt
A4881: mgnx | B4881: 1125345 | C4881: MacroGenics Inc
A4882: m | B4882: 794367 | C4882: Macy's Inc
A4883: mcn | B4883: 1289868 | C4883: Madison Covered Call & Equity Strtgy Fd
A4884: msge | B4884: 1795250 | C4884: Madison Square Garden Entertainment Corp
A4885: msgs | B4885: 1636519 | C4885: Madison Square Garden Sports Corp
... A8573: aa | B8573: 1675149 | C8573: Alcoa Corp
A8574: aac-un | B8574: 1829432 | C8574: =IFERROR(__xludf.DUMMYFUNCTION("GOOGLEFINANCE(A8574,""name"")"),"#N/A") -> #N/A
A8575: aac-wt | B8575: 1829432 | C8575: =IFERROR(__xludf.DUMMYFUNCTION("GOOGLEFINANCE(A8575,""name"")"),"#N/A") -> #N/A
A8576: aacp | B8576: 1822365 | C8576: =IFERROR(__xludf.DUMMYFUNCTION("GOOGLEFINANCE(""aacp"",""name"")"),"#N/A") -> #N/A
A8577: aaic | B8577: 1209028 | C8577: =IFERROR(__xludf.DUMMYFUNCTION("GOOGLEFINANCE(A8577,""name"")"),"#N/A") -> #N/A
A8578: aaic-pb | B8578: 1209028 | C8578: =IFERROR(__xludf.DUMMYFUNCTION("GOOGLEFINANCE(A8578,""name"")"),"#N/A") -> #N/A
A8579: aaic-pc | B8579: 1209028 | C8579: =IFERROR(__xludf.DUMMYFUNCTION("GOOGLEFINANCE(A8579,""name"")"),"#N/A") -> #N/A
A8580: aaidx | B8580: 1754927 | C8580: =IFERROR(__xludf.DUMMYFUNCTION("GOOGLEFINANCE(A8580,""name"")"),"#N/A") -> #N/A
A8581: aain | B8581: 1209028 | C8581: =IFERROR(__xludf.DUMMYFUNCTION("GOOGLEFINANCE(A8581,""name"")"),"#N/A") -> #N/A
A8582: aam-pa | B8582: 1411494 | C8582: =IFERROR(__xludf.DUMMYFUNCTION("GOOGLEFINANCE(A8582,""name"")"),"#N/A") -> #N/A
A8583: aam-pb | B8583: 1411494 | C8583: =IFERROR(__xludf.DUMMYFUNCTION("GOOGLEFINANCE(A8583,""name"")"),"#N/A") -> #N/A
A8584: aaqc | B8584: 1838883 | C8584: =IFERROR(__xludf.DUMMYFUNCTION("GOOGLEFINANCE(A8584,""name"")"),"#N/A") -> #N/A
A8585: aaqc-un | B8585: 1838883 | C8585: =IFERROR(__xludf.DUMMYFUNCTION("GOOGLEFINANCE(A8585,""name"")"),"#N/A") -> #N/A
A8586: aaqc-wt | B8586: 1838883 | C8586: =IFERROR(__xludf.DUMMYFUNCTION("GOOGLEFINANCE(A8586,""name"")"),"#N/A") -> #N/A
A8587: aatp | B8587: 1713210 | C8587: =IFERROR(__xludf.DUMMYFUNCTION("GOOGLEFINANCE(""AATP"",""name"")"),"#N/A") -> #N/A
A8588: aaww | B8588: 1135185 | C8588: =IFERROR(__xludf.DUMMYFUNCTION("GOOGLEFINANCE(A8588,""name"")"),"#N/A") -> #N/A
A8589: ab | B8589: 825313 | C8589: =IFERROR(__xludf.DUMMYFUNCTION("GOOGLEFINANCE(A8589,""name"")"),"Alliancebernstein Holding LP") -> Alliancebernstein Holding LP
A8590: abcm | B8590: 1492074 | C8590: =IFERROR(__xludf.DUMMYFUNCTION("GOOGLEFINANCE(A8590,""name"")"),"#N/A") -> #N/A
A8591: abgi | B8591: 1833764 | C8591: =IFERROR(__xludf.DUMMYFUNCTION("GOOGLEFINANCE(A8591,""name"")"),"#N/A") -> #N/A
A8592: abmd | B8592: 815094 | C8592: =IFERROR(__xludf.DUMMYFUNCTION("GOOGLEFINANCE(A8592,""name"")"),"#N/A") -> #N/A
A8593: abml | B8593: 1576873 | C8593: =IFERROR(__xludf.DUMMYFUNCTION("GOOGLEFINANCE(A8593,""name"")"),"#N/A") -> #N/A
A8594: abr-pd | B8594: 1253986 | C8594: =IFERROR(__xludf.DUMMYFUNCTION("GOOGLEFINANCE(A8594,""name"")"),"#N/A") -> #N/A
A8595: abr-pe | B8595: 1253986 | C8595: =IFERROR(__xludf.DUMMYFUNCTION("GOOGLEFINANCE(A8595,""name"")"),"#N/A") -> #N/A
A8596: abr-pf | B8596: 1253986 | C8596: =IFERROR(__xludf.DUMMYFUNCTION("GOOGLEFINANCE(A8596,""name"")"),"#N/A") -> #N/A
A8597: abst | B8597: 1071058 | C8597: =IFERROR(__xludf.DUMMYFUNCTION("GOOGLEFINANCE(A8597,""name"")"),"#N/A") -> #N/A
A8598: abtx | B8598: 1642081 | C8598: =IFERROR(__xludf.DUMMYFUNCTION("GOOGLEFINANCE(A8598,""name"")"),"#N/A") -> #N/A
A8599: ac | B8599: 1642122 | C8599: =IFERROR(__xludf.DUMMYFUNCTION("GOOGLEFINANCE(A8599,""name"")"),"Air Canada") -> Air Canada
A8600: acam | B8600: 1846125 | C8600: =IFERROR(__xludf.DUMMYFUNCTION("GOOGLEFINANCE(A8600,""name"")"),"#N/A") -> #N/A
A8601: acaq | B8601: 1869141 | C8601: =IFERROR(__xludf.DUMMYFUNCTION("GOOGLEFINANCE(A8601,""name"")"),"#N/A") -> #N/A
A8602: acaq-un | B8602: 1869141 | C8602: =IFERROR(__xludf.DUMMYFUNCTION("GOOGLEFINANCE(A8602,""name"")"),"#N/A") -> #N/A
A8603: acaq-wt | B8603: 1869141 | C8603: =IFERROR(__xludf.DUMMYFUNCTION("GOOGLEFINANCE(A8603,""name"")"),"#N/A") -> #N/A
A8604: acax | B8604: 1897245 | C8604: =IFERROR(__xludf.DUMMYFUNCTION("GOOGLEFINANCE(A8604,""name"")"),"#N/A") -> #N/A
A8605: acaxr | B8605: 1897245 | C8605: =IFERROR(__xludf.DUMMYFUNCTION("GOOGLEFINANCE(A8605,""name"")"),"#N/A") -> #N/A
A8606: acaxu | B8606: 1897245 | C8606: =IFERROR(__xludf.DUMMYFUNCTION("GOOGLEFINANCE(A8606,""name"")"),"#N/A") -> #N/A
A8607: acaxw | B8607: 1897245 | C8607: =IFERROR(__xludf.DUMMYFUNCTION("GOOGLEFINANCE(A8607,""name"")"),"#N/A") -> #N/A
A8608: acbi | B8608: 1461755 | C8608: =IFERROR(__xludf.DUMMYFUNCTION("GOOGLEFINANCE(A8608,""name"")"),"#N/A") -> #N/A
A8609: accv | B8609: 1847499 | C8609: =IFERROR(__xludf.DUMMYFUNCTION("GOOGLEFINANCE(A8609,""name"")"),"#N/A") -> #N/A
A8610: acdi | B8610: 1850316 | C8610: =IFERROR(__xludf.DUMMYFUNCTION("GOOGLEFINANCE(A8610,""name"")"),"#N/A") -> #N/A
A8611: acdi-un | B8611: 1850316 | C8611: =IFERROR(__xludf.DUMMYFUNCTION("GOOGLEFINANCE(A8611,""name"")"),"#N/A") -> #N/A
A8612: acdi-wt | B8612: 1850316 | C8612: =IFERROR(__xludf.DUMMYFUNCTION("GOOGLEFINANCE(A8612,""name"")"),"#N/A") -> #N/A
A8613: acer | B8613: 1069308 | C8613: =IFERROR(__xludf.DUMMYFUNCTION("GOOGLEFINANCE(A8613,""name"")"),"#N/A") -> #N/A
A8614: acev | B8614: 1813658 | C8614: =IFERROR(__xludf.DUMMYFUNCTION("GOOGLEFINANCE(A8614,""name"")"),"#N/A") -> #N/A
A8615: acevu | B8615: 1813658 | C8615: =IFERROR(__xludf.DUMMYFUNCTION("GOOGLEFINANCE(A8615,""name"")"),"#N/A") -> #N/A
A8616: acevw | B8616: 1813658 | C8616: =IFERROR(__xludf.DUMMYFUNCTION("GOOGLEFINANCE(A8616,""name"")"),"#N/A") -> #N/A
A8617: achhy | B8617: 1161611 | C8617: =IFERROR(__xludf.DUMMYFUNCTION("GOOGLEFINANCE(A8617,""name"")"),"#N/A") -> #N/A
A8618: achn | B8618: 1672571 | C8618: =IFERROR(__xludf.DUMMYFUNCTION("GOOGLEFINANCE(A8618,""name"")"),"#N/A") -> #N/A
A8619: achr-wt | B8619: 1824502 | C8619: =IFERROR(__xludf.DUMMYFUNCTION("GOOGLEFINANCE(A8619,""name"")"),"#N/A") -> #N/A
A8620: acii | B8620: 1838614 | C8620: =IFERROR(__xludf.DUMMYFUNCTION("GOOGLEFINANCE(A8620,""name"")"),"Innovator Index Autocallable Income Strategy ETF") -> Innovator Index Autocallable Income Strategy ETF
A8621: acii-un | B8621: 1838614 | C8621: =IFERROR(__xludf.DUMMYFUNCTION("GOOGLEFINANCE(A8621,""name"")"),"#N/A") -> #N/A
A8622: acii-wt | B8622: 1838614 | C8622: =IFERROR(__xludf.DUMMYFUNCTION("GOOGLEFINANCE(A8622,""name"")"),"#N/A") -> #N/A
A8623: acmc | B8623: 934543 | C8623: =IFERROR(__xludf.DUMMYFUNCTION("GOOGLEFINANCE(A8623,""name"")"),"#N/A") -> #N/A
A8624: acmsy | B8624: 1850767 | C8624: =IFERROR(__xludf.DUMMYFUNCTION("GOOGLEFINANCE(A8624,""name"")"),"#N/A") -> #N/A
A8625: acp-pa | B8625: 1503290 | C8625: =IFERROR(__xludf.DUMMYFUNCTION("GOOGLEFINANCE(A8625,""name"")"),"#N/A") -> #N/A
A8626: acqr | B8626: 1837393 | C8626: =IFERROR(__xludf.DUMMYFUNCTION("GOOGLEFINANCE(A8626,""name"")"),"#N/A") -> #N/A
A8627: acqru | B8627: 1837393 | C8627: =IFERROR(__xludf.DUMMYFUNCTION("GOOGLEFINANCE(A8627,""name"")"),"#N/A") -> #N/A
A8628: acqrw | B8628: 1837393 | C8628: =IFERROR(__xludf.DUMMYFUNCTION("GOOGLEFINANCE(A8628,""name"")"),"#N/A") -> #N/A
A8629: acr-pc | B8629: 1332551 | C8629: =IFERROR(__xludf.DUMMYFUNCTION("GOOGLEFINANCE(A8629,""name"")"),"#N/A") -> #N/A
A8630: acr-pd | B8630: 1332551 | C8630: =IFERROR(__xludf.DUMMYFUNCTION("GOOGLEFINANCE(A8630,""name"")"),"#N/A") -> #N/A
A8631: acro-un | B8631: 1847891 | C8631: =IFERROR(__xludf.DUMMYFUNCTION("GOOGLEFINANCE(A8631,""name"")"),"#N/A") -> #N/A
...

Sheet VIX
B1: The one constant in the stock markets is change. Otherwise put, volatility is a constant companion to investors, which is why the Cboe Volatility Index (VIX) is such a widely tracked market index. Ever since this measurement of investor sentiment regarding future volatility was introduced (with futures and options following later), many investors have wondered about the best ways to trade the VIX Index.
A3: Realizing the generally negative correlation between volatility and stock market performance, many investors have looked to use volatility instruments to hedge their portfolios. In this article, we'll review four ways you can trade the VIX using specific exchange-traded funds and exchange-traded notes.
A5: KEY TAKEAWAYS
A6: Since the Cboe Volatility Index (VIX) was introduced, investors have traded this measure of investor sentiment about future volatility.
A7: The primary way to trade the VIX is to buy exchange-traded funds (ETFs) and exchange-traded notes (ETNs) tied to the VIX itself.
A8: ETFs and ETNs related to the VIX include the iPath Series B S&P 500 VIX Short-Term Futures ETN (VXX) and the ProShares Short VIX Short-Term Futures ETF (SVXY).
A10: Beware the Lag
A11: Investors considering these ETFs and ETNs should realize that they are not great proxies for the performance of the spot VIX. These funds can be expected to perform very differently from the VIX. Some may rise or fall in tandem with the VIX, but the rate at which they move and the lag time can make pinpointing entry and exit points challenging even for seasoned traders.
A13: Market volatility investments are best suited for investors with a short-time horizon who can closely watch their positions and move quickly if the market turns against them.
A15: If investors want to place bets on equity market volatility or use them as hedges, the VIX-related ETF and ETN products are acceptable but highly-flawed instruments; however, they certainly have a strong convenience aspect to them, as they trade like any other stock.
A16: What Is the VIX?
A17: The Cboe Volatility Index (VIX) represents the market’s expectations for the strength of short-term price changes (or volatility) in the S&P 500 index (SPX). The level of market volatility is used to gauge market sentiment and the level of fear and uncertainty among market participants
A18: Volatility is a measure of dispersion seen in financial instruments. Volatility is represented by the CBOE Volatility Index (VIX) and investors have sought ways to trade this index, primarily as a means to hedge their portfolios. For investors, choosing exchange-traded notes (ETNs) and exchange-traded funds (ETFs) as investment vehicles for this purpose are easily accessible options with plenty to choose from.
... A21: VIX might be said to provide a crowd-sourced estimate for the degree to which the market is uncertain about the future.

Sheet SIC Index
A1: SIC Code | B1: Office | C1: Industry Title
A2: 100 | B2: Industrial Applications and Services | C2: AGRICULTURAL PRODUCTION-CROPS
A3: 200 | B3: Industrial Applications and Services | C3: AGRICULTURAL PROD-LIVESTOCK & ANIMAL SPECIALTIES
A4: 700 | B4: Industrial Applications and Services | C4: AGRICULTURAL SERVICES
A5: 800 | B5: Industrial Applications and Services | C5: FORESTRY
A6: 900 | B6: Industrial Applications and Services | C6: FISHING, HUNTING AND TRAPPING
A7: 1000 | B7: Office of Energy & Transportation | C7: METAL MINING
A8: 1040 | B8: Office of Energy & Transportation | C8: GOLD AND SILVER ORES
A9: 1090 | B9: Office of Energy & Transportation | C9: MISCELLANEOUS METAL ORES
A10: 1220 | B10: Office of Energy & Transportation | C10: BITUMINOUS COAL & LIGNITE MINING
A11: 1221 | B11: Office of Energy & Transportation | C11: BITUMINOUS COAL & LIGNITE SURFACE MINING
A12: 1311 | B12: Office of Energy & Transportation | C12: CRUDE PETROLEUM & NATURAL GAS
A13: 1381 | B13: Office of Energy & Transportation | C13: DRILLING OIL & GAS WELLS
... A445: 9995 | B445: Office of Real Estate & Construction | C445: NON-OPERATING ESTABLISHMENTS

Sheet Pulse(Heartbeat of the market)

Sheet Crypto
A1: VXV
A2: ILV
A3: AIOZ
A4: STOS
A6: Victoria VR | B6: in good buy zone
A7: Koinos | B7: High % of jacksons port. Have to use MEXC, and VPN. MetaMask
A8: BENQI
A9: Octopus Network

Sheet (ETL)
A1: Phase 1: Discovery –
A2: The data science team learn and investigate the problem.
A3: Develop context and understanding. | B3: Extract, transform, and load (ETL)
A4: Come to know about data sources needed and available for the project.
A5: The team formulates initial hypothesis that can be later tested with data.
A6: Phase 2: Data Preparation –
A7: Steps to explore, preprocess, and condition data prior to modeling and analysis.
A8: It requires the presence of an analytic sandbox, the team execute, load, and transform, to get data into the sandbox.
A9: Data preparation tasks are likely to be performed multiple times and not in predefined order.
A10: Several tools commonly used for this phase are – Hadoop, Alpine Miner, Open Refine, etc.
A11: Phase 3: Model Planning –
A12: Team explores data to learn about relationships between variables and subsequently, selects key variables and the most suitable models.
A13: In this phase, data science team develop data sets for training, testing, and production purposes.
A14: Team builds and executes models based on the work done in the model planning phase.
A15: Several tools commonly used for this phase are – Matlab, STASTICA.
... A29: Free or open source tools – Octave, WEKA, SQL, MADlib.

Sheet index and match
A1: Guest Name | B1: Dietary Restriction | C1: Sent Invitation | D1: Table Number | F1: KEY | I1: INDEX
A2: David | B2: Vegetarian | C2: No | D2: 3 | F2: Yellow highlight indicates a formula exists in cell
A3: Bob | B3: None | C3: No | D3: 5 | F3: Red highlight indicates the intended formula output | I3: Returns the content of a cell, specified by row and column offset. | N3: INDEX and MATCH
A4: david | B4: None | C4: Yes | D4: 1
A5: Nancy | B5: None | C5: No | D5: 4 | I5: Examples
A6: Mary | B6: Vegetarian | C6: Yes | D6: 2
I7: Make a copy
G8: INDEX(reference,row,column)
A9: Formula | B9: Formula Output | G9: =index(A2$D6,2,1) -> #ERROR! | I9: Guest Name | J9: Dietary Restriction | K9: Sent Invitation | L9: Table Number
A10: {=INDEX(A2:D6, 2, 1)} -> Bob | B10: Bob | G10: index(A2:d6,2,1) | H10: {=index(B3:E7,2,1)} -> None | I10: David | J10: Vegetarian | K10: No | L10: 3
A11: {=INDEX(A2:D6, 4, 2)} -> None | B11: None | G11: INDEX(A1:D6, 6, 2) | I11: Bob | J11: None | K11: No | L11: 5
A12: {=INDEX(A2:D6,1,1)} -> David | B12: David | F12: {=INDEX(A1:D6, MATCH(2, D1:D6, 0), MATCH("Guest Name", A1:D1, 0))} -> Mary | I12: david | J12: None | K12: Yes | L12: 1
A13: {=INDEX(A1:D6, 6, 3)} -> Yes | B13: Yes | I13: Nancy | J13: None | K13: No | L13: 4
I14: Mary | J14: Vegetarian | K14: Yes | L14: 2
A16: Formula | I16: Formula | J16: Formula Output
A17: {=INDEX(A2:D6, 2, 0)} -> Bob | B17: None | C17: No | D17: 5 | I17: {=INDEX(A2:D6, 2, 1)} -> Bob | J17: Bob
G18: INDEX and MATCH | I18: {=INDEX(A2:D6, 4, 4)} -> 4 | J18: 4
A19: Formula Output | I19: {=INDEX(A2:D6,1,1)} -> David | J19: David
A20: Bob | B20: None | C20: No | D20: 5 | I20: {=INDEX(A1:D6, 6, 2)} -> Vegetarian | J20: Vegetarian
A23: Formula | B23: Formula Output
A24: {=INDEX(A2:D6, 0, 4)} -> 3 | B24: 3
A25: 5 | B25: 5 | I25: Formula | J25: Formula Output
A26: 1 | B26: 1 | I26: {=INDEX(A2:D6, 0, 4)} -> 3 | J26: 3
A27: 4 | B27: 4 | J27: 5
A28: 2 | B28: 2 | J28: 1
J29: 4
J30: 2
A32: INDEX MATCH USE CASE | I32: Returns the cell(s) found by index value into the referenced range.
A34: Guest Name | B34: Dietary Restriction | C34: Sent Invitation | D34: Table Number | I34: Sample Usage
A35: David | B35: Vegetarian | C35: No | D35: 3
A36: Bob | B36: None | C36: No | D36: 5 | I36: INDEX(A1:C20, 5, 1)
A37: david | B37: None | C37: Yes | D37: 1
A38: Nancy | B38: None | C38: No | D38: 4 | I38: Syntax
A39: Mary | B39: Vegetarian | C39: Yes | D39: 2
I40: INDEX(reference, [row], [column])
A42: Goal | B42: Formula | C42: Formula Output | D42: Comment | I42: reference - The range of cells from which the values are returned.
A43: Find Mary's Dietary Restriction | B43: =VLOOKUP("Mary", A1:D6, 2, false) -> Vegetarian | C43: Vegetarian | D43: Both search key and index are hardcoded
A44: Find Mary's Dietary Restriction | B44: {=INDEX(A1:D6, MATCH("Mary", A1:A6, 0), 2)} -> Vegetarian | C44: Vegetarian | D44: Row number is dynamic & column number is hardcoded | I44: row - [OPTIONAL - 0 by default] - The index of the row to be returned from within the reference range of cells.
A45: Find Mary's Dietary Restriction | B45: {=INDEX(A1:D6, MATCH("Mary", A1:A6, 0), MATCH("Dietary Restriction", A1:D1, 0))} -> Vegetarian | C45: Vegetarian | D45: Both row number & column number are dynamic
A46: Find Who is at Table Number 2 | B46: Using VLOOKUP, this would not be possible | C46: N/A | D46: VLOOKUP can only be used when the lookup value is to the left of the desired attribute to return | I46: column - [OPTIONAL - 0 by default] - The index of the column to be returned from within the reference range of cells.
A47: Find Who is at Table Number 2 | B47: {=INDEX(A1:D6, MATCH(2, D1:D6, 0), MATCH("Guest Name", A1:D1, 0))} -> Mary | C47: Mary | D47: INDEX and MATCH can be used regardless of where the lookup value is located relative to the desired attribute to return | I47: Using INDEX and Match
I49: INDEX and MATCH can be used together to perform more advanced and dynamic lookups.
I51: Tip: VLOOKUP can be used when the lookup value is to the left of the desired attribute to return. INDEX and MATCH can be used regardless of where the lookup value is located in the dataset.
I52: Guest Name | J52: Dietary Restriction | K52: Sent Invitation | L52: Table Number
I53: David | J53: Vegetarian | K53: No | L53: 3
I54: Bob | J54: None | K54: No | L54: 5
I55: david | J55: None | K55: Yes | L55: 1
I56: Nancy | J56: None | K56: No | L56: 4
I57: Mary | J57: Vegetarian | K57: Yes | L57: 2
I59: Goal | J59: Formula | K59: Formula Output | L59: Comment
I60: Find Mary's Dietary Restriction | J60: =VLOOKUP("Mary", A1:D6, 2, false) -> Vegetarian | K60: Vegetarian | L60: Both search key and index are hardcoded
I61: Find Mary's Dietary Restriction | J61: {=INDEX(A1:D6, MATCH("Mary", A1:A6, 0), 2)} -> Vegetarian | K61: Vegetarian | L61: Row number is dynamic & column number is hardcoded
I62: Find Mary's Dietary Restriction | J62: {=INDEX(A1:D6, MATCH("Mary", A1:A6, 0), MATCH("Dietary Restriction", A1:D1, 0))} -> Vegetarian | K62: Vegetarian | L62: Both row number & column number are dynamic
I63: Find Who is at Table Number 2 | J63: Using VLOOKUP, this would not be possible | K63: N/A | L63: VLOOKUP can only be used when the lookup value is to the left of the desired attribute to return
I64: Find Who is at Table Number 2 | J64: {=INDEX(A1:D6, MATCH(2, D1:D6, 0), MATCH("Guest Name", A1:D1, 0))} -> Mary | K64: Mary | L64: INDEX and MATCH can be used regardless of where the lookup value is located relative to the desired attribute to return | M64: INDEX(A1:D6, MATCH(2, D1:D6, 0), MATCH("Guest Name", A1:D1, 0))
I65: See Also
I67: MATCH: Returns the relative position of an item in a range that matches a specified value.
I69: OFFSET: Returns a range reference shifted a specified number of rows and columns from a starting cell reference.
I71: Notes
I72: If you set row or column to 0, INDEX returns the array of values for the entire column or row, respectively.

Sheet betas
A1: Date updated: | B1: 44931 | H1: YouTube Video explaining estimation choices and process. | I1: Notes
A2: Created by: | B2: Aswath Damodaran, adamodar@stern.nyu.edu | I2: if you are looking for a pure-play beta, i.e., a beta for a business, the unlevered beta corrected for cash is your best bet. Since even sector betas can move over time, I have also reported the average of the this sector beta across time in the last column. This number, for obvious reasons, is less likely to be volatile over time.
A3: What is this data? | B3: Beta, Unlevered beta and other risk measures | F3: US companies
A4: Home Page: | B4: http://www.damodaran.com
A5: Data website: | B5: https://pages.stern.nyu.edu/~adamodar/New_Home_Page/data.html
A6: Companies in each industry: | B6: https://pages.stern.nyu.edu/~adamodar/pc/datasets/indname.xls
A7: Variable definitions: | B7: https://pages.stern.nyu.edu/~adamodar/New_Home_Page/datafile/variable.htm
A8: Do you want to use marginal or effective tax rates in unlevering betas? | F8: Marginal
A9: If marginal tax rate, enter the marginal tax rate to use | F9: 0.25 | L9: Unlevered beta corrected for cash - Over time
A10: Industry Name | B10: Number of firms | C10: Beta | D10: D/E Ratio | E10: Effective Tax rate | F10: Unlevered beta | G10: Cash/Firm value | H10: Unlevered beta corrected for cash | I10: HiLo Risk | J10: Standard deviation of equity | K10: Standard deviation in operating income (last 10 years) | L10: 2019 | M10: 2020 | N10: 2021 | O10: 2022 | P10: Average (2019-23)
A11: Software (Entertainment) | B11: 91 | C11: 1.3635757 | D11: 0.048025373 | E11: 0.03816572 | F11: =IF($F$8="Effective",C11/(1+(1-E11)*D11),C11/(1+(1-$F$9)*D11)) -> 1.3161686 | G11: 0.030718171 | H11: =F11/(1-G11) -> 1.3578802 | I11: 0.68715522 | J11: 0.58709544 | K11: 0.6913671 | L11: 1.2697947 | M11: 1.2858745 | N11: 0.96 | O11: 1.2075499 | P11: =AVERAGE('Industry Averages'!$H11,'Industry Averages'!$L11:$O11) -> #REF!
A12: Shoe | B12: 13 | C12: 1.3276925 | D12: 0.090140656 | E12: 0.10698368 | F12: =IF($F$8="Effective",C12/(1+(1-E12)*D12),C12/(1+(1-$F$9)*D12)) -> 1.2436172 | G12: 0.034958749 | H12: =F12/(1-G12) -> 1.2886674 | I12: 0.50846346 | J12: 0.39374186 | K12: 0.2827079 | L12: 0.741282 | M12: 0.83360997 | N12: 0.98 | O12: 1.1884917 | P12: =AVERAGE('Industry Averages'!$H12,'Industry Averages'!$L12:$O12) -> #REF!
A13: Software (System & Application) | B13: 390 | C13: 1.4697712 | D13: 0.093648718 | E13: 0.033951144 | F13: =IF($F$8="Effective",C13/(1+(1-E13)*D13),C13/(1+(1-$F$9)*D13)) -> 1.3733144 | G13: 0.028066077 | H13: =F13/(1-G13) -> 1.4129709 | I13: 0.61640664 | J13: 0.5211121 | K13: 0.32240159 | L13: 1.1619596 | M13: 1.1491608 | N13: 0.89 | O13: 1.1224549 | P13: =AVERAGE('Industry Averages'!$H13,'Industry Averages'!$L13:$O13) -> #REF!
A14: Computers/Peripherals | B14: 42 | C14: 1.2910864 | D14: 0.095226989 | E14: 0.091326262 | F14: =IF($F$8="Effective",C14/(1+(1-E14)*D14),C14/(1+(1-$F$9)*D14)) -> 1.2050233 | G14: 0.017944828 | H14: =F14/(1-G14) -> 1.2270424 | I14: 0.4600213 | J14: 0.48725444 | K14: 0.25020425 | L14: 1.4982789 | M14: 1.6400833 | N14: 1.14 | O14: 1.2487709 | P14: =AVERAGE('Industry Averages'!$H14,'Industry Averages'!$L14:$O14) -> #REF!
A15: Semiconductor | B15: 68 | C15: 1.6077463 | D15: 0.11265628 | E15: 0.081819269 | F15: =IF($F$8="Effective",C15/(1+(1-E15)*D15),C15/(1+(1-$F$9)*D15)) -> 1.4824876 | G15: 0.033748762 | H15: =F15/(1-G15) -> 1.5342672 | I15: 0.48933792 | J15: 0.38404265 | K15: 0.38437761 | L15: 1.2637967 | M15: 1.2368903 | N15: 0.96 | O15: 1.1358211 | P15: =AVERAGE('Industry Averages'!$H15,'Industry Averages'!$L15:$O15) -> #REF!
A16: Oil/Gas (Integrated) | B16: 4 | C16: 0.97748589 | D16: 0.11503816 | E16: 0.14222153 | F16: =IF($F$8="Effective",C16/(1+(1-E16)*D16),C16/(1+(1-$F$9)*D16)) -> 0.89984823 | G16: 0.049056001 | H16: =F16/(1-G16) -> 0.94626837 | I16: 0.34410897 | J16: 0.30548944 | K16: 0.97627648 | L16: 1.0556072 | M16: 1.1174662 | N16: 0.98 | O16: 1.2509262 | P16: =AVERAGE('Industry Averages'!$H16,'Industry Averages'!$L16:$O16) -> #REF!
A17: Telecom. Equipment | B17: 79 | C17: 1.2331195 | D17: 0.11678322 | E17: 0.04057193 | F17: =IF($F$8="Effective",C17/(1+(1-E17)*D17),C17/(1+(1-$F$9)*D17)) -> 1.1338118 | G17: 0.037911017 | H17: =F17/(1-G17) -> 1.1784896 | I17: 0.52733005 | J17: 0.41348754 | K17: 0.13611769 | L17: 1.0228587 | M17: 0.83597866 | N17: 0.83 | O17: 1.0568635 | P17: =AVERAGE('Industry Averages'!$H17,'Industry Averages'!$L17:$O17) -> #REF!
A18: Semiconductor Equip | B18: 30 | C18: 1.7571427 | D18: 0.11786825 | E18: 0.10936898 | F18: =IF($F$8="Effective",C18/(1+(1-E18)*D18),C18/(1+(1-$F$9)*D18)) -> 1.6144256 | G18: 0.044292966 | H18: =F18/(1-G18) -> 1.6892474 | I18: 0.43513373 | J18: 0.41568723 | K18: 0.68492909 | L18: 1.3908895 | M18: 1.2534843 | N18: 1.07 | O18: 1.3414181 | P18: =AVERAGE('Industry Averages'!$H18,'Industry Averages'!$L18:$O18) -> #REF!
A19: Healthcare Products | B19: 254 | C19: 1.1623832 | D19: 0.12602807 | E19: 0.036967519 | F19: =IF($F$8="Effective",C19/(1+(1-E19)*D19),C19/(1+(1-$F$9)*D19)) -> 1.0620017 | G19: 0.031994528 | H19: =F19/(1-G19) -> 1.097103 | I19: 0.59385543 | J19: 0.50940123 | K19: 0.3009798 | L19: 1.0412421 | M19: 0.98181868 | N19: 0.8 | O19: 0.91238002 | P19: =AVERAGE('Industry Averages'!$H19,'Industry Averages'!$L19:$O19) -> #REF!
A20: Information Services | B20: 73 | C20: 1.4047129 | D20: 0.13058755 | E20: 0.1244953 | F20: =IF($F$8="Effective",C20/(1+(1-E20)*D20),C20/(1+(1-$F$9)*D20)) -> 1.2794069 | G20: 0.040524176 | H20: =F20/(1-G20) -> 1.3334436 | I20: 0.47681215 | J20: 0.45109371 | K20: 0.28354506 | L20: 1.0476148 | M20: 1.0315159 | N20: 0.97 | O20: 1.2038668 | P20: =AVERAGE('Industry Averages'!$H20,'Industry Averages'!$L20:$O20) -> #REF!
A21: Drugs (Pharmaceutical) | B21: 281 | C21: 1.2680062 | D21: 0.13615574 | E21: 0.023739474 | F21: =IF($F$8="Effective",C21/(1+(1-E21)*D21),C21/(1+(1-$F$9)*D21)) -> 1.1505188 | G21: 0.025649637 | H21: =F21/(1-G21) -> 1.1808061 | I21: 0.69191225 | J21: 0.64883554 | K21: 0.18546972 | L21: 1.3790872 | M21: 1.2856575 | N21: 0.84 | O21: 1.0098236 | P21: =AVERAGE('Industry Averages'!$H21,'Industry Averages'!$L21:$O21) -> #REF!
A22: Heathcare Information and Technology | B22: 138 | C22: 1.4715095 | D22: 0.14208144 | E22: 0.043049399 | F22: =IF($F$8="Effective",C22/(1+(1-E22)*D22),C22/(1+(1-$F$9)*D22)) -> 1.3298041 | G22: 0.029861395 | H22: =F22/(1-G22) -> 1.3707362 | I22: 0.61728792 | J22: 0.53871738 | K22: 0.48966292 | L22: 1.1770734 | M22: 1.1526974 | N22: 0.75 | O22: 0.9088883 | P22: =AVERAGE('Industry Averages'!$H22,'Industry Averages'!$L22:$O22) -> #REF!
... A37: Metals & Mining | B37: 68 | C37: 1.2900535 | D37: 0.21544931 | E37: 0.041470687 | F37: =IF($F$8="Effective",C37/(1+(1-E37)*D37),C37/(1+(1-$F$9)*D37)) -> 1.1105957 | G37: 0.08907141 | H37: =F37/(1-G37) -> 1.2191907 | I37: 0.66580497 | J37: 0.7005624 | K37: 0.5271134 | L37: 1.1094423 | M37: 1.0865722 | N37: 0.82 | O37: 1.1279972 | P37: =AVERAGE('Industry Averages'!$H37,'Industry Averages'!$L37:$O37) -> #REF!
A38: Coal & Related Energy | B38: 19 | C38: 1.4521789 | D38: 0.21708836 | E38: 0.022762443 | F38: =IF($F$8="Effective",C38/(1+(1-E38)*D38),C38/(1+(1-$F$9)*D38)) -> 1.2488464 | G38: 0.12601748 | H38: =F38/(1-G38) -> 1.4289146 | I38: 0.55022557 | J38: 0.61956739 | K38: NA | L38: 0.96728429 | M38: 1.0486644 | N38: 0.56 | O38: 0.81971087 | P38: =AVERAGE('Industry Averages'!$H38,'Industry Averages'!$L38:$O38) -> #REF!
A39: Electrical Equipment | B39: 110 | C39: 1.5896687 | D39: 0.22517897 | E39: 0.044688548 | F39: =IF($F$8="Effective",C39/(1+(1-E39)*D39),C39/(1+(1-$F$9)*D39)) -> 1.3599881 | G39: 0.050721749 | H39: =F39/(1-G39) -> 1.4326549 | I39: 0.59440288 | J39: 0.58554859 | K39: 0.13952392 | L39: 1.1823979 | M39: 1.3071189 | N39: 1 | O39: 1.1943273 | P39: =AVERAGE('Industry Averages'!$H39,'Industry Averages'!$L39:$O39) -> #REF!
A40: Beverage (Alcoholic) | B40: 23 | C40: 1.0129742 | D40: 0.22909688 | E40: 0.093937842 | F40: =IF($F$8="Effective",C40/(1+(1-E40)*D40),C40/(1+(1-$F$9)*D40)) -> 0.86444329 | G40: 0.018550559 | H40: =F40/(1-G40) -> 0.88078229 | I40: 0.58705826 | J40: 0.49874676 | K40: 0.3379956 | L40: 1.0479649 | M40: 0.91888256 | N40: 0.67 | O40: 0.72052481 | P40: =AVERAGE('Industry Averages'!$H40,'Industry Averages'!$L40:$O40) -> #REF!
A41: Healthcare Support Services | B41: 131 | C41: 1.1603653 | D41: 0.23605438 | E41: 0.067422783 | F41: =IF($F$8="Effective",C41/(1+(1-E41)*D41),C41/(1+(1-$F$9)*D41)) -> 0.98583268 | G41: 0.080849129 | H41: =F41/(1-G41) -> 1.0725472 | I41: 0.5635984 | J41: 0.47792508 | K41: 0.27585815 | L41: 1.0266507 | M41: 0.94623821 | N41: 0.74 | O41: 0.94984695 | P41: =AVERAGE('Industry Averages'!$H41,'Industry Averages'!$L41:$O41) -> #REF!
A42: Tobacco | B42: 15 | C42: 2.0004565 | D42: 0.24055401 | E42: 0.098330509 | F42: =IF($F$8="Effective",C42/(1+(1-E42)*D42),C42/(1+(1-$F$9)*D42)) -> 1.6947054 | G42: 0.028404797 | H42: =F42/(1-G42) -> 1.7442505 | I42: 0.60634882 | J42: 0.44059236 | K42: 0.076952135 | L42: 1.1252644 | M42: 1.4263226 | N42: 0.61 | O42: 0.86224908 | P42: =AVERAGE('Industry Averages'!$H42,'Industry Averages'!$L42:$O42) -> #REF!
A43: Environmental & Waste Services | B43: 62 | C43: 1.0153454 | D43: 0.25536486 | E43: 0.054211006 | F43: =IF($F$8="Effective",C43/(1+(1-E43)*D43),C43/(1+(1-$F$9)*D43)) -> 0.85214038 | G43: 0.0081137078 | H43: =F43/(1-G43) -> 0.85911095 | I43: 0.61566157 | J43: 0.48087347 | K43: 0.13314927 | L43: 0.9601752 | M43: 1.0485101 | N43: 0.82 | O43: 1.086183 | P43: =AVERAGE('Industry Averages'!$H43,'Industry Averages'!$L43:$O43) -> #REF!
A44: Aerospace/Defense | B44: 77 | C44: 1.4141823 | D44: 0.26057121 | E44: 0.086027664 | F44: =IF($F$8="Effective",C44/(1+(1-E44)*D44),C44/(1+(1-$F$9)*D44)) -> 1.182992 | G44: 0.037667224 | H44: =F44/(1-G44) -> 1.2292962 | I44: 0.47207386 | J44: 0.37555545 | K44: 0.19186739 | L44: 1.092226 | M44: 1.0785222 | N44: 0.91 | O44: 1.1104127 | P44: =AVERAGE('Industry Averages'!$H44,'Industry Averages'!$L44:$O44) -> #REF!
A45: Total Market (without financials) | B45: 5649 | C45: 1.292817 | D45: 0.26398868 | E45: 0.06384678 | F45: =IF($F$8="Effective",C45/(1+(1-E45)*D45),C45/(1+(1-$F$9)*D45)) -> 1.0791537 | G45: 0.03751669 | H45: =F45/(1-G45) -> 1.1212181 | I45: 0.55752138 | J45: 0.47976813 | K45: 0.1850361 | L45: 0.99855895 | M45: 1.0124817 | N45: 0.86 | O45: 1.0402068 | P45: =AVERAGE('Industry Averages'!$H45,'Industry Averages'!$L45:$O45) -> #REF!
A46: Chemical (Specialty) | B46: 76 | C46: 1.2772947 | D46: 0.27404332 | E46: 0.10749765 | F46: =IF($F$8="Effective",C46/(1+(1-E46)*D46),C46/(1+(1-$F$9)*D46)) -> 1.0595274 | G46: 0.049966819 | H46: =F46/(1-G46) -> 1.115253 | I46: 0.48818196 | J46: 0.42320469 | K46: 0.11590456 | L46: 0.98902379 | M46: 0.96485709 | N46: 0.82 | O46: 0.99772295 | P46: =AVERAGE('Industry Averages'!$H46,'Industry Averages'!$L46:$O46) -> #REF!
A47: Transportation (Railroads) | B47: 4 | C47: 1.1078309 | D47: 0.27451205 | E47: 0.1656796 | F47: =IF($F$8="Effective",C47/(1+(1-E47)*D47),C47/(1+(1-$F$9)*D47)) -> 0.91868772 | G47: 0.014686917 | H47: =F47/(1-G47) -> 0.93238153 | I47: 0.22719139 | J47: 0.16341269 | K47: 0.11810856 | L47: 2.0801518 | M47: 1.8919832 | N47: 0.74 | O47: 0.64760822 | P47: =AVERAGE('Industry Averages'!$H47,'Industry Averages'!$L47:$O47) -> #REF!
A48: Business & Consumer Services | B48: 164 | C48: 1.17092 | D48: 0.27473813 | E48: 0.094263091 | F48: =IF($F$8="Effective",C48/(1+(1-E48)*D48),C48/(1+(1-$F$9)*D48)) -> 0.97086897 | G48: 0.048045201 | H48: =F48/(1-G48) -> 1.0198688 | I48: 0.53842314 | J48: 0.45782494 | K48: 0.18885582 | L48: 1.0001911 | M48: 0.89488662 | N48: 0.83 | O48: 0.98611315 | P48: =AVERAGE('Industry Averages'!$H48,'Industry Averages'!$L48:$O48) -> #REF!
A49: Steel | B49: 28 | C49: 1.3424844 | D49: 0.28595103 | E49: 0.14954163 | F49: =IF($F$8="Effective",C49/(1+(1-E49)*D49),C49/(1+(1-$F$9)*D49)) -> 1.1054137 | G49: 0.088354279 | H49: =F49/(1-G49) -> 1.2125475 | I49: 0.39412505 | J49: 0.38298957 | K49: 1.0458573 | L49: 1.2948714 | M49: 1.2855689 | N49: 0.78 | O49: 0.982557 | P49: =AVERAGE('Industry Averages'!$H49,'Industry Averages'!$L49:$O49) -> #REF!
A50: Food Processing | B50: 92 | C50: 0.91752023 | D50: 0.2885787 | E50: 0.077369309 | F50: =IF($F$8="Effective",C50/(1+(1-E50)*D50),C50/(1+(1-$F$9)*D50)) -> 0.75427044 | G50: 0.018736494 | H50: =F50/(1-G50) -> 0.76867268 | I50: 0.48660887 | J50: 0.34228783 | K50: 0.16971272 | L50: 0.61142199 | M50: 0.69680825 | N50: 0.53 | O50: 0.63241385 | P50: =AVERAGE('Industry Averages'!$H50,'Industry Averages'!$L50:$O50) -> #REF!
... A103: Brokerage & Investment Banking | B103: 30 | C103: 1.2048083 | D103: 2.0108832 | E103: 0.15316532 | F103: =IF($F$8="Effective",C103/(1+(1-E103)*D103),C103/(1+(1-$F$9)*D103)) -> 0.48035498 | G103: 0.30759698 | H103: =F103/(1-G103) -> 0.69375056 | I103: 0.35452868 | J103: 0.27996249 | K103: 0.37879797 | L103: 0.45767102 | M103: 0.56767432 | N103: 0.57 | O103: 0.67007031 | P103: =AVERAGE('Industry Averages'!$H103,'Industry Averages'!$L103:$O103) -> #REF!
A104: Bank (Money Center) | B104: 7 | C104: 1.0801016 | D104: 2.1638477 | E104: 0.16253159 | F104: =IF($F$8="Effective",C104/(1+(1-E104)*D104),C104/(1+(1-$F$9)*D104)) -> 0.41179894 | G104: 0.44301926 | H104: =F104/(1-G104) -> 0.73934143 | I104: 0.22354726 | J104: 0.19594323 | K104: NA | L104: 0.42823345 | M104: 0.55954147 | N104: 0.59 | O104: 1.0325147 | P104: =AVERAGE('Industry Averages'!$H104,'Industry Averages'!$L104:$O104) -> #REF!
A105: Rubber& Tires | B105: 3 | C105: 0.83801498 | D105: 3.3033396 | E105: 0 | F105: =IF($F$8="Effective",C105/(1+(1-E105)*D105),C105/(1+(1-$F$9)*D105)) -> 0.2409817 | G105: 0.099691022 | H105: =F105/(1-G105) -> 0.26766555 | I105: 0.45026186 | J105: 0.39785998 | K105: 0.50671999 | L105: 0.23902988 | M105: 0.45318133 | N105: 0.54 | O105: 0.58921294 | P105: =AVERAGE('Industry Averages'!$H105,'Industry Averages'!$L105:$O105) -> #REF!
A106: Financial Svcs. (Non-bank & Insurance) | B106: 223 | C106: 0.88572507 | D106: 10.043963 | E106: 0.14608586 | F106: =IF($F$8="Effective",C106/(1+(1-E106)*D106),C106/(1+(1-$F$9)*D106)) -> 0.1038003 | G106: 0.022363595 | H106: =F106/(1-G106) -> 0.10617475 | I106: 0.3378425 | J106: 0.27145307 | K106: 0.61670379 | L106: 0.075615335 | M106: 0.098263138 | N106: 0.11 | O106: 0.15175875 | P106: =AVERAGE('Industry Averages'!$H106,'Industry Averages'!$L106:$O106) -> #REF!

Sheet Beneish M Score Calculator
B3: Beneish M Score Calculator
B5: Company Name | C5: IEP
B7: (in millions) | D7: 2 | E7: =D7-1 -> 1
B8: Revenue | D8: 14101000000 | E8: 11338000000
B9: Cost of Goods Sold | D9: 11689000000 | E9: 9485000000
B10: Selling, General, & Admin. Expense | D10: 1250000000 | E10: 1238000000 | F10: found on statement of operation
B11: Depreciation | D11: 509000000 | E11: 517000000 | F11: cash flows statement
B12: Net Income from Continuing Operations | D12: 10073 | E12: 3033
B13: Accounts Receivables | D13: 16677 | E13: 13164
B14: Current Assets | D14: 75101 | E14: 60197
B15: Property, Plants, & Equipment | D15: 61797 | E15: 48866
B16: Securities 1 | D16: 942 | E16: 737
B17: Total Assets | D17: 162648 | E17: 131310
B18: Current Liabilities | D18: 68391 | E18: 57883
B19: Total Long-term Debt | D19: 23495 | E19: 24743
B20: Cash Flow from Operations | D20: 30723 | E20: 18365
B21: Securities is also referred to as total long term investments
B23: Financial Ratios Indexes | D23: =D7 -> 2 | E23: =E7 -> 1 | F23: Index
B24: Day Sales in Receivables Index (DSRI) | D24: =D13/D8*365 -> 0.00043167896 | E24: =E13/E8*365 -> 0.00042378374 | F24: =D24/E24 -> 1.0186303
B25: Gross Margin Index (GMI) | D25: =(D8-D9)/D8 -> 0.1710517 | E25: =(E8-E9)/E8 -> 0.1634327 | F25: =E25/D25 -> 0.95545794
B26: Asset Quality Index (AQI) | D26: =(1-(D14+D15+D16))/D17 -> -0.84746815 | E26: =(1-(E14+E15+E16))/E17 -> -0.83618156 | F26: =D26/E26 -> 1.0134978
B27: Sales Growth Index (SGI) | D27: =D8 -> 14101000000 | E27: =E8 -> 11338000000 | F27: =D27/E27 -> 1.2436938
B28: Depreciation Index (DEPI) | D28: =D11/(D15+D11) -> 0.99987861 | E28: =E11/(E15+E11) -> 0.99990549 | F28: =E28/D28 -> 1.0000269
B29: Selling, General, & Admin. Expenses Index (SGAI) | D29: =D10/D8 -> 0.088646195 | E29: =E10/E8 -> 0.10919033 | F29: =D29/E29 -> 0.81185021
B30: Leverage Index (LVGI) | D30: =(D18+D19)/D17 -> 0.56493778 | E30: =(E18+E19)/E17 -> 0.62924377 | F30: =D30/E30 -> 0.89780432
B31: Total Accruals to Total Assets (TATA) | D31: =(D12-D20)/D17 -> -0.12696129 | F31: =D31 -> -0.12696129
B32: Beneish M Score | F32: =-4.84+0.92*F24+0.528*F25+0.404*F26+0.892*F27+0.115*F28-0.172*F29+4.679*F31-0.327*F30 -> -2.7918194
B34: Interpretation
B35: =IF(F32>-2.22,C5&" is likely to have manipulated their earnings.",C5&" is not likely to have manipulated their earnings.") -> IEP is not likely to have manipulated their earnings.
B36: Beneish M Score < -2.22: Company is not likely to have manipulated their earnings
B37: Beneish M Score > -2.22: Company is likely to have manipulated their earnings

Sheet EO
A1: order_# | B1: citation | C1: document_number | D1: end_page | E1: html_url | F1: pdf_url | G1: publication_date | H1: signing_date | I1: start_page | J1: title | K1: disposition_notes
A2: 13116 | B2: 64 FR 16333 | C2: 99-8433 | D2: 16335 | E2: https://www.federalregister.gov/documents/1999/04/05/99-8433/identification-of-trade-expansion-priorities-and-discriminatory-procurement-practices | F2: https://www.govinfo.gov/content/pkg/FR-1999-04-05/pdf/99-8433.pdf | G2: 36255 | H2: 36250 | I2: 16333 | J2: Identification of Trade Expansion Priorities and Discriminatory Procurement Practices
A3: 13117 | B3: 64 FR 16591 | C3: 99-8509 | D3: 16591 | E3: https://www.federalregister.gov/documents/1999/04/05/99-8509/further-amendment-to-executive-order-12981-as-amended | F3: https://www.govinfo.gov/content/pkg/FR-1999-04-05/pdf/99-8509.pdf | G3: 36255 | H3: 36250 | I3: 16591 | J3: Further Amendment to Executive Order 12981, as Amended | K3: Amends: EO 12981, December 5, 1995 Note: This Executive order amends the administration of export controls
A4: 13118 | B4: 64 FR 16595 | C4: 99-8547 | D4: 16599 | E4: https://www.federalregister.gov/documents/1999/04/05/99-8547/implementation-of-the-foreign-affairs-reform-and-restructuring-act-of-1998 | F4: https://www.govinfo.gov/content/pkg/FR-1999-04-05/pdf/99-8547.pdf | G4: 36255 | H4: 36250 | I4: 16595 | J4: Implementation of the Foreign Affairs Reform and Restructuring Act of 1998 | K4: Amends: EO 11223 of May 12, 1965; EO 11269 of February 14, 1966; EO 11958 of January 18, 1977; EO 12163 of September 29, 1979; EO 12188 of January 2, 1980; EO 12260 of December 31, 1980; EO 12293 of February 23, 1981; EO 12301 of March 26, 1981; EO 12703 of February 20, 1990; EO 12884 of December 1, 1993; Memorandum of March 23, 1999;; ; Revokes: EO 12599 of June 23, 1987
A5: 13119 | B5: 64 FR 18797 | C5: 99-9738 | D5: 18797 | E5: https://www.federalregister.gov/documents/1999/04/16/99-9738/designation-of-federal-republic-of-yugoslavia-serbiamontenegro-albania-the-airspace-above-and | F5: https://www.govinfo.gov/content/pkg/FR-1999-04-16/pdf/99-9738.pdf | G5: 36266 | H5: 36263 | I5: 18797 | J5: Designation of Federal Republic of Yugoslavia (Serbia/Montenegro), Albania, the Airspace Above, and Adjacent Waters as a Combat Zone
A6: 13120 | B6: 64 FR 23007 | C6: 99-10901 | D6: 23007 | E6: https://www.federalregister.gov/documents/1999/04/29/99-10901/ordering-the-selected-reserve-and-certain-individual-ready-reserve-members-of-the-armed-forces-to | F6: https://www.govinfo.gov/content/pkg/FR-1999-04-29/pdf/99-10901.pdf | G6: 36279 | H6: 36277 | I6: 23007 | J6: Ordering the Selected Reserve and Certain Individual Ready Reserve Members of the Armed Forces to Active Duty | K6: Amended by: EO 13286, February 28, 2003
A7: 13121 | B7: 64 FR 24021 | C7: 99-11410 | D7: 24022 | E7: https://www.federalregister.gov/documents/1999/05/05/99-11410/blocking-property-of-the-governments-of-the-federal-republic-of-yugoslavia-serbia-and-montenegro-the | F7: https://www.govinfo.gov/content/pkg/FR-1999-05-05/pdf/99-11410.pdf | G7: 36285 | H7: 36280 | I7: 24021 | J7: Blocking Property of the Governments of the Federal Republic of Yugoslavia (Serbia and Montenegro), the Republic of Serbia, and the Republic of Montenegro, and Prohibiting Trade Transactions Involving the Federal Republic of Yugoslavia (Serbia and Montenegro) in Response to the Situation in Kosovo | K7: Amends: EO 13088, June 9, 1998 See: Notice of May 25, 2000; EO 13192, January 17, 2001; Notice of May 24, 2001 Revoked by: EO 13304, May 28, 2003
A8: 13122 | B8: 64 FR 29201 | C8: 99-13825 | D8: 29202 | E8: https://www.federalregister.gov/documents/1999/05/28/99-13825/interagency-task-force-on-the-economic-development-of-the-southwest-border | F8: https://www.govinfo.gov/content/pkg/FR-1999-05-28/pdf/99-13825.pdf | G8: 36308 | H8: 36305 | I8: 29201 | J8: Interagency Task Force on the Economic Development of the Southwest Border | K8: Amended by: EO 13284, January 23, 2003
A9: 13123 | B9: 64 FR 30851 | C9: 99-14633 | D9: 30860 | E9: https://www.federalregister.gov/documents/1999/06/08/99-14633/greening-the-government-through-efficient-energy-management | F9: https://www.govinfo.gov/content/pkg/FR-1999-06-08/pdf/99-14633.pdf | G9: 36319 | H9: 36314 | I9: 30851 | J9: Greening the Government Through Efficient Energy Management | K9: Revokes: EO 12759, April 17, 1991; EO 12845, April 21, 1993; EO 12902, March 9, 1994 Revoked by: EO 13423, January 24, 2007 See: EO 13148, April 21, 2000
A10: 13124 | B10: 64 FR 31103 | C10: 99-14825 | D10: 31104 | E10: https://www.federalregister.gov/documents/1999/06/09/99-14825/amending-the-civil-service-rules-relating-to-federal-employees-with-psychiatric-disabilities | F10: https://www.govinfo.gov/content/pkg/FR-1999-06-09/pdf/99-14825.pdf | G10: 36320 | H10: 36315 | I10: 31103 | J10: Amending the Civil Service Rules Relating To Federal Employees With Psychiatric Disabilities
A11: 13125 | B11: 64 FR 31105 | C11: 99-14901 | D11: 31107 | E11: https://www.federalregister.gov/documents/1999/06/10/99-14901/increasing-participation-of-asian-americans-and-pacific-islanders-in-federal-programs | F11: https://www.govinfo.gov/content/pkg/FR-1999-06-10/pdf/99-14901.pdf | G11: 36321 | H11: 36318 | I11: 31105 | J11: Increasing Participation of Asian Americans and Pacific Islanders in Federal Programs | K11: Amended by: EO 13216, June 6, 2001 Superseded by: EO 13515, October 14, 2009; EO 14031, May 28, 2021
A12: 13126 | B12: 64 FR 32383 | C12: 99-15491 | D12: 32385 | E12: https://www.federalregister.gov/documents/1999/06/16/99-15491/prohibition-of-acquisition-of-products-produced-by-forced-or-indentured-child-labor | F12: https://www.govinfo.gov/content/pkg/FR-1999-06-16/pdf/99-15491.pdf | G12: 36327 | H12: 36323 | I12: 32383 | J12: Prohibition of Acquisition of Products Produced by Forced or Indentured Child Labor
A13: 13127 | B13: 64 FR 32793 | C13: 99-15623 | D13: 32793 | E13: https://www.federalregister.gov/documents/1999/06/17/99-15623/amendment-to-executive-order-13073-year-2000-conversion | F13: https://www.govinfo.gov/content/pkg/FR-1999-06-17/pdf/99-15623.pdf | G13: 36328 | H13: 36325 | I13: 32793 | J13: Amendment to Executive Order 13073, Year 2000 Conversion | K13: Amends: EO 13073, February 4, 1998
A14: 13128 | B14: 64 FR 34703 | C14: 99-16634 | D14: 34704 | E14: https://www.federalregister.gov/documents/1999/06/28/99-16634/implementation-of-the-chemical-weapons-convention-and-the-chemical-weapons-convention-implementation | F14: https://www.govinfo.gov/content/pkg/FR-1999-06-28/pdf/99-16634.pdf | G14: 36339 | H14: 36336 | I14: 34703 | J14: Implementation of the Chemical Weapons Convention and the Chemical Weapons Convention Implementation Act | K14: Amends: EO 12938, November 14, 1994
A15: 13129 | B15: 64 FR 36759 | C15: 99-17444 | D15: 36761 | E15: https://www.federalregister.gov/documents/1999/07/07/99-17444/blocking-property-and-prohibiting-transactions-with-the-taliban | F15: https://www.govinfo.gov/content/pkg/FR-1999-07-07/pdf/99-17444.pdf | G15: 36348 | H15: 36345 | I15: 36759 | J15: Blocking Property and Prohibiting Transactions With the Taliban | K15: See: EO 13268, July 2, 2002
A16: 13130 | B16: 64 FR 38535 | C16: 99-18476 | D16: 38536 | E16: https://www.federalregister.gov/documents/1999/07/19/99-18476/national-infrastructure-assurance-council | F16: https://www.govinfo.gov/content/pkg/FR-1999-07-19/pdf/99-18476.pdf | G16: 36360 | H16: 36355 | I16: 38535 | J16: National Infrastructure Assurance Council | K16: Revoked by: EO 13231, October 16, 2001 See: EO 13010, July 15, 1996; EO 13286, February 28, 2003
A17: 13131 | B17: 64 FR 40733 | C17: 99-19396 | D17: 40734 | E17: https://www.federalregister.gov/documents/1999/07/27/99-19396/further-amendments-to-executive-order-12757-implementation-of-the-enterprise-for-the-americas | F17: https://www.govinfo.gov/content/pkg/FR-1999-07-27/pdf/99-19396.pdf | G17: 36368 | H17: 36363 | I17: 40733 | J17: Further Amendments to Executive Order 12757, Implementation of the Enterprise for the Americas Initiative | K17: Amends: EO 12757, March 19, 1991 See: EO 12823, December 3, 1992; EO 13028, December 3, 1996 Revoked by: EO 13345, July 8, 2004
A18: 13132 | B18: 64 FR 43255 | C18: 99-20729 | D18: 43259 | E18: https://www.federalregister.gov/documents/1999/08/10/99-20729/federalism | F18: https://www.govinfo.gov/content/pkg/FR-1999-08-10/pdf/99-20729.pdf | G18: 36382 | H18: 36376 | I18: 43255 | J18: Federalism | K18: Revokes: EO 12612, October 26, 1987; EO 12875, October 26, 1993; EO 13083, May 14, 1998; EO 13095, August 5, 1998;; Supplements: EO 12372, July 14, 1982; EO 12866, September 30, 1993; EO 12988, February 5, 1996 See: EO 13175, November 6, 2000
A19: 13133 | B19: 64 FR 43895 | C19: 99-20924 | D19: 43896 | E19: https://www.federalregister.gov/documents/1999/08/11/99-20924/working-group-on-unlawful-conduct-on-the-internet | F19: https://www.govinfo.gov/content/pkg/FR-1999-08-11/pdf/99-20924.pdf | G19: 36383 | H19: 36377 | I19: 43895 | J19: Working Group on Unlawful Conduct on the Internet | K19: Amended by: EO 13286, February 28, 2003
A20: 13134 | B20: 64 FR 44639 | C20: 99-21392 | D20: 44642 | E20: https://www.federalregister.gov/documents/1999/08/16/99-21392/developing-and-promoting-biobased-products-and-bioenergy | F20: https://www.govinfo.gov/content/pkg/FR-1999-08-16/pdf/99-21392.pdf | G20: 36388 | H20: 36384 | I20: 44639 | J20: Developing and Promoting Biobased Products and Bioenergy | K20: Revoked by: EO 13225, September 28, 2001 (in part); EO 13423, January 24, 2007 See: EO 13148, April 21, 2000
A21: 13135 | B21: 64 FR 47339 | C21: 99-22778 | D21: 47339 | E21: https://www.federalregister.gov/documents/1999/08/31/99-22778/amendment-to-executive-order-12216-presidents-committee-on-the-international-labor-organization | F21: https://www.govinfo.gov/content/pkg/FR-1999-08-31/pdf/99-22778.pdf | G21: 36403 | H21: 36399 | I21: 47339 | J21: Amendment to Executive Order 12216, President's Committee on the International Labor Organization | K21: Amends: EO 12216, June 18, 1980
A22: 13136 | B22: 64 FR 48931 | C22: 99-23508 | D22: 48931 | E22: https://www.federalregister.gov/documents/1999/09/08/99-23508/amendment-to-executive-order-13090-presidents-commission-on-the-celebration-of-women-in-american | F22: https://www.govinfo.gov/content/pkg/FR-1999-09-08/pdf/99-23508.pdf | G22: 36411 | H22: 36406 | I22: 48931 | J22: Amendment to Executive Order 13090, President's Commission on the Celebration of Women in American History | K22: Amends: EO 13090, June 29, 1998
A23: 13137 | B23: 64 FR 50733 | C23: 99-24582 | D23: 50733 | E23: https://www.federalregister.gov/documents/1999/09/20/99-24582/amendment-to-executive-order-12975-as-amended-national-bioethics-advisory-commission | F23: https://www.govinfo.gov/content/pkg/FR-1999-09-20/pdf/99-24582.pdf | G23: 36423 | H23: 36418 | I23: 50733 | J23: Amendment to Executive Order 12975, as Amended, National Bioethics Advisory Commission | K23: Amends: EO 12975, October 3, 1995 See: EO 13316, September 17, 2003
A24: 13138 | B24: 64 FR 53879 | C24: 99-25958 | D24: 53881 | E24: https://www.federalregister.gov/documents/1999/10/04/99-25958/continuance-of-certain-federal-advisory-committees | F24: https://www.govinfo.gov/content/pkg/FR-1999-10-04/pdf/99-25958.pdf | G24: 36437 | H24: 36433 | I24: 53879 | J24: Continuance of Certain Federal Advisory Committees | K24: Amends: EO 12131, May 4, 1979; EO 12345, February 2, 1982; EO 12367, June 15, 1982; EO 13115, March 25, 1999 Supersedes: EO 13062, September 29, 1997 (in part) Revokes: EO 12852, June 29, 1993; EO 12961, May 26, 1995; EO 13010, July 15, 1996, (in part); EO 13017, September 5, 1996; EO 13037, March 3, 1997; EO 13038, March 11, 1997; EO 13050, June 13, 1997 Superseded by: EO 13225, September 28, 2001 (in part) Revoked by: EO 13226, September 30, 2001 (in part)
... A26: 13140 | B26: 64 FR 55115 | C26: 99-26670 | D26: 55123 | E26: https://www.federalregister.gov/documents/1999/10/12/99-26670/1999-amendments-to-the-manual-for-courts-martial-united-states | F26: https://www.govinfo.gov/content/pkg/FR-1999-10-12/pdf/99-26670.pdf | G26: 36445 | H26: 36439 | I26: 55115 | J26: 1999 Amendments to the Manual for Courts-Martial, United States | K26: Amends: EO 12473, April 13, 1984 See: EO 12484, July 13, 1984; EO 12550, February 19, 1986; EO 12586, March 3, 1987; EO 12708, March 23, 1990; EO 12767, June 27, 1991; EO 12888, December 23, 1993; EO 12936, November 10, 1994; EO 12960, May 12, 1995; EO 13086, May 27, 1998
A27: 13141 | B27: 64 FR 63169 | C27: 99-30346 | D27: 63170 | E27: https://www.federalregister.gov/documents/1999/11/18/99-30346/environmental-review-of-trade-agreements | F27: https://www.govinfo.gov/content/pkg/FR-1999-11-18/pdf/99-30346.pdf | G27: 36482 | H27: 36480 | I27: 63169 | J27: Environmental Review of Trade Agreements
A28: 13142 | B28: 64 FR 66089 | C28: 99-30687 | D28: 66090 | E28: https://www.federalregister.gov/documents/1999/11/23/99-30687/amendment-to-executive-order-12958-classified-national-security-information | F28: https://www.govinfo.gov/content/pkg/FR-1999-11-23/pdf/99-30687.pdf | G28: 36487 | H28: 36483 | I28: 66089 | J28: Amendment To Executive Order 12958-Classified National Security Information | K28: Amends: EO 12958, April 17, 1995
A29: 13143 | B29: 64 FR 68273 | C29: 99-31748 | D29: 68273 | E29: https://www.federalregister.gov/documents/1999/12/06/99-31748/amending-executive-order-10173-as-amended-prescribing-regulations-relating-to-the-safeguarding-of | F29: https://www.govinfo.gov/content/pkg/FR-1999-12-06/pdf/99-31748.pdf | G29: 36500 | H29: 36495 | I29: 68273 | J29: Amending Executive Order 10173, as Amended, Prescribing Regulations Relating to the Safeguarding of Vessels, Harbors, Ports, and Waterfront Facilities of the United States | K29: Amends: EO 10173, October 18, 1950
A30: 13144 | B30: 64 FR 72237 | C30: 99-33511 | D30: 72247 | E30: https://www.federalregister.gov/documents/1999/12/23/99-33511/adjustments-of-certain-rates-of-pay | F30: https://www.govinfo.gov/content/pkg/FR-1999-12-23/pdf/99-33511.pdf | G30: 36517 | H30: 36515 | I30: 72237 | J30: Adjustments of Certain Rates of Pay | K30: Supersedes: EO 13106, December 7, 1998 (in part) Superseded by: EO 13182, December 23, 2000
A31: 13145 | B31: 65 FR 6877 | C31: 00-3331 | D31: 6880 | E31: https://www.federalregister.gov/documents/2000/02/10/00-3331/to-prohibit-discrimination-in-federal-employment-based-on-genetic-information | F31: https://www.govinfo.gov/content/pkg/FR-2000-02-10/pdf/00-3331.pdf | G31: 36566 | H31: 36564 | I31: 6877 | J31: To Prohibit Discrimination in Federal Employment Based on Genetic Information
A32: 13146 | B32: 65 FR 11201 | C32: 00-5209 | D32: 11202 | E32: https://www.federalregister.gov/documents/2000/03/02/00-5209/presidents-council-on-the-future-of-princeville-north-carolina | F32: https://www.govinfo.gov/content/pkg/FR-2000-03-02/pdf/00-5209.pdf | G32: 36587 | H32: 36585 | I32: 11201 | J32: President's Council on the Future of Princeville, North Carolina
A33: 13147 | B33: 65 FR 13233 | C33: 00-6126 | D33: 13234 | E33: https://www.federalregister.gov/documents/2000/03/10/00-6126/white-house-commission-on-complementary-and-alternative-medicine-policy | F33: https://www.govinfo.gov/content/pkg/FR-2000-03-10/pdf/00-6126.pdf | G33: 36595 | H33: 36592 | I33: 13233 | J33: White House Commission on Complementary and Alternative Medicine Policy | K33: Amended by: EO 13167, September 15, 2000 Revoked by: EO 13316, September 17, 2003
A34: 13148 | B34: 65 FR 24595 | C34: 00-10550 | D34: 24606 | E34: https://www.federalregister.gov/documents/2000/04/26/00-10550/greening-the-government-through-leadership-in-environmental-management | F34: https://www.govinfo.gov/content/pkg/FR-2000-04-26/pdf/00-10550.pdf | G34: 36642 | H34: 36637 | I34: 24595 | J34: Greening the Government Through Leadership in Environmental Management | K34: Revokes: EO 12088, October 13, 1978 (in part); EO 12843, April 21, 1993; EO 12856, August 3, 1993; EO 12969, August 8, 1995; Memorandum of April 26, 1994 See: EO 13101, September 14, 1998; EO 13123, June 3, 1999; EO 13134, August 12, 1999 Revoked by: EO 13423, January 24, 2007
A35: 13149 | B35: 65 FR 24607 | C35: 00-10551 | D35: 24611 | E35: https://www.federalregister.gov/documents/2000/04/26/00-10551/greening-the-government-through-federal-fleet-and-transportation-efficiency | F35: https://www.govinfo.gov/content/pkg/FR-2000-04-26/pdf/00-10551.pdf | G35: 36642 | H35: 36637 | I35: 24607 | J35: Greening the Government Through Federal Fleet and Transportation Efficiency | K35: Revokes: EO 13031, December 13, 1996 Revoked by: EO 13423, January 24, 2007 See: EO 13101, September 14, 1998; Proc. 7308, May 15, 2000 (65 FR 31783)
A36: 13150 | B36: 65 FR 24613 | C36: 00-10552 | D36: 24614 | E36: https://www.federalregister.gov/documents/2000/04/26/00-10552/federal-workforce-transportation | F36: https://www.govinfo.gov/content/pkg/FR-2000-04-26/pdf/00-10552.pdf | G36: 36642 | H36: 36637 | I36: 24613 | J36: Federal Workforce Transportation
A37: 13151 | B37: 65 FR 25619 | C37: 00-11070 | D37: 25621 | E37: https://www.federalregister.gov/documents/2000/05/02/00-11070/global-disaster-information-network | F37: https://www.govinfo.gov/content/pkg/FR-2000-05-02/pdf/00-11070.pdf | G37: 36648 | H37: 36643 | I37: 25619 | J37: Global Disaster Information Network | K37: Amended by: EO 13284, January 23, 2003
